Workbook

Sheet note
B1: correct cat
A2: 71 | B2: SC | C2: unlock | D2: PoolTemplate.sol | E2: Incorrect comparison, typo | F2: H-02 | G2: https://code4rena.com/reports/2022-01-insure/#h-02-typo-in-pooltemplate-unlock-function-results-in-user-being-able-to-unlock-multiple-times | H2: The line `insurances[_id].status == false;` seems to be a typo. It should probably be `insurances[_id].status = false;` since the current line is comparing the status to false but not actually changing it.
A3: 3 | B3: S3 | C3: registerTradeAndBorrow | D3: CrossMarginAccounts.sol | E3: Incorrect state update in registerTradeAndBorrow | F3: H-06 | G3: https://code4rena.com/reports/2021-04-marginswap/#h-06-users-are-credited-more-tokens-when-paying-back-debt-with-registertradeandborrow | H3: The registerTradeAndBorrow function does not correctly update the account's holdings and borrowed states, leading to potential inconsistencies in the smart contract's states.
A4: 54 | B4: SC | C4: _setKeyManagerOf | D4: MixinKeys.sol | E4: Duplicate entries in `owners` array | F4: L-24 | G4: https://code4rena.com/reports/2021-11-unlock/#overview | H4: The _setKeyManagerOf function emits the KeyManagerChanged event with the new key manager address always set to address(0). This does not accurately reflect the new key manager's address and can cause confusion for any off-chain listeners monitoring the event.

Sheet riskBugs
A1: ID | B1: Bug ID | C1: Bug Label | D1: Cat | E1: Difficulty | F1: File Name | G1: Valid | H1: Bug Description | I1: Reference | J1: Comment
A2: 3 | B2: H-02 | C2: SE-4 | D2: =IF(OR(LEFT(C2, 2)="SE", LEFT(C2, 2)="S4"), "C6", IF(LEFT(C2, 2)="S1", "C1", IF(OR(LEFT(C2, 2)="S2", LEFT(C2, 2)="S5"), "C3&5", IF(LEFT(C2, 2)="S3", "C4", IF(LEFT(C2, 2)="SC", "C7", IF(LEFT(C2, 2)="S6", "C2", "Other")))))) -> C6 | E2: 1 | F2: MarginRouter.sol | G2: native | H2: Missing fromToken != toToken check | I2: https://code4rena.com/reports/2021-04-marginswap#h-02-missing-fromtoken--totoken-check
A3: 3 | B3: H-03 | C3: S1-1 | D3: =IF(OR(LEFT(C3, 2)="SE", LEFT(C3, 2)="S4"), "C6", IF(LEFT(C3, 2)="S1", "C1", IF(OR(LEFT(C3, 2)="S2", LEFT(C3, 2)="S5"), "C3&5", IF(LEFT(C3, 2)="S3", "C4", IF(LEFT(C3, 2)="SC", "C7", IF(LEFT(C3, 2)="S6", "C2", "Other")))))) -> C1 | E3: 1 | F3: PriceAware.sol | G3: native | H3: Price feed can be manipulated | I3: https://code4rena.com/reports/2021-04-marginswap#h-03-price-feed-can-be-manipulated
A4: 3 | B4: H-04 | C4: S6-2 | D4: =IF(OR(LEFT(C4, 2)="SE", LEFT(C4, 2)="S4"), "C6", IF(LEFT(C4, 2)="S1", "C1", IF(OR(LEFT(C4, 2)="S2", LEFT(C4, 2)="S5"), "C3&5", IF(LEFT(C4, 2)="S3", "C4", IF(LEFT(C4, 2)="SC", "C7", IF(LEFT(C4, 2)="S6", "C2", "Other")))))) -> C2 | E4: 1 | F4: Lending.sol BaseLending.sol HourlyBondSubscriptionLending.sol | G4: native | H4: Inconsistent usage of applyInterest | I4: https://code4rena.com/reports/2021-04-marginswap#h-04-inconsistent-usage-of-applyinterest
A5: 3 | B5: H-05 | C5: S6-4 | D5: =IF(OR(LEFT(C5, 2)="SE", LEFT(C5, 2)="S4"), "C6", IF(LEFT(C5, 2)="S1", "C1", IF(OR(LEFT(C5, 2)="S2", LEFT(C5, 2)="S5"), "C3&5", IF(LEFT(C5, 2)="S3", "C4", IF(LEFT(C5, 2)="SC", "C7", IF(LEFT(C5, 2)="S6", "C2", "Other")))))) -> C2 | E5: 1 | F5: CrossMarginAccounts.sol | G5: native | H5: Wrong liquidation logic | I5: https://code4rena.com/reports/2021-04-marginswap#h-05-wrong-liquidation-logic
A6: 3 | B6: H-06 | C6: SC | D6: =IF(OR(LEFT(C6, 2)="SE", LEFT(C6, 2)="S4"), "C6", IF(LEFT(C6, 2)="S1", "C1", IF(OR(LEFT(C6, 2)="S2", LEFT(C6, 2)="S5"), "C3&5", IF(LEFT(C6, 2)="S3", "C4", IF(LEFT(C6, 2)="SC", "C7", IF(LEFT(C6, 2)="S6", "C2", "Other")))))) -> C7 | E6: 1 | F6: CrossMarginAccounts.sol CrossMarginTrading.sol | G6: native | H6: Users are credited more tokens when paying back debt with registerTradeAndBorrow | I6: https://code4rena.com/reports/2021-04-marginswap#h-06-users-are-credited-more-tokens-when-paying-back-debt-with-registertradeandborrow
A7: 3 | B7: H-07 | C7: S3-1 | D7: =IF(OR(LEFT(C7, 2)="SE", LEFT(C7, 2)="S4"), "C6", IF(LEFT(C7, 2)="S1", "C1", IF(OR(LEFT(C7, 2)="S2", LEFT(C7, 2)="S5"), "C3&5", IF(LEFT(C7, 2)="S3", "C4", IF(LEFT(C7, 2)="SC", "C7", IF(LEFT(C7, 2)="S6", "C2", "Other")))))) -> C4 | E7: 1 | F7: CrossMarginAccounts.sol | G7: native | H7: account.holdsToken is never set | I7: https://code4rena.com/reports/2021-04-marginswap#h-07-accountholdstoken-is-never-set
A8: 5 | B8: H-03 | C8: SC | D8: =IF(OR(LEFT(C8, 2)="SE", LEFT(C8, 2)="S4"), "C6", IF(LEFT(C8, 2)="S1", "C1", IF(OR(LEFT(C8, 2)="S2", LEFT(C8, 2)="S5"), "C3&5", IF(LEFT(C8, 2)="S3", "C4", IF(LEFT(C8, 2)="SC", "C7", IF(LEFT(C8, 2)="S6", "C2", "Other")))))) -> C7 | E8: 1 | F8: Vader.sol | G8: native | H8: Missing DAO functionality to call changeDAO() function in Vader.sol | I8: https://code4rena.com/reports/2021-04-vader#h-03-missing-dao-functionality-to-call-changedao-function-in-vadersol
A9: 5 | B9: H-04 | C9: SE-4 | D9: =IF(OR(LEFT(C9, 2)="SE", LEFT(C9, 2)="S4"), "C6", IF(LEFT(C9, 2)="S1", "C1", IF(OR(LEFT(C9, 2)="S2", LEFT(C9, 2)="S5"), "C3&5", IF(LEFT(C9, 2)="S3", "C4", IF(LEFT(C9, 2)="SC", "C7", IF(LEFT(C9, 2)="S6", "C2", "Other")))))) -> C6 | E9: 1 | F9: DAO.sol | G9: native | H9: Proposals can be cancelled | I9: https://code4rena.com/reports/2021-04-vader#h-04-proposals-can-be-cancelled
A10: 5 | B10: H-05 | C10: SE-2 | D10: =IF(OR(LEFT(C10, 2)="SE", LEFT(C10, 2)="S4"), "C6", IF(LEFT(C10, 2)="S1", "C1", IF(OR(LEFT(C10, 2)="S2", LEFT(C10, 2)="S5"), "C3&5", IF(LEFT(C10, 2)="S3", "C4", IF(LEFT(C10, 2)="SC", "C7", IF(LEFT(C10, 2)="S6", "C2", "Other")))))) -> C6 | E10: 3 | F10: DAO.sol | G10: native | H10: Flash loans can affect governance voting in DAO.sol | I10: https://code4rena.com/reports/2021-04-vader#h-05-flash-loans-can-affect-governance-voting-in-daosol
A11: 5 | B11: H-07 | C11: S6-4 | D11: =IF(OR(LEFT(C11, 2)="SE", LEFT(C11, 2)="S4"), "C6", IF(LEFT(C11, 2)="S1", "C1", IF(OR(LEFT(C11, 2)="S2", LEFT(C11, 2)="S5"), "C3&5", IF(LEFT(C11, 2)="S3", "C4", IF(LEFT(C11, 2)="SC", "C7", IF(LEFT(C11, 2)="S6", "C2", "Other")))))) -> C2 | E11: 1 | F11: Utils.sol | G11: native | H11: Wrong calcAsymmetricShare calculation | I11: https://code4rena.com/reports/2021-04-vader#h-07-wrong-calcasymmetricshare-calculation
A12: 5 | B12: H-08 | C12: S6-4 | D12: =IF(OR(LEFT(C12, 2)="SE", LEFT(C12, 2)="S4"), "C6", IF(LEFT(C12, 2)="S1", "C1", IF(OR(LEFT(C12, 2)="S2", LEFT(C12, 2)="S5"), "C3&5", IF(LEFT(C12, 2)="S3", "C4", IF(LEFT(C12, 2)="SC", "C7", IF(LEFT(C12, 2)="S6", "C2", "Other")))))) -> C2 | E12: 3 | F12: Utils.sol | G12: native | H12: Wrong liquidity units calculation | I12: https://code4rena.com/reports/2021-04-vader#h-08-wrong-liquidity-units-calculation
A13: 5 | B13: H-10 | C13: S5-3 | D13: =IF(OR(LEFT(C13, 2)="SE", LEFT(C13, 2)="S4"), "C6", IF(LEFT(C13, 2)="S1", "C1", IF(OR(LEFT(C13, 2)="S2", LEFT(C13, 2)="S5"), "C3&5", IF(LEFT(C13, 2)="S3", "C4", IF(LEFT(C13, 2)="SC", "C7", IF(LEFT(C13, 2)="S6", "C2", "Other")))))) -> C3&5 | E13: 1 | F13: Router.sol | G13: too long | H13: Anyone can list anchors / curate tokens | I13: https://code4rena.com/reports/2021-04-vader#h-10-anyone-can-list-anchors--curate-tokens
... A99: 35 | B99: H-12 | C99: S6-1 | D99: =IF(OR(LEFT(C99, 2)="SE", LEFT(C99, 2)="S4"), "C6", IF(LEFT(C99, 2)="S1", "C1", IF(OR(LEFT(C99, 2)="S2", LEFT(C99, 2)="S5"), "C3&5", IF(LEFT(C99, 2)="S3", "C4", IF(LEFT(C99, 2)="SC", "C7", IF(LEFT(C99, 2)="S6", "C2", "Other")))))) -> C2 | E99: 1 | F99: ConcentratedLiquidityPool.sol | G99: too long | H99: ConcentratedLiquidityPool: secondsPerLiquidity should be modified whenever pool liquidity changes | I99: https://code4rena.com/reports/2021-09-sushitrident-2#h-12-concentratedliquiditypool-secondsperliquidity-should-be-modified-whenever-pool-liquidity-changes
A100: 35 | B100: H-17 | C100: SC | D100: =IF(OR(LEFT(C100, 2)="SE", LEFT(C100, 2)="S4"), "C6", IF(LEFT(C100, 2)="S1", "C1", IF(OR(LEFT(C100, 2)="S2", LEFT(C100, 2)="S5"), "C3&5", IF(LEFT(C100, 2)="S3", "C4", IF(LEFT(C100, 2)="SC", "C7", IF(LEFT(C100, 2)="S6", "C2", "Other")))))) -> C7 | E100: 1 | F100: ConcentratedLiquidityPoolManager.sol ConcentratedLiquidityPosition.sol Ticks.sol | G100: native | H100: Understanding the fee growth mechanism (why nearestTick is unsuitable) | I100: https://code4rena.com/reports/2021-09-sushitrident-2#h-17-understanding-the-fee-growth-mechanism-why-nearesttick-is-unsuitable | J100: good learning material
A101: 36 | B101: H-02 | C101: S3-1 | D101: =IF(OR(LEFT(C101, 2)="SE", LEFT(C101, 2)="S4"), "C6", IF(LEFT(C101, 2)="S1", "C1", IF(OR(LEFT(C101, 2)="S2", LEFT(C101, 2)="S5"), "C3&5", IF(LEFT(C101, 2)="S3", "C4", IF(LEFT(C101, 2)="SC", "C7", IF(LEFT(C101, 2)="S6", "C2", "Other")))))) -> C4 | E101: 1 | F101: Basket.sol | G101: native | H101: Basket.sol#auctionBurn() A failed auction will freeze part of the funds | I101: https://code4rena.com/reports/2021-09-defiprotocol#h-02-basketsolauctionburn-a-failed-auction-will-freeze-part-of-the-funds
A102: 37 | B102: H-01 | C102: SC | D102: =IF(OR(LEFT(C102, 2)="SE", LEFT(C102, 2)="S4"), "C6", IF(LEFT(C102, 2)="S1", "C1", IF(OR(LEFT(C102, 2)="S2", LEFT(C102, 2)="S5"), "C3&5", IF(LEFT(C102, 2)="S3", "C4", IF(LEFT(C102, 2)="SC", "C7", IF(LEFT(C102, 2)="S6", "C2", "Other")))))) -> C7 | E102: 1 | F102: TempusController.sol | G102: compact | H102: Steal tokens from TempusController | I102: https://code4rena.com/reports/2021-10-tempus#h-01-steal-tokens-from-tempuscontroller
A103: 38 | B103: H-02 | C103: SC | D103: =IF(OR(LEFT(C103, 2)="SE", LEFT(C103, 2)="S4"), "C6", IF(LEFT(C103, 2)="S1", "C1", IF(OR(LEFT(C103, 2)="S2", LEFT(C103, 2)="S5"), "C3&5", IF(LEFT(C103, 2)="S3", "C4", IF(LEFT(C103, 2)="SC", "C7", IF(LEFT(C103, 2)="S6", "C2", "Other")))))) -> C7 | E103: 2 | F103: QuickAccManager.sol | G103: native | H103: QuickAccManager.sol#cancel() Wrong hashTx makes it impossible to cancel a scheduled transaction | I103: https://code4rena.com/reports/2021-10-ambire#h-02-quickaccmanagersolcancel-wrong-hashtx-makes-it-impossible-to-cancel-a-scheduled-transaction
A104: 38 | B104: H-03 | C104: S2-3 | D104: =IF(OR(LEFT(C104, 2)="SE", LEFT(C104, 2)="S4"), "C6", IF(LEFT(C104, 2)="S1", "C1", IF(OR(LEFT(C104, 2)="S2", LEFT(C104, 2)="S5"), "C3&5", IF(LEFT(C104, 2)="S3", "C4", IF(LEFT(C104, 2)="SC", "C7", IF(LEFT(C104, 2)="S6", "C2", "Other")))))) -> C3&5 | E104: 2 | F104: QuickAccManager.sol | G104: native | H104: Signature replay attacks for different identities (nonce on wrong party) | I104: https://code4rena.com/reports/2021-10-ambire#h-03-signature-replay-attacks-for-different-identities-nonce-on-wrong-party
A105: 38 | B105: H-04 | C105: SC | D105: =IF(OR(LEFT(C105, 2)="SE", LEFT(C105, 2)="S4"), "C6", IF(LEFT(C105, 2)="S1", "C1", IF(OR(LEFT(C105, 2)="S2", LEFT(C105, 2)="S5"), "C3&5", IF(LEFT(C105, 2)="S3", "C4", IF(LEFT(C105, 2)="SC", "C7", IF(LEFT(C105, 2)="S6", "C2", "Other")))))) -> C7 | E105: 1 | F105: QuickAccManager.sol | G105: native | H105: QuickAccManager Smart Contract signature verification can be exploited | I105: https://code4rena.com/reports/2021-10-ambire#h-04-quickaccmanager-smart-contract-signature-verification-can-be-exploited
A106: 39 | B106: H-02 | C106: S6-4 | D106: =IF(OR(LEFT(C106, 2)="SE", LEFT(C106, 2)="S4"), "C6", IF(LEFT(C106, 2)="S1", "C1", IF(OR(LEFT(C106, 2)="S2", LEFT(C106, 2)="S5"), "C3&5", IF(LEFT(C106, 2)="S3", "C4", IF(LEFT(C106, 2)="SC", "C7", IF(LEFT(C106, 2)="S6", "C2", "Other")))))) -> C2 | E106: 2 | F106: Swivel.sol | G106: compact | H106: Swivel: Taker is charged fees twice in exitVaultFillingVaultInitiate | I106: https://code4rena.com/reports/2021-09-swivel#h-02-swivel-taker-is-charged-fees-twice-in-exitvaultfillingvaultinitiate
A107: 39 | B107: H-03 | C107: SE-4 | D107: =IF(OR(LEFT(C107, 2)="SE", LEFT(C107, 2)="S4"), "C6", IF(LEFT(C107, 2)="S1", "C1", IF(OR(LEFT(C107, 2)="S2", LEFT(C107, 2)="S5"), "C3&5", IF(LEFT(C107, 2)="S3", "C4", IF(LEFT(C107, 2)="SC", "C7", IF(LEFT(C107, 2)="S6", "C2", "Other")))))) -> C6 | E107: 1 | F107: VaultTracker.sol | G107: native | H107: transferNotionalFrom doesn’t check from != to | I107: https://code4rena.com/reports/2021-09-swivel#h-03-transfernotionalfrom-doesnt-check-from--to
A108: 41 | B108: H-01 | C108: SC | D108: =IF(OR(LEFT(C108, 2)="SE", LEFT(C108, 2)="S4"), "C6", IF(LEFT(C108, 2)="S1", "C1", IF(OR(LEFT(C108, 2)="S2", LEFT(C108, 2)="S5"), "C3&5", IF(LEFT(C108, 2)="S3", "C4", IF(LEFT(C108, 2)="SC", "C7", IF(LEFT(C108, 2)="S6", "C2", "Other")))))) -> C7 | E108: 1 | F108: Auction.sol Basket.sol | G108: native | H108: Bonding mechanism allows malicious user to DOS auctions | I108: https://code4rena.com/reports/2021-10-defiprotocol#h-01-bonding-mechanism-allows-malicious-user-to-dos-auctions
A109: 42 | B109: H-01 | C109: S6-3 | D109: =IF(OR(LEFT(C109, 2)="SE", LEFT(C109, 2)="S4"), "C6", IF(LEFT(C109, 2)="S1", "C1", IF(OR(LEFT(C109, 2)="S2", LEFT(C109, 2)="S5"), "C3&5", IF(LEFT(C109, 2)="S3", "C4", IF(LEFT(C109, 2)="SC", "C7", IF(LEFT(C109, 2)="S6", "C2", "Other")))))) -> C2 | E109: 2 | F109: MochiVault.sol | G109: native | H109: Vault fails to track debt correctly that leads to bad debt | I109: https://code4rena.com/reports/2021-10-mochi#h-01-vault-fails-to-track-debt-correctly-that-leads-to-bad-debt
A110: 42 | B110: H-02 | C110: SC | D110: =IF(OR(LEFT(C110, 2)="SE", LEFT(C110, 2)="S4"), "C6", IF(LEFT(C110, 2)="S1", "C1", IF(OR(LEFT(C110, 2)="S2", LEFT(C110, 2)="S5"), "C3&5", IF(LEFT(C110, 2)="S3", "C4", IF(LEFT(C110, 2)="SC", "C7", IF(LEFT(C110, 2)="S6", "C2", "Other")))))) -> C7 | E110: 1 | F110: FeePoolV0.sol | G110: native | H110: FeePoolV0.sol#distributeMochi() will unexpectedly flush treasuryShare, causing the protocol fee cannot be properly accounted for and collected | I110: https://code4rena.com/reports/2021-10-mochi#h-02-feepoolv0soldistributemochi-will-unexpectedly-flush-treasuryshare-causing-the-protocol-fee-cannot-be-properly-accounted-for-and-collected
A111: 42 | B111: H-04 | C111: S2-1 | D111: =IF(OR(LEFT(C111, 2)="SE", LEFT(C111, 2)="S4"), "C6", IF(LEFT(C111, 2)="S1", "C1", IF(OR(LEFT(C111, 2)="S2", LEFT(C111, 2)="S5"), "C3&5", IF(LEFT(C111, 2)="S3", "C4", IF(LEFT(C111, 2)="SC", "C7", IF(LEFT(C111, 2)="S6", "C2", "Other")))))) -> C3&5 | E111: 3 | F111: MochiProfileV0.sol | G111: native | H111: registerAsset() can overwrite _assetClass value | I111: https://code4rena.com/reports/2021-10-mochi#h-04-registerasset-can-overwrite-_assetclass-value
A112: 42 | B112: H-05 | C112: S6-4 | D112: =IF(OR(LEFT(C112, 2)="SE", LEFT(C112, 2)="S4"), "C6", IF(LEFT(C112, 2)="S1", "C1", IF(OR(LEFT(C112, 2)="S2", LEFT(C112, 2)="S5"), "C3&5", IF(LEFT(C112, 2)="S3", "C4", IF(LEFT(C112, 2)="SC", "C7", IF(LEFT(C112, 2)="S6", "C2", "Other")))))) -> C2 | E112: 1 | F112: MochiVault.sol | G112: native | H112: debts calculation is not accurate | I112: https://code4rena.com/reports/2021-10-mochi#h-05-debts-calculation-is-not-accurate
... A167: 54 | B167: H-04 | C167: S3-1 | D167: =IF(OR(LEFT(C167, 2)="SE", LEFT(C167, 2)="S4"), "C6", IF(LEFT(C167, 2)="S1", "C1", IF(OR(LEFT(C167, 2)="S2", LEFT(C167, 2)="S5"), "C3&5", IF(LEFT(C167, 2)="S3", "C4", IF(LEFT(C167, 2)="SC", "C7", IF(LEFT(C167, 2)="S6", "C2", "Other")))))) -> C4 | E167: 1 | F167: MixinKeys.sol | G167: native | H167: Approvals not cleared after key transfer | I167: https://code4rena.com/reports/2021-11-unlock#h-04-approvals-not-cleared-after-key-transfer
A168: 55 | B168: H-01 | C168: S5-3 | D168: =IF(OR(LEFT(C168, 2)="SE", LEFT(C168, 2)="S4"), "C6", IF(LEFT(C168, 2)="S1", "C1", IF(OR(LEFT(C168, 2)="S2", LEFT(C168, 2)="S5"), "C3&5", IF(LEFT(C168, 2)="S3", "C4", IF(LEFT(C168, 2)="SC", "C7", IF(LEFT(C168, 2)="S6", "C2", "Other")))))) -> C3&5 | E168: 1 | F168: MapleLoan.sol | G168: =#N/A -> #N/A | H168: makePayment() Lack of access control allows malicious lender to retrieve a large portion of the funds earlier, making the borrower suffer fund loss | I168: https://code4rena.com/reports/2021-12-maple#h-01-makepayment-lack-of-access-control-allows-malicious-lender-to-retrieve-a-large-portion-of-the-funds-earlier-making-the-borrower-suffer-fund-loss
A169: 56 | B169: H-02 | C169: S6-4 | D169: =IF(OR(LEFT(C169, 2)="SE", LEFT(C169, 2)="S4"), "C6", IF(LEFT(C169, 2)="S1", "C1", IF(OR(LEFT(C169, 2)="S2", LEFT(C169, 2)="S5"), "C3&5", IF(LEFT(C169, 2)="S3", "C4", IF(LEFT(C169, 2)="SC", "C7", IF(LEFT(C169, 2)="S6", "C2", "Other")))))) -> C2 | E169: 1 | F169: CDP.sol | G169: native | H169: CDP.sol update overwrites user’s credit on every positive increment | I169: https://code4rena.com/reports/2021-11-yaxis#h-02-cdpsol-update-overwrites-users-credit-on-every-positive-increment
A170: 58 | B170: H-02 | C170: S6-4 | D170: =IF(OR(LEFT(C170, 2)="SE", LEFT(C170, 2)="S4"), "C6", IF(LEFT(C170, 2)="S1", "C1", IF(OR(LEFT(C170, 2)="S2", LEFT(C170, 2)="S5"), "C3&5", IF(LEFT(C170, 2)="S3", "C4", IF(LEFT(C170, 2)="SC", "C7", IF(LEFT(C170, 2)="S6", "C2", "Other")))))) -> C2 | E170: 1 | F170: LpIssuer.sol | G170: native | H170: Wrong implementation of performanceFee can cause users to lose 50% to 100% of their funds | I170: https://code4rena.com/reports/2021-12-mellow#h-02-wrong-implementation-of-performancefee-can-cause-users-to-lose-50-to-100-of-their-funds
A171: 58 | B171: H-03 | C171: S4-1 | D171: =IF(OR(LEFT(C171, 2)="SE", LEFT(C171, 2)="S4"), "C6", IF(LEFT(C171, 2)="S1", "C1", IF(OR(LEFT(C171, 2)="S2", LEFT(C171, 2)="S5"), "C3&5", IF(LEFT(C171, 2)="S3", "C4", IF(LEFT(C171, 2)="SC", "C7", IF(LEFT(C171, 2)="S6", "C2", "Other")))))) -> C6 | E171: 1 | F171: UniV3Vault.sol | G171: native | H171: UniV3Vault.sol#collectEarnings() can be front run | I171: https://code4rena.com/reports/2021-12-mellow#h-03-univ3vaultsolcollectearnings-can-be-front-run
A172: 58 | B172: H-04 | C172: S3-1 | D172: =IF(OR(LEFT(C172, 2)="SE", LEFT(C172, 2)="S4"), "C6", IF(LEFT(C172, 2)="S1", "C1", IF(OR(LEFT(C172, 2)="S2", LEFT(C172, 2)="S5"), "C3&5", IF(LEFT(C172, 2)="S3", "C4", IF(LEFT(C172, 2)="SC", "C7", IF(LEFT(C172, 2)="S6", "C2", "Other")))))) -> C4 | E172: 2 | F172: AaveVault.sol | G172: native | H172: AaveVault does not update TVL on deposit/withdraw | I172: https://code4rena.com/reports/2021-12-mellow#h-04-aavevault-does-not-update-tvl-on-depositwithdraw
A173: 59 | B173: H-02 | C173: SC | D173: =IF(OR(LEFT(C173, 2)="SE", LEFT(C173, 2)="S4"), "C6", IF(LEFT(C173, 2)="S1", "C1", IF(OR(LEFT(C173, 2)="S2", LEFT(C173, 2)="S5"), "C3&5", IF(LEFT(C173, 2)="S3", "C4", IF(LEFT(C173, 2)="SC", "C7", IF(LEFT(C173, 2)="S6", "C2", "Other")))))) -> C7 | E173: 1 | F173: UniswapHandler.sol PoolTransferVerification.sol | G173: native | H173: Unable to remove liquidity in Recovery Mode | I173: https://code4rena.com/reports/2021-11-malt#h-02-unable-to-remove-liquidity-in-recovery-mode
A174: 59 | B174: H-04 | C174: S6-4 | D174: =IF(OR(LEFT(C174, 2)="SE", LEFT(C174, 2)="S4"), "C6", IF(LEFT(C174, 2)="S1", "C1", IF(OR(LEFT(C174, 2)="S2", LEFT(C174, 2)="S5"), "C3&5", IF(LEFT(C174, 2)="S3", "C4", IF(LEFT(C174, 2)="SC", "C7", IF(LEFT(C174, 2)="S6", "C2", "Other")))))) -> C2 | E174: 1 | F174: AuctionBurnReserveSkew.sol | G174: native | H174: AuctionBurnReserveSkew.getPegDeltaFrequency() Wrong implementation can result in an improper amount of excess Liquidity Extension balance to be used at the end of an auction | I174: https://code4rena.com/reports/2021-11-malt#h-04-auctionburnreserveskewgetpegdeltafrequency-wrong-implementation-can-result-in-an-improper-amount-of-excess-liquidity-extension-balance-to-be-used-at-the-end-of-an-auction-
A175: 59 | B175: H-05 | C175: S6-4 | D175: =IF(OR(LEFT(C175, 2)="SE", LEFT(C175, 2)="S4"), "C6", IF(LEFT(C175, 2)="S1", "C1", IF(OR(LEFT(C175, 2)="S2", LEFT(C175, 2)="S5"), "C3&5", IF(LEFT(C175, 2)="S3", "C4", IF(LEFT(C175, 2)="SC", "C7", IF(LEFT(C175, 2)="S6", "C2", "Other")))))) -> C2 | E175: 1 | F175: AuctionEscapeHatch.sol | G175: native | H175: AuctionEschapeHatch.sol#exitEarly updates state of the auction wrongly | I175: https://code4rena.com/reports/2021-11-malt#h-05-auctioneschapehatchsolexitearly-updates-state-of-the-auction-wrongly
A176: 60 | B176: H-01 | C176: S6-4 | D176: =IF(OR(LEFT(C176, 2)="SE", LEFT(C176, 2)="S4"), "C6", IF(LEFT(C176, 2)="S1", "C1", IF(OR(LEFT(C176, 2)="S2", LEFT(C176, 2)="S5"), "C3&5", IF(LEFT(C176, 2)="S3", "C4", IF(LEFT(C176, 2)="SC", "C7", IF(LEFT(C176, 2)="S6", "C2", "Other")))))) -> C2 | E176: 1 | F176: OptimisticLedger.sol | G176: native | H176: Wrong shortfall calculation | I176: https://code4rena.com/reports/2021-12-perennial#h-01-wrong-shortfall-calculation
A177: 60 | B177: H-02 | C177: SC | D177: =IF(OR(LEFT(C177, 2)="SE", LEFT(C177, 2)="S4"), "C6", IF(LEFT(C177, 2)="S1", "C1", IF(OR(LEFT(C177, 2)="S2", LEFT(C177, 2)="S5"), "C3&5", IF(LEFT(C177, 2)="S3", "C4", IF(LEFT(C177, 2)="SC", "C7", IF(LEFT(C177, 2)="S6", "C2", "Other")))))) -> C7 | E177: 1 | F177: Collateral.sol | G177: native | H177: withdrawTo Does Not Sync Before Checking A Position’s Margin Requirements | I177: https://code4rena.com/reports/2021-12-perennial#h-02-withdrawto-does-not-sync-before-checking-a-positions-margin-requirements
A178: 61 | B178: H-01 | C178: S6-4 | D178: =IF(OR(LEFT(C178, 2)="SE", LEFT(C178, 2)="S4"), "C6", IF(LEFT(C178, 2)="S1", "C1", IF(OR(LEFT(C178, 2)="S2", LEFT(C178, 2)="S5"), "C3&5", IF(LEFT(C178, 2)="S3", "C4", IF(LEFT(C178, 2)="SC", "C7", IF(LEFT(C178, 2)="S6", "C2", "Other")))))) -> C2 | E178: 1 | F178: CreditLine.sol | G178: too long | H178: In CreditLine#_borrowTokensToLiquidate, oracle is used wrong way | I178: https://code4rena.com/reports/2021-12-sublime#h-01-in-creditline_borrowtokenstoliquidate-oracle-is-used-wrong-way
A179: 61 | B179: H-02 | C179: S6-2 | D179: =IF(OR(LEFT(C179, 2)="SE", LEFT(C179, 2)="S4"), "C6", IF(LEFT(C179, 2)="S1", "C1", IF(OR(LEFT(C179, 2)="S2", LEFT(C179, 2)="S5"), "C3&5", IF(LEFT(C179, 2)="S3", "C4", IF(LEFT(C179, 2)="SC", "C7", IF(LEFT(C179, 2)="S6", "C2", "Other")))))) -> C2 | E179: 1 | F179: SavingsAccountUtil.sol | G179: native | H179: Wrong returns of SavingsAccountUtil.depositFromSavingsAccount() can cause fund loss | I179: https://code4rena.com/reports/2021-12-sublime#h-02-wrong-returns-of-savingsaccountutildepositfromsavingsaccount-can-cause-fund-loss
A180: 61 | B180: H-03 | C180: SC | D180: =IF(OR(LEFT(C180, 2)="SE", LEFT(C180, 2)="S4"), "C6", IF(LEFT(C180, 2)="S1", "C1", IF(OR(LEFT(C180, 2)="S2", LEFT(C180, 2)="S5"), "C3&5", IF(LEFT(C180, 2)="S3", "C4", IF(LEFT(C180, 2)="SC", "C7", IF(LEFT(C180, 2)="S6", "C2", "Other")))))) -> C7 | E180: 1 | F180: SavingsAccountUtil.sol | G180: native | H180: denial of service | I180: https://code4rena.com/reports/2021-12-sublime#h-03-denial-of-service
... A202: 67 | B202: H-03 | C202: S1-1 | D202: =IF(OR(LEFT(C202, 2)="SE", LEFT(C202, 2)="S4"), "C6", IF(LEFT(C202, 2)="S1", "C1", IF(OR(LEFT(C202, 2)="S2", LEFT(C202, 2)="S5"), "C3&5", IF(LEFT(C202, 2)="S3", "C4", IF(LEFT(C202, 2)="SC", "C7", IF(LEFT(C202, 2)="S6", "C2", "Other")))))) -> C1 | E202: 15 | F202: NonUSTStrategy.sol | G202: native | H202: Vaults with non-UST underlying asset vulnerable to flash loan attack on curve pool | I202: https://code4rena.com/reports/2022-01-sandclock#h-03-vaults-with-non-ust-underlying-asset-vulnerable-to-flash-loan-attack-on-curve-pool
A203: 68 | B203: H-01 | C203: S3-1 | D203: =IF(OR(LEFT(C203, 2)="SE", LEFT(C203, 2)="S4"), "C6", IF(LEFT(C203, 2)="S1", "C1", IF(OR(LEFT(C203, 2)="S2", LEFT(C203, 2)="S5"), "C3&5", IF(LEFT(C203, 2)="S3", "C4", IF(LEFT(C203, 2)="SC", "C7", IF(LEFT(C203, 2)="S6", "C2", "Other")))))) -> C4 | E203: 1 | F203: SingleTokenJoinV2.sol | G203: native | H203: Unused ERC20 tokens are not refunded, and can be stolen by attacker | I203: https://code4rena.com/reports/2021-12-amun#h-01-unused-erc20-tokens-are-not-refunded-and-can-be-stolen-by-attacker | J203: forget to refund leftover tokens, i.e., missing state updates
A204: 68 | B204: H-02 | C204: SC | D204: =IF(OR(LEFT(C204, 2)="SE", LEFT(C204, 2)="S4"), "C6", IF(LEFT(C204, 2)="S1", "C1", IF(OR(LEFT(C204, 2)="S2", LEFT(C204, 2)="S5"), "C3&5", IF(LEFT(C204, 2)="S3", "C4", IF(LEFT(C204, 2)="SC", "C7", IF(LEFT(C204, 2)="S6", "C2", "Other")))))) -> C7 | E204: 2 | F204: BasketFacet.sol | G204: native | H204: It might not be possible to withdraw tokens from the basket | I204: https://code4rena.com/reports/2021-12-amun#h-02-it-might-not-be-possible-to-withdraw-tokens-from-the-basket
A205: 69 | B205: H-03 | C205: SC | D205: =IF(OR(LEFT(C205, 2)="SE", LEFT(C205, 2)="S4"), "C6", IF(LEFT(C205, 2)="S1", "C1", IF(OR(LEFT(C205, 2)="S2", LEFT(C205, 2)="S5"), "C3&5", IF(LEFT(C205, 2)="S3", "C4", IF(LEFT(C205, 2)="SC", "C7", IF(LEFT(C205, 2)="S6", "C2", "Other")))))) -> C7 | E205: 9 | F205: NFTXMarketplaceZap.sol NFTXStakingZap.sol | G205: compact | H205: A vault can be locked from MarketplaceZap and StakingZap | I205: https://code4rena.com/reports/2021-12-nftx#h-03-a-vault-can-be-locked-from-marketplacezap-and-stakingzap
A206: 70 | B206: H-01 | C206: S4-1 | D206: =IF(OR(LEFT(C206, 2)="SE", LEFT(C206, 2)="S4"), "C6", IF(LEFT(C206, 2)="S1", "C1", IF(OR(LEFT(C206, 2)="S2", LEFT(C206, 2)="S5"), "C3&5", IF(LEFT(C206, 2)="S3", "C4", IF(LEFT(C206, 2)="SC", "C7", IF(LEFT(C206, 2)="S6", "C2", "Other")))))) -> C6 | E206: 6 | F206: VaderPoolV2.sol | G206: compact | H206: VaderPoolV2 minting synths & fungibles can be frontrun | I206: https://code4rena.com/reports/2021-12-vader#h-01-vaderpoolv2-minting-synths--fungibles-can-be-frontrun
A207: 70 | B207: H-03 | C207: S6-4 | D207: =IF(OR(LEFT(C207, 2)="SE", LEFT(C207, 2)="S4"), "C6", IF(LEFT(C207, 2)="S1", "C1", IF(OR(LEFT(C207, 2)="S2", LEFT(C207, 2)="S5"), "C3&5", IF(LEFT(C207, 2)="S3", "C4", IF(LEFT(C207, 2)="SC", "C7", IF(LEFT(C207, 2)="S6", "C2", "Other")))))) -> C2 | E207: 3 | F207: LiquidityBasedTWAP.sol | G207: compact | H207: Oracle doesn’t calculate USDV/VADER price correctly | I207: https://code4rena.com/reports/2021-12-vader#h-03-oracle-doesnt-calculate-usdvvader-price-correctly
A208: 70 | B208: H-04 | C208: S6-4 | D208: =IF(OR(LEFT(C208, 2)="SE", LEFT(C208, 2)="S4"), "C6", IF(LEFT(C208, 2)="S1", "C1", IF(OR(LEFT(C208, 2)="S2", LEFT(C208, 2)="S5"), "C3&5", IF(LEFT(C208, 2)="S3", "C4", IF(LEFT(C208, 2)="SC", "C7", IF(LEFT(C208, 2)="S6", "C2", "Other")))))) -> C2 | E208: 1 | F208: LiquidityBasedTWAP.sol | G208: compact | H208: Vader TWAP averages wrong | I208: https://code4rena.com/reports/2021-12-vader#h-04-vader-twap-averages-wrong
A209: 70 | B209: H-05 | C209: S6-4 | D209: =IF(OR(LEFT(C209, 2)="SE", LEFT(C209, 2)="S4"), "C6", IF(LEFT(C209, 2)="S1", "C1", IF(OR(LEFT(C209, 2)="S2", LEFT(C209, 2)="S5"), "C3&5", IF(LEFT(C209, 2)="S3", "C4", IF(LEFT(C209, 2)="SC", "C7", IF(LEFT(C209, 2)="S6", "C2", "Other")))))) -> C2 | E209: 1 | F209: LiquidityBasedTWAP.sol | G209: compact | H209: Oracle returns an improperly scaled USDV/VADER price | I209: https://code4rena.com/reports/2021-12-vader#h-05-oracle-returns-an-improperly-scaled-usdvvader-price
A210: 70 | B210: H-06 | C210: S1-1 | D210: =IF(OR(LEFT(C210, 2)="SE", LEFT(C210, 2)="S4"), "C6", IF(LEFT(C210, 2)="S1", "C1", IF(OR(LEFT(C210, 2)="S2", LEFT(C210, 2)="S5"), "C3&5", IF(LEFT(C210, 2)="S3", "C4", IF(LEFT(C210, 2)="SC", "C7", IF(LEFT(C210, 2)="S6", "C2", "Other")))))) -> C1 | E210: 2 | F210: USDV.sol FixedPoint.sol VaderPoolV2 | G210: native | H210: LPs of VaderPoolV2 can manipulate pool reserves to extract funds from the reserve. | I210: https://code4rena.com/reports/2021-12-vader#h-06-lps-of-vaderpoolv2-can-manipulate-pool-reserves-to-extract-funds-from-the-reserve
A211: 70 | B211: H-07 | C211: S1-1 | D211: =IF(OR(LEFT(C211, 2)="SE", LEFT(C211, 2)="S4"), "C6", IF(LEFT(C211, 2)="S1", "C1", IF(OR(LEFT(C211, 2)="S2", LEFT(C211, 2)="S5"), "C3&5", IF(LEFT(C211, 2)="S3", "C4", IF(LEFT(C211, 2)="SC", "C7", IF(LEFT(C211, 2)="S6", "C2", "Other")))))) -> C1 | E211: 2 | F211: VaderPoolV2.sol | G211: compact | H211: Redemption value of synths can be manipulated to drain VaderPoolV2 of all native assets in the associated pair | I211: https://code4rena.com/reports/2021-12-vader#h-07-redemption-value-of-synths-can-be-manipulated-to-drain-vaderpoolv2-of-all-native-assets-in-the-associated-pair
A212: 70 | B212: H-08 | C212: S6-4 | D212: =IF(OR(LEFT(C212, 2)="SE", LEFT(C212, 2)="S4"), "C6", IF(LEFT(C212, 2)="S1", "C1", IF(OR(LEFT(C212, 2)="S2", LEFT(C212, 2)="S5"), "C3&5", IF(LEFT(C212, 2)="S3", "C4", IF(LEFT(C212, 2)="SC", "C7", IF(LEFT(C212, 2)="S6", "C2", "Other")))))) -> C2 | E212: 1 | F212: VaderReserve.sol | G212: native | H212: Reserve does not properly apply prices of VADER and USDV tokens | I212: https://code4rena.com/reports/2021-12-vader#h-08-reserve-does-not-properly-apply-prices-of-vader-and-usdv-tokens
A213: 70 | B213: H-09 | C213: S6-4 | D213: =IF(OR(LEFT(C213, 2)="SE", LEFT(C213, 2)="S4"), "C6", IF(LEFT(C213, 2)="S1", "C1", IF(OR(LEFT(C213, 2)="S2", LEFT(C213, 2)="S5"), "C3&5", IF(LEFT(C213, 2)="S3", "C4", IF(LEFT(C213, 2)="SC", "C7", IF(LEFT(C213, 2)="S6", "C2", "Other")))))) -> C2 | E213: 2 | F213: USDV.sol | G213: native | H213: USDV.sol Mint and Burn Amounts Are Incorrect | I213: https://code4rena.com/reports/2021-12-vader#h-09-usdvsol-mint-and-burn-amounts-are-incorrect
A214: 70 | B214: H-10 | C214: S3-1 | D214: =IF(OR(LEFT(C214, 2)="SE", LEFT(C214, 2)="S4"), "C6", IF(LEFT(C214, 2)="S1", "C1", IF(OR(LEFT(C214, 2)="S2", LEFT(C214, 2)="S5"), "C3&5", IF(LEFT(C214, 2)="S3", "C4", IF(LEFT(C214, 2)="SC", "C7", IF(LEFT(C214, 2)="S6", "C2", "Other")))))) -> C4 | E214: 1 | F214: LiquidityBasedTWAP.sol | G214: compact | H214: previousPrices Is Never Updated Upon Syncing Token Price | I214: https://code4rena.com/reports/2021-12-vader#h-10-previousprices-is-never-updated-upon-syncing-token-price
A215: 70 | B215: H-11 | C215: SC | D215: =IF(OR(LEFT(C215, 2)="SE", LEFT(C215, 2)="S4"), "C6", IF(LEFT(C215, 2)="S1", "C1", IF(OR(LEFT(C215, 2)="S2", LEFT(C215, 2)="S5"), "C3&5", IF(LEFT(C215, 2)="S3", "C4", IF(LEFT(C215, 2)="SC", "C7", IF(LEFT(C215, 2)="S6", "C2", "Other")))))) -> C7 | E215: 1 | F215: LiquidityBasedTWAP.sol | G215: compact | H215: totalLiquidityWeight Is Updated When Adding New Token Pairs Which Skews Price Data For getVaderPrice and getUSDVPrice | I215: https://code4rena.com/reports/2021-12-vader#h-11-totalliquidityweight-is-updated-when-adding-new-token-pairs-which-skews-price-data-for-getvaderprice-and-getusdvprice
... A263: 102 | B263: H-01 | C263: S6-1 | D263: =IF(OR(LEFT(C263, 2)="SE", LEFT(C263, 2)="S4"), "C6", IF(LEFT(C263, 2)="S1", "C1", IF(OR(LEFT(C263, 2)="S2", LEFT(C263, 2)="S5"), "C3&5", IF(LEFT(C263, 2)="S3", "C4", IF(LEFT(C263, 2)="SC", "C7", IF(LEFT(C263, 2)="S6", "C2", "Other")))))) -> C2 | E263: 1 | F263: ScalingPriceOracle.sol | G263: native | H263: Oracle price does not compound | I263: https://code4rena.com/reports/2022-03-volt#h-01-oracle-price-does-not-compound
A264: 103 | B264: H-01 | C264: S2-1 | D264: =IF(OR(LEFT(C264, 2)="SE", LEFT(C264, 2)="S4"), "C6", IF(LEFT(C264, 2)="S1", "C1", IF(OR(LEFT(C264, 2)="S2", LEFT(C264, 2)="S5"), "C3&5", IF(LEFT(C264, 2)="S3", "C4", IF(LEFT(C264, 2)="SC", "C7", IF(LEFT(C264, 2)="S6", "C2", "Other")))))) -> C3&5 | E264: 5 | F264: GenericSwapFacet.sol NXTPFacet.sol CBridgeFacet.sol HopFacet.sol AnyswapFacet.sol | G264: =#N/A -> #N/A | H264: Reliance on lifiData.receivingAssetId can cause loss of funds | I264: https://code4rena.com/reports/2022-03-lifinance#h-01-reliance-on-lifidatareceivingassetid-can-cause-loss-of-funds
A265: 103 | B265: H-02 | C265: SC | D265: =IF(OR(LEFT(C265, 2)="SE", LEFT(C265, 2)="S4"), "C6", IF(LEFT(C265, 2)="S1", "C1", IF(OR(LEFT(C265, 2)="S2", LEFT(C265, 2)="S5"), "C3&5", IF(LEFT(C265, 2)="S3", "C4", IF(LEFT(C265, 2)="SC", "C7", IF(LEFT(C265, 2)="S6", "C2", "Other")))))) -> C7 | E265: 3 | F265: LibSwap.sol GenericSwapFacet.sol | G265: native | H265: All swapping functions lack checks for returned tokens | I265: https://code4rena.com/reports/2022-03-lifinance#h-02-all-swapping-functions-lack-checks-for-returned-tokens
A266: 104 | B266: H-02 | C266: S5-3 | D266: =IF(OR(LEFT(C266, 2)="SE", LEFT(C266, 2)="S4"), "C6", IF(LEFT(C266, 2)="S1", "C1", IF(OR(LEFT(C266, 2)="S2", LEFT(C266, 2)="S5"), "C3&5", IF(LEFT(C266, 2)="S3", "C4", IF(LEFT(C266, 2)="SC", "C7", IF(LEFT(C266, 2)="S6", "C2", "Other")))))) -> C3&5 | E266: 10 | F266: Splitter.sol | G266: native | H266: Splitter: Anyone can call incrementWindow to steal the tokens in the contract | I266: https://code4rena.com/reports/2022-03-joyn#h-02-splitter-anyone-can-call-incrementwindow-to-steal-the-tokens-in-the-contract
A267: 104 | B267: H-04 | C267: S5-3 | D267: =IF(OR(LEFT(C267, 2)="SE", LEFT(C267, 2)="S4"), "C6", IF(LEFT(C267, 2)="S1", "C1", IF(OR(LEFT(C267, 2)="S2", LEFT(C267, 2)="S5"), "C3&5", IF(LEFT(C267, 2)="S3", "C4", IF(LEFT(C267, 2)="SC", "C7", IF(LEFT(C267, 2)="S6", "C2", "Other")))))) -> C3&5 | E267: 12 | F267: CoreCollection.sol | G267: native | H267: CoreCollection can be reinitialized | I267: https://code4rena.com/reports/2022-03-joyn#h-04-corecollection-can-be-reinitialized
A268: 105 | B268: H-02 | C268: SE-1 | D268: =IF(OR(LEFT(C268, 2)="SE", LEFT(C268, 2)="S4"), "C6", IF(LEFT(C268, 2)="S1", "C1", IF(OR(LEFT(C268, 2)="S2", LEFT(C268, 2)="S5"), "C3&5", IF(LEFT(C268, 2)="S3", "C4", IF(LEFT(C268, 2)="SC", "C7", IF(LEFT(C268, 2)="S6", "C2", "Other")))))) -> C6 | E268: 1 | F268: Too long | G268: too long | H268: System could be wrapped and made useless without contract whitelisting | I268: https://code4rena.com/reports/2022-03-paladin#h-02-system-could-be-wrapped-and-made-useless-without-contract-whitelisting
A269: 107 | B269: H-02 | C269: S2-1 | D269: =IF(OR(LEFT(C269, 2)="SE", LEFT(C269, 2)="S4"), "C6", IF(LEFT(C269, 2)="S1", "C1", IF(OR(LEFT(C269, 2)="S2", LEFT(C269, 2)="S5"), "C3&5", IF(LEFT(C269, 2)="S3", "C4", IF(LEFT(C269, 2)="SC", "C7", IF(LEFT(C269, 2)="S6", "C2", "Other")))))) -> C3&5 | E269: 8 | F269: NFTVault.sol JPEGLock.sol | G269: too long | H269: Existing user’s locked JPEG could be overwritten by new user, causing permanent loss of JPEG funds | I269: https://code4rena.com/reports/2022-04-jpegd#h-02-existing-users-locked-jpeg-could-be-overwritten-by-new-user-causing-permanent-loss-of-jpeg-funds
A270: 107 | B270: H-09 | C270: SC | D270: =IF(OR(LEFT(C270, 2)="SE", LEFT(C270, 2)="S4"), "C6", IF(LEFT(C270, 2)="S1", "C1", IF(OR(LEFT(C270, 2)="S2", LEFT(C270, 2)="S5"), "C3&5", IF(LEFT(C270, 2)="S3", "C4", IF(LEFT(C270, 2)="SC", "C7", IF(LEFT(C270, 2)="S6", "C2", "Other")))))) -> C7 | E270: 1 | F270: NFTVault.sol | G270: too long | H270: Bad debts should not continue to accrue interest | I270: https://code4rena.com/reports/2022-04-jpegd#h-09-bad-debts-should-not-continue-to-accrue-interest
A271: 109 | B271: H-01 | C271: SC | D271: =IF(OR(LEFT(C271, 2)="SE", LEFT(C271, 2)="S4"), "C6", IF(LEFT(C271, 2)="S1", "C1", IF(OR(LEFT(C271, 2)="S2", LEFT(C271, 2)="S5"), "C3&5", IF(LEFT(C271, 2)="S3", "C4", IF(LEFT(C271, 2)="SC", "C7", IF(LEFT(C271, 2)="S6", "C2", "Other")))))) -> C7 | E271: 2 | F271: AxelarGateway.sol | G271: compact | H271: Cross-chain smart contract calls can revert but source chain tokens remain burnt and are not refunded | I271: https://code4rena.com/reports/2022-04-axelar#h-01-cross-chain-smart-contract-calls-can-revert-but-source-chain-tokens-remain-burnt-and-are-not-refunded
A272: 110 | B272: H-01 | C272: S6-2 | D272: =IF(OR(LEFT(C272, 2)="SE", LEFT(C272, 2)="S4"), "C6", IF(LEFT(C272, 2)="S1", "C1", IF(OR(LEFT(C272, 2)="S2", LEFT(C272, 2)="S5"), "C3&5", IF(LEFT(C272, 2)="S3", "C4", IF(LEFT(C272, 2)="SC", "C7", IF(LEFT(C272, 2)="S6", "C2", "Other")))))) -> C2 | E272: 11 | F272: StakedCitadel.sol | G272: compact | H272: StakedCitadel doesn’t use correct balance for internal accounting | I272: https://code4rena.com/reports/2022-04-badger-citadel#h-01-stakedcitadel-doesnt-use-correct-balance-for-internal-accounting
A273: 112 | B273: H-01 | C273: S6-1 | D273: =IF(OR(LEFT(C273, 2)="SE", LEFT(C273, 2)="S4"), "C6", IF(LEFT(C273, 2)="S1", "C1", IF(OR(LEFT(C273, 2)="S2", LEFT(C273, 2)="S5"), "C3&5", IF(LEFT(C273, 2)="S3", "C4", IF(LEFT(C273, 2)="SC", "C7", IF(LEFT(C273, 2)="S6", "C2", "Other")))))) -> C2 | E273: 2 | F273: StakerVault.sol | G273: native | H273: User can steal all rewards due to checkpoint after transfer | I273: https://code4rena.com/reports/2022-04-backd#h-01-user-can-steal-all-rewards-due-to-checkpoint-after-transfer
A274: 112 | B274: H-02 | C274: S3-1 | D274: =IF(OR(LEFT(C274, 2)="SE", LEFT(C274, 2)="S4"), "C6", IF(LEFT(C274, 2)="S1", "C1", IF(OR(LEFT(C274, 2)="S2", LEFT(C274, 2)="S5"), "C3&5", IF(LEFT(C274, 2)="S3", "C4", IF(LEFT(C274, 2)="SC", "C7", IF(LEFT(C274, 2)="S6", "C2", "Other")))))) -> C4 | E274: 1 | F274: StakerVault.sol | G274: native | H274: function lockFunds in TopUpActionLibrary can cause serious fund lose. fee and Capped bypass. It’s not calling stakerVault.increaseActionLockedBalance when transfers stakes. | I274: https://code4rena.com/reports/2022-04-backd#h-02-function-lockfunds-in-topupactionlibrary-can-cause-serious-fund-lose-fee-and-capped-bypass-its-not-calling-stakervaultincreaseactionlockedbalance-when-transfers-stakes
A275: 113 | B275: H-01 | C275: SC | D275: =IF(OR(LEFT(C275, 2)="SE", LEFT(C275, 2)="S4"), "C6", IF(LEFT(C275, 2)="S1", "C1", IF(OR(LEFT(C275, 2)="S2", LEFT(C275, 2)="S5"), "C3&5", IF(LEFT(C275, 2)="S3", "C4", IF(LEFT(C275, 2)="SC", "C7", IF(LEFT(C275, 2)="S6", "C2", "Other")))))) -> C7 | E275: 3 | F275: NFTPair.sol NFTPairWithOracle.sol | G275: too long | H275: Avoidance of Liquidation Via Malicious Oracle | I275: https://code4rena.com/reports/2022-04-abranft#h-01-avoidance-of-liquidation-via-malicious-oracle
A276: 113 | B276: H-02 | C276: SE-2 | D276: =IF(OR(LEFT(C276, 2)="SE", LEFT(C276, 2)="S4"), "C6", IF(LEFT(C276, 2)="S1", "C1", IF(OR(LEFT(C276, 2)="S2", LEFT(C276, 2)="S5"), "C3&5", IF(LEFT(C276, 2)="S3", "C4", IF(LEFT(C276, 2)="SC", "C7", IF(LEFT(C276, 2)="S6", "C2", "Other")))))) -> C6 | E276: 10 | F276: NFTPairWithOracle.sol | G276: too long | H276: The return value success of the get function of the INFTOracle interface is not checked | I276: https://code4rena.com/reports/2022-04-abranft#h-02-the-return-value-success-of-the-get-function-of-the-inftoracle-interface-is-not-checked
... A301: 193 | B301: H-02 | C301: S1-2 | D301: =IF(OR(LEFT(C301, 2)="SE", LEFT(C301, 2)="S4"), "C6", IF(LEFT(C301, 2)="S1", "C1", IF(OR(LEFT(C301, 2)="S2", LEFT(C301, 2)="S5"), "C3&5", IF(LEFT(C301, 2)="S3", "C4", IF(LEFT(C301, 2)="SC", "C7", IF(LEFT(C301, 2)="S6", "C2", "Other")))))) -> C1 | E301: 28 | F301: Pair.sol | G301: compact | H301: Liquidity providers may lose funds when adding liquidity | I301: https://code4rena.com/reports/2022-12-caviar#h-02-liquidity-providers-may-lose-funds-when-adding-liquidity

Sheet stkbar
B1: C1 | C1: C2 | D1: C3&5 | E1: C4 | F1: C6 | G1: C7 | H1: Total
A2: Code4rena | B2: 24 | C2: 63 | D2: 34 | E2: 21 | F2: 46 | G2: 58 | H2: =SUM(B2:G2) -> 246
A3: uniq | B3: 63 | C3: 148 | D3: 76 | E3: 46 | F3: 192 | G3: 105 | H3: =SUM(B3:G3) -> 630
A4: TP | B4: 26 | C4: 67 | D4: 60 | E4: 22 | F4: 116 | G4: 76 | H4: =SUM(B4:G4) -> 367
A5: report | B5: 13 | C5: 12 | D5: 16 | E5: 9 | F5: 11 | G5: 7 | H5: =SUM(B5:G5) -> 68
A6: high | B6: 8 | C6: 5 | D6: 9 | E6: 7 | F6: 5 | G6: 2 | H6: =SUM(B6:G6) -> 36
A7: high% | B7: =B6/B2 -> 0.33333333 | C7: =C6/C2 -> 0.079365079 | D7: =D6/D2 -> 0.26470588 | E7: =E6/E2 -> 0.33333333 | F7: =F6/F2 -> 0.10869565 | G7: =G6/G2 -> 0.034482759 | H7: =H6/H2 -> 0.14634146
C14: high in report | D14: non-high in report | E14: true not in report | F14: false alarm | G14: total
A15: C1
B16: Code4rena | C16: 24 | G16: =SUM(C16:F16) -> 24
B17: GPT_alarms | C17: 8 | D17: =B5-C17 -> 5 | E17: =B4-B5 -> 13 | F17: =B3-B4 -> 37 | G17: =SUM(C17:F17) -> 63
A19: C2
B20: Code4rena | C20: 63 | G20: =SUM(C20:F20) -> 63
B21: GPT_alarms | C21: 5 | D21: =C5-C21 -> 7 | E21: =C4-C5 -> 55 | F21: =C3-C4 -> 81 | G21: =SUM(C21:F21) -> 148
A23: C3&5
B24: Code4rena | C24: 34 | G24: =SUM(C24:F24) -> 34
B25: GPT_alarms | C25: 9 | D25: =D5-C25 -> 7 | E25: =D4-D5 -> 44 | F25: =D3-D4 -> 16 | G25: =SUM(C25:F25) -> 76
A27: C4
B28: Code4rena | C28: 21 | G28: =SUM(C28:F28) -> 21
B29: GPT_alarms | C29: 7 | D29: =E5-C29 -> 2 | E29: =E4-E5 -> 13 | F29: =E3-E4 -> 24 | G29: =SUM(C29:F29) -> 46
A31: C6
B32: Code4rena | C32: 46 | G32: =SUM(C32:F32) -> 46
B33: GPT_alarms | C33: 5 | D33: =F5-C33 -> 6 | E33: =F4-F5 -> 105 | F33: =F3-F4 -> 76 | G33: =SUM(C33:F33) -> 192
A35: C7
B36: Code4rena | C36: 58 | G36: =SUM(C36:F36) -> 58
B37: GPT_alarms | C37: 2 | D37: =G5-C37 -> 5 | E37: =G4-G5 -> 69 | F37: =G3-G4 -> 29 | G37: =SUM(C37:F37) -> 105
A39: placeholder

Sheet c1raw
A1: OriProj | B1: Proj | C1: Test | D1: Seq | E1: Functions | F1: Explanation
A2: 3_1 | B2: 3 | C2: 1 | D2: 1 | E2: getPriceFromAMM | F2: In this smart contract, the getPriceFromAMM function is responsible for fetching the price of a token from the AMM (Automated Market Maker). While the contract does have some mechanisms in place to prevent price manipulation, the getPriceFromAMM function can still be susceptible to manipulation. The reason being that it relies on the external data provided by the AMM, which can be subject to manipulation through methods like sandwich attacks or flash loans. An attacker could temporarily manipulate the prices on the AMM and influence the token prices fetched by the getPriceFromAMM function.
A3: 3_1 | B3: 3 | C3: 1 | D3: 2 | E3: getCurrentPriceInPeg | F3: The getCurrentPriceInPeg function is responsible for determining the current price of a token in the peg. This function relies on the prices fetched by the getPriceFromAMM function, which, as mentioned earlier, can be manipulated. Therefore, any manipulation in getPriceFromAMM can also affect the getCurrentPriceInPeg function. This can potentially lead to incorrect price estimations and impact the entire smart contract's functionality.
A4: 3_2 | B4: 3 | C4: 2 | D4: 1 | E4: getPriceFromAMM | F4: The getPriceFromAMM function fetches the price of a token from an external AMM (Automated Market Maker) and updates the stored price of the token. The prices fetched from external AMMs can be manipulated if a malicious actor has a substantial influence on the liquidity of the token. This could lead to incorrect price updates, affecting the smart contract's behavior.
A5: 3_2 | B5: 3 | C5: 2 | D5: 2 | E5: getCurrentPriceInPeg | F5: The getCurrentPriceInPeg function retrieves the current price of the token in the pegged currency. The price is fetched by calling the getPriceFromAMM function, which is susceptible to price manipulation as explained above. If the price of the token is manipulated in the AMM, it will affect the price returned by this function as well.
A6: 3_2 | B6: 3 | C6: 2 | D6: 3 | E6: viewCurrentPriceInPeg | F6: The viewCurrentPriceInPeg function is a view function that returns the current price of a token in the pegged currency. It calculates the price by using data fetched from external AMMs through UniswapStyleLib.getAmountsOut, which can be manipulated if a malicious actor has a significant influence on the liquidity of the token. This can lead to incorrect price estimations, impacting the contract's behavior.
A7: 3_3 | B7: 3 | C7: 3 | D7: 1 | E7: getPriceFromAMM | F7: The function getPriceFromAMM retrieves the price from the AMM, but it has some potential for price manipulation. The contract checks if the output amount is within a predefined range (UPDATE_MIN_PEG_AMOUNT and UPDATE_MAX_PEG_AMOUNT) before updating the token price. An attacker could manipulate the price in the AMM by placing large orders to force the output amount outside of the predefined range, causing the contract to not update the price. This manipulation could lead to incorrect pricing data being used in the smart contract.
A8: 3_3 | B8: 3 | C8: 3 | D8: 2 | E8: setLiquidationPath | F8: The function setLiquidationPath sets the liquidation path from a given token to the current liquidation peg. The path and tokens are provided externally and not verified within the contract, which may leave the contract vulnerable to price manipulation. An attacker could provide a custom path that includes a manipulated token price in the AMM or even a malicious AMM contract. This could lead to incorrect pricing data being used in the smart contract, impacting the liquidation process and other contract functions that rely on accurate pricing information.
A9: 16_1 | B9: 16 | C9: 1 | D9: 1 | E9: recordTrade | F9: The function 'recordTrade' updates pricing information and uses the external oracle's latest answer through 'uint256 currentOraclePrice = oracle.latestAnswer();'. This exposes the contract to potential price oracle manipulation. An attacker could manipulate the oracle's data, thus influencing the pricing information in the smart contract, which could lead to incorrect funding rates and other consequences.
A10: 16_1 | B10: 16 | C10: 1 | D10: 2 | E10: fairPrice | F10: The 'fairPrice' function returns the fair price by using the external oracle's latest answer through 'oracle.latestAnswer()'. This exposes the contract to potential price oracle manipulation. An attacker could manipulate the oracle's data, which would lead to an incorrect fair price being returned, possibly affecting the decision-making process of the smart contract's users.
A11: 16_2 | B11: 16 | C11: 2 | D11: 1 | E11: recordTrade | F11: In the `recordTrade` function, the `tradePrice` is used to update the hourly tracer prices. Since the `tradePrice` is not directly fetched from the oracle but passed as a function argument, it may be manipulated by an attacker to influence the hourly prices.
A12: 16_2 | B12: 16 | C12: 2 | D12: 2 | E12: updatePrice | F12: The `updatePrice` function is called in the `recordTrade` function, and it also takes `marketPrice` and `oraclePrice` as input arguments. Since these arguments are passed down from the `recordTrade` function, they might be manipulated by an attacker to influence the hourly prices and eventually affect the funding rate and time value.
A13: 16_2 | B13: 16 | C13: 2 | D13: 3 | E13: fairPrice | F13: The `fairPrice` function directly uses the `oracle.latestAnswer()` to calculate the fair price. If an attacker can manipulate the oracle's latest answer, it can result in an incorrect fair price. This can be mitigated by using a secure oracle implementation, but it's crucial to be aware of the possibility of oracle manipulation affecting the smart contract.
... A134: 193_3 | B134: 193 | C134: 3 | D134: 1 | E134: price | F134: The price function calculates the price of the fractional tokens based on the reserves of the base token and the fractional tokens. It is defined as: (_baseTokenReserves() * ONE) / fractionalTokenReserves(). Since the contract allows users to add and remove liquidity, buy, and sell tokens, they can influence the reserves of the base and fractional tokens. Consequently, users can manipulate the price by influencing the reserves through these functions.

Sheet c1Uniq
A1: Proj | B1: Functions | C1: Certainty | D1: comments | E1: Note | F1: Link | G1: GPT Expla
A2: 3 | B2: getPriceFromAMM | C2: =COUNTIFS(c1raw!B:B, A2, c1raw!$E:$E, B2) -> 3 | D2: M-08 | E2: low risk | F2: https://code4rena.com/reports/2021-04-marginswap/#m-08-priceaware-uses-prices-from-getamountsout | G2: In this smart contract, the getPriceFromAMM function is responsible for fetching the price of a token from the AMM (Automated Market Maker). While the contract does have some mechanisms in place to prevent price manipulation, the getPriceFromAMM function can still be susceptible to manipulation. The reason being that it relies on the external data provided by the AMM, which can be subject to manipulation through methods like sandwich attacks or flash loans. An attacker could temporarily manipulate the prices on the AMM and influence the token prices fetched by the getPriceFromAMM function.
A3: 3 | B3: getCurrentPriceInPeg | C3: =COUNTIFS(c1raw!B:B, A3, c1raw!$E:$E, B3) -> 2 | D3: H-03 | E3: high risk | F3: https://code4rena.com/reports/2021-04-marginswap/#h-03-price-feed-can-be-manipulated | G3: The getCurrentPriceInPeg function is responsible for determining the current price of a token in the peg. This function relies on the prices fetched by the getPriceFromAMM function, which, as mentioned earlier, can be manipulated. Therefore, any manipulation in getPriceFromAMM can also affect the getCurrentPriceInPeg function. This can potentially lead to incorrect price estimations and impact the entire smart contract's functionality.
A4: 3 | B4: setLiquidationPath | C4: =COUNTIFS(c1raw!B:B, A4, c1raw!$E:$E, B4) -> 1 | D4: M-02 | E4: low risk | F4: https://code4rena.com/reports/2021-04-marginswap/#m-02-missing-checks-if-pairs-equal-tokens | G4: The function setLiquidationPath sets the liquidation path from a given token to the current liquidation peg. The path and tokens are provided externally and not verified within the contract, which may leave the contract vulnerable to price manipulation. An attacker could provide a custom path that includes a manipulated token price in the AMM or even a malicious AMM contract. This could lead to incorrect pricing data being used in the smart contract, impacting the liquidation process and other contract functions that rely on accurate pricing information.
A5: 3 | B5: viewCurrentPriceInPeg | C5: =COUNTIFS(c1raw!B:B, A5, c1raw!$E:$E, B5) -> 1 | D5: =TRUE() -> 1 | E5: very low risk | F5: external data | G5: The viewCurrentPriceInPeg function is a view function that returns the current price of a token in the pegged currency. It calculates the price by using data fetched from external AMMs through UniswapStyleLib.getAmountsOut, which can be manipulated if a malicious actor has a significant influence on the liquidity of the token. This can lead to incorrect price estimations, impacting the contract's behavior.
A6: 16 | B6: recordTrade | C6: =COUNTIFS(c1raw!B:B, A6, c1raw!$E:$E, B6) -> 3 | D6: H-01 | E6: high risk | F6: https://code4rena.com/reports/2021-06-tracer/#h-01-wrong-trading-pricing-calculations | G6: The function 'recordTrade' updates pricing information and uses the external oracle's latest answer through 'uint256 currentOraclePrice = oracle.latestAnswer();'. This exposes the contract to potential price oracle manipulation. An attacker could manipulate the oracle's data, thus influencing the pricing information in the smart contract, which could lead to incorrect funding rates and other consequences.
A7: 16 | B7: fairPrice | C7: =COUNTIFS(c1raw!B:B, A7, c1raw!$E:$E, B7) -> 2 | D7: H-01 | E7: high risk, affected by above | F7: https://code4rena.com/reports/2021-06-tracer/#h-02-wrong-trading-pricing-calculations | G7: The 'fairPrice' function returns the fair price by using the external oracle's latest answer through 'oracle.latestAnswer()'. This exposes the contract to potential price oracle manipulation. An attacker could manipulate the oracle's data, which would lead to an incorrect fair price being returned, possibly affecting the decision-making process of the smart contract's users.
A8: 16 | B8: updatePrice | C8: =COUNTIFS(c1raw!B:B, A8, c1raw!$E:$E, B8) -> 1 | D8: H-01 | E8: high risk, affected by above | F8: https://code4rena.com/reports/2021-06-tracer/#h-03-wrong-trading-pricing-calculations | G8: The `updatePrice` function is called in the `recordTrade` function, and it also takes `marketPrice` and `oraclePrice` as input arguments. Since these arguments are passed down from the `recordTrade` function, they might be manipulated by an attacker to influence the hourly prices and eventually affect the funding rate and time value.
A9: 16 | B9: get24HourPrices | C9: =COUNTIFS(c1raw!B:B, A9, c1raw!$E:$E, B9) -> 1 | D9: H-01 | E9: high risk, affected by above | F9: https://code4rena.com/reports/2021-06-tracer/#h-02-wrong-trading-pricing-calculations | G9: The `get24HourPrices` function calculates the average 24-hour price for both the tracer and oracle prices. If an attacker is able to manipulate the input prices in the `recordTrade` and `updatePrice` functions, they can influence the 24-hour average prices returned by this function. This would eventually impact the time value calculation and other functions that rely on the 24-hour average prices.
A10: 16 | B10: getHourlyAvgTracerPrice | C10: =COUNTIFS(c1raw!B:B, A10, c1raw!$E:$E, B10) -> 1 | D10: H-01 | E10: high risk, affected by above | F10: https://code4rena.com/reports/2021-06-tracer/#h-02-wrong-trading-pricing-calculations | G10: The `getHourlyAvgTracerPrice` function calculates the hourly average price for a given tracer market. Since this function relies on the hourly tracer prices, which can be manipulated through the `recordTrade` and `updatePrice` functions, an attacker could influence the hourly average price for a tracer market.
A11: 16 | B11: getHourlyAvgOraclePrice | C11: =COUNTIFS(c1raw!B:B, A11, c1raw!$E:$E, B11) -> 1 | D11: H-01 | E11: high risk, affected by above | F11: https://code4rena.com/reports/2021-06-tracer/#h-02-wrong-trading-pricing-calculations | G11: The `getHourlyAvgOraclePrice` function calculates the hourly average price for a given oracle market. This function relies on the hourly oracle prices, which can be manipulated through the `recordTrade` and `updatePrice` functions. An attacker could influence the hourly average price for an oracle market, affecting the overall price calculation and funding rates.
A12: 20 | B12: mintSynth | C12: =COUNTIFS(c1raw!B:B, A12, c1raw!$E:$E, B12) -> 3 | D12: H-09 | E12: high risk | F12: https://code4rena.com/reports/2021-07-spartan/#h-09-arbitrary-synth-mintburn-from-pool | G12: The mintSynth function allows a pool to mint new synthetic tokens based on the amount of LP tokens added. However, there is no validation on the price oracles used to determine the value of the underlying assets. An attacker could manipulate the oracle to create an inaccurate price, allowing them to mint more synthetic tokens than they should be able to. This would result in an imbalanced pool and potential losses for other participants.
A13: 20 | B13: realise | C13: =COUNTIFS(c1raw!B:B, A13, c1raw!$E:$E, B13) -> 3 | D13: H-05 | E13: high risk | F13: https://code4rena.com/reports/2021-07-spartan/#h-05-synth-realise-is-vulnerable-to-flash-loan-attacks | G13: The realise function is designed to burn excess LP tokens when their value outweighs the value of the synthetic token supply. The function relies on external price data to calculate the value of LP tokens and synthetic tokens. If an attacker manipulates the oracle, they could cause the function to burn more or less LP tokens than necessary, leading to imbalances in the pool and potential losses for other participants.
A14: 20 | B14: harvestSingle | C14: =COUNTIFS(c1raw!B:B, A14, c1raw!$E:$E, B14) -> 3 | D14: M-08 | E14: low risk | F14: https://code4rena.com/reports/2021-07-spartan/#m-08-synthvault-deposit-lockup-bypass | G14: The smart contract fetches external data such as prices through the iUTILS contract. The iUTILS contract calculates prices based on the liquidity pools in the DAO, which are external to the SynthVault contract. The calcCurrentReward and calcReward functions, which are used by the harvestSingle function, rely on these external prices to calculate rewards for the user. If an attacker can manipulate the prices in the liquidity pools, they could potentially manipulate the rewards distribution, causing incorrect reward payouts. This could lead to the exploitation of the SynthVault contract and have an impact on the price of various tokens in the system.
A15: 20 | B15: calcSpotValueInBaseWithPool | C15: =COUNTIFS(c1raw!B:B, A15, c1raw!$E:$E, B15) -> 3 | D15: =TRUE() -> 1 | E15: very low risk | F15: external data | G15: The function calcSpotValueInBaseWithPool calculates the value of an amount in the base token, given a pool. However, it relies on data fetched from external contracts (iPOOL(pool).baseAmount() and iPOOL(pool).tokenAmount()), which can be manipulated by malicious actors, potentially impacting the calculated spot value in the base token.
A16: 20 | B16: calcSpotValueInTokenWithPool | C16: =COUNTIFS(c1raw!B:B, A16, c1raw!$E:$E, B16) -> 3 | D16: =TRUE() -> 1 | E16: very low risk | F16: external data | G16: Similar to calcSpotValueInBaseWithPool, calcSpotValueInTokenWithPool calculates the value of an amount in a token given a pool, and it also relies on the same external data (iPOOL(pool).baseAmount() and iPOOL(pool).tokenAmount()). As a result, this function is also susceptible to price manipulation.
A17: 20 | B17: burnSynth | C17: =COUNTIFS(c1raw!B:B, A17, c1raw!$E:$E, B17) -> 2 | D17: L-11 | E17: low risk | F17: https://code4rena.com/reports/2021-07-spartan/#l-11-inconsistent-value-of-burnsynth-between-pool-and-synth | G17: The burnSynth function allows users to burn synthetic tokens and receive LP tokens in return. Similar to mintSynth, the function relies on external price data to calculate the amount of LP tokens to return. If an attacker manipulates the oracle to provide an inaccurate price, they could receive more LP tokens than they should, causing an imbalance in the pool and potential losses for other participants.
A18: 20 | B18: swapTo | C18: =COUNTIFS(c1raw!B:B, A18, c1raw!$E:$E, B18) -> 2 | D18: =TRUE() -> 1 | E18: very low risk | F18: external data | G18: The 'swapTo' function allows swapping of tokens in the contract. The external data is fetched from the '_DAO()' function that returns the DAO's address, which is used to fetch the pool factory. However, price oracle manipulation could potentially occur if an attacker manipulates the price of the tokens in the pool, leading to an incorrect valuation of the tokens being swapped, causing potential losses for the users interacting with the smart contract. This is also applicable to other functions that use '_DAO()' to fetch pool-related information such as 'addLiquidity', 'zapLiquidity', 'removeLiquidity', etc.
A19: 20 | B19: swapAssetToSynth | C19: =COUNTIFS(c1raw!B:B, A19, c1raw!$E:$E, B19) -> 2 | D19: =TRUE() -> 1 | E19: very low risk | F19: external data | G19: The 'swapAssetToSynth' function allows swapping of assets to synthetic assets. It fetches data from the '_DAO()' function to obtain the pool factory and eventually the pool. Price oracle manipulation could occur if the price of the synthetic asset is manipulated, leading to an incorrect valuation of the synthetic asset being minted, causing potential losses for the users interacting with the smart contract.
A20: 20 | B20: swapSynthToAsset | C20: =COUNTIFS(c1raw!B:B, A20, c1raw!$E:$E, B20) -> 2 | D20: =TRUE() -> 1 | E20: very low risk | F20: external data | G20: The 'swapSynthToAsset' function allows swapping of synthetic assets to other assets. It fetches data from the '_DAO()' function to obtain the pool factory and eventually the pool. Price oracle manipulation could occur if the price of the synthetic asset is manipulated, leading to an incorrect valuation of the synthetic asset being burned, causing potential losses for the users interacting with the smart contract.
A21: 20 | B21: calcSwapValueInBaseWithPool | C21: =COUNTIFS(c1raw!B:B, A21, c1raw!$E:$E, B21) -> 2 | D21: =TRUE() -> 1 | E21: very low risk | F21: external data | G21: The function calcSwapValueInBaseWithPool calculates the value of an amount after a swap in the base token, given a pool. This function uses external data fetched from iPOOL(pool).baseAmount() and iPOOL(pool).tokenAmount(). Since these external data points can be manipulated, this function is vulnerable to price manipulation.
A22: 20 | B22: calcSwapValueInTokenWithPool | C22: =COUNTIFS(c1raw!B:B, A22, c1raw!$E:$E, B22) -> 2 | D22: =TRUE() -> 1 | E22: very low risk | F22: external data | G22: The function calcSwapValueInTokenWithPool calculates the value of an amount after a swap in a token, given a pool. It also relies on external data from iPOOL(pool).baseAmount() and iPOOL(pool).tokenAmount(), which makes it susceptible to price manipulation if these data points are manipulated.
A23: 20 | B23: swap | C23: =COUNTIFS(c1raw!B:B, A23, c1raw!$E:$E, B23) -> 1 | D23: =TRUE() -> 1 | E23: very low risk | F23: external data | G23: In the swap function, external price data is fetched from the pool contracts. If an attacker can manipulate the price of tokens in these pools, they can create artificial arbitrage opportunities and exploit them, leading to incorrect token prices and potential losses for other users.
A24: 20 | B24: calcSwapOutput | C24: =COUNTIFS(c1raw!B:B, A24, c1raw!$E:$E, B24) -> 1 | D24: =FALSE() -> 0 | F24: public function with users' inputs | G24: The 'calcSwapOutput' function calculates the output of a swap based on the input amount, the token reserves, and the base reserves. The function uses the formula `y = (x * X * Y) / (x + X)^2`. An attacker can manipulate the oracle price by manipulating the reserves of the pool, i.e., changing the values of X and Y, which will affect the swap output.
A25: 20 | B25: calcSwapFee | C25: =COUNTIFS(c1raw!B:B, A25, c1raw!$E:$E, B25) -> 1 | D25: =FALSE() -> 0 | F25: public function with users' inputs | G25: The 'calcSwapFee' function calculates the swap fee based on the input amount, the token reserves, and the base reserves. The function uses the formula `y = (x * x * Y) / (x + X)^2`. Similar to the 'calcSwapOutput' function, an attacker can manipulate the oracle price by manipulating the reserves of the pool, i.e., changing the values of X and Y, which will affect the swap fee calculation.
A26: 20 | B26: buyTo | C26: =COUNTIFS(c1raw!B:B, A26, c1raw!$E:$E, B26) -> 1 | D26: =TRUE() -> 1 | E26: very low risk | F26: external data | G26: The 'buyTo' function allows a user to buy a token by transferring the BASE token. This function relies on the price provided by the Pool contract, which can be manipulated by an attacker through flash loans or providing large amounts of tokens in a single transaction. The manipulation of the price in the liquidity pools will affect the price used in the 'buyTo' function, leading to potential price manipulation.
A27: 20 | B27: sellTo | C27: =COUNTIFS(c1raw!B:B, A27, c1raw!$E:$E, B27) -> 1 | D27: =TRUE() -> 1 | E27: very low risk | F27: external data | G27: In the 'sellTo' function, users can sell their tokens in exchange for the BASE token. Similar to the 'buyTo' function, this function relies on the price provided by the Pool contract, which can be manipulated by an attacker. The price manipulation in the liquidity pools will impact the price used in the 'sellTo' function, leading to potential price manipulation.
A28: 23 | B28: getRiskAdjustedPresentValue | C28: =COUNTIFS(c1raw!B:B, A28, c1raw!$E:$E, B28) -> 1 | D28: =TRUE() -> 1 | E28: very low risk | F28: external data | G28: In the getRiskAdjustedPresentValue function, the oracle rate is used to calculate the present value of an fCash asset with risk adjustments. Since the oracle rate is fetched from an external source, manipulating the oracle rate would directly impact the calculated present value of an fCash asset in the smart contract, potentially affecting the overall valuation of the assets.
A29: 23 | B29: getLiquidityTokenValue | C29: =COUNTIFS(c1raw!B:B, A29, c1raw!$E:$E, B29) -> 2 | D29: H-10 | E29: high risk | F29: https://code4rena.com/reports/2021-08-notional/#h-10-liquidity-token-value-can-be-manipulated | G29: The getLiquidityTokenValue function calculates the asset cash claim and the present value of the fCash asset (if it exists) using the market oracle rate. As the market.oracleRate is fetched from an external source, price manipulation could occur if the oracle rate is manipulated. The manipulated oracle rate will affect the present value calculations for the fCash assets.
A30: 23 | B30: getNetCashGroupValue | C30: =COUNTIFS(c1raw!B:B, A30, c1raw!$E:$E, B30) -> 3 | D30: =TRUE() -> 1 | E30: very low risk | F30: external data | G30: The getNetCashGroupValue function calculates the present value of assets in the cash group using the oracle rate fetched from the cash group through the calculateOracleRate method. This external dependency on the oracle rate means that if the oracle rate is manipulated, the present value calculations for the assets in the cash group would be affected, resulting in potential price manipulation.
A31: 42 | B31: _shareMochi | C31: =COUNTIFS(c1raw!B:B, A31, c1raw!$E:$E, B31) -> 1 | D31: =TRUE() -> 1 | E31: very low risk | F31: external data | G31: {=INDEX(c1raw!$F:$F, MATCH(1, (c1raw!B:B=A31) * (c1raw!$E:$E=B31), 0))} -> In the _shareMochi function, the smart contract fetches external data from the Mochi token balance to distribute Mochi to vMochi Vault and veCRV Holders. Although there isn't a direct price oracle manipulation in this function, if the price oracle is manipulated in the _buyMochi function, it will affect the Mochi token balance and the amounts distributed in this function. This can lead to incorrect distribution of rewards and losses for the participants in the smart contract.
A32: 42 | B32: _buyCRV | C32: =COUNTIFS(c1raw!B:B, A32, c1raw!$E:$E, B32) -> 1 | D32: =TRUE() -> 1 | E32: very low risk | F32: external data | G32: {=INDEX(c1raw!$F:$F, MATCH(1, (c1raw!B:B=A32) * (c1raw!$E:$E=B32), 0))} -> In the _buyCRV function, the smart contract fetches external data from the Uniswap router to swap USDM for CRV tokens. Since Uniswap uses an automated market maker model, it is vulnerable to price manipulation attacks. An attacker can manipulate the price oracle by trading large volumes of tokens right before or after this function is called, which can lead to incorrect token prices and affect the outcome of the swap.
A33: 42 | B33: distributeMochi | C33: =COUNTIFS(c1raw!B:B, A33, c1raw!$E:$E, B33) -> 4 | D33: =TRUE() -> 1 | E33: very low risk | F33: external data | G33: The distributeMochi function is responsible for buying Mochi with the mochiShare, which is executed through the _buyMochi internal function. This process fetches price data from Uniswap by using the IUniswapV2Router02's swapExactTokensForTokens function. An attacker can manipulate the price of the Mochi token on Uniswap by executing a sandwich attack, for instance, by placing large buy and sell orders around the target transaction. This manipulation can lead to an incorrect price feed, which could result in the FeePoolV0 contract buying Mochi at an inflated or deflated price.
A34: 42 | B34: veCRVInitialize | C34: =COUNTIFS(c1raw!B:B, A34, c1raw!$E:$E, B34) -> 3 | D34: =TRUE() -> 1 | E34: very low risk | F34: external data | G34: The veCRVInitialize function calls the _buyCRV internal function to buy CRV tokens with veCRVShare. This function fetches price data from Uniswap by using the IUniswapV2Router02's swapExactTokensForTokens function. An attacker can manipulate the price of the CRV token on Uniswap by executing a sandwich attack, for instance, by placing large buy and sell orders around the target transaction. This manipulation can lead to an incorrect price feed, which could result in the MochiTreasuryV0 contract buying CRV at an inflated or deflated price.
A35: 42 | B35: veCRVlock | C35: =COUNTIFS(c1raw!B:B, A35, c1raw!$E:$E, B35) -> 3 | D35: =TRUE() -> 1 | E35: very low risk | F35: external data | G35: The veCRVlock function calls the _buyCRV internal function to buy CRV tokens with veCRVShare before locking them in the veCrv contract. The price manipulation mentioned in the first sequence can impact the amount of CRV tokens bought and subsequently locked. If the CRV token price is manipulated, the contract might lock an incorrect amount of tokens in the veCrv contract, leading to potentially unfair allocations for users participating in the system.
A36: 42 | B36: _buyMochi | C36: =COUNTIFS(c1raw!B:B, A36, c1raw!$E:$E, B36) -> 2 | D36: =TRUE() -> 1 | E36: very low risk | F36: external data | G36: The _buyMochi function is also susceptible to price oracle manipulation for the same reasons mentioned above for the distributeMochi function. It relies on the Uniswap V2 router to swap USDM tokens for Mochi tokens, which could be manipulated by an attacker through large trades on Uniswap. This would allow the attacker to obtain Mochi tokens at an artificially skewed price.
A37: 52 | B37: _swap | C37: =COUNTIFS(c1raw!B:B, A37, c1raw!$E:$E, B37) -> 5 | D37: =TRUE() -> 1 | E37: very low risk | F37: external data | G37: The _swap function can be potentially manipulated due to its reliance on external data fetched from the pool contract. The pool contract calculates the conversion rate between assets, and if the pool contract is manipulated or has incorrect pricing data, it would lead to inaccurate conversions and potential price manipulation. The manipulation could occur due to oracle attacks or front-running in the pool contract, which would have a cascading effect on the smart contract relying on that data.
A38: 52 | B38: calculateInGivenOut | C38: =COUNTIFS(c1raw!B:B, A38, c1raw!$E:$E, B38) -> 2 | D38: =TRUE() -> 1 | E38: very low risk | F38: external data | G38: In the calculateInGivenOut function, the contract fetches the pool reserves and calculates the amountIn based on the given amountOut and the reserve amounts. Since the reserve amounts are fetched from the external VaderPool contract, it is possible for an attacker to manipulate the prices in that external contract, thus affecting the prices and the output of the calculateInGivenOut function.
A39: 52 | B39: calculateOutGivenIn | C39: =COUNTIFS(c1raw!B:B, A39, c1raw!$E:$E, B39) -> 2 | D39: =TRUE() -> 1 | E39: very low risk | F39: external data | G39: In the calculateOutGivenIn function, the contract fetches the pool reserves and calculates the amountOut based on the given amountIn and the reserve amounts. Since the reserve amounts are fetched from the external VaderPool contract, it is possible for an attacker to manipulate the prices in that external contract, thus affecting the prices and the output of the calculateOutGivenIn function.
A40: 52 | B40: mintSynth | C40: =COUNTIFS(c1raw!B:B, A40, c1raw!$E:$E, B40) -> 2 | D40: H-01 | E40: high risk | F40: https://code4rena.com/reports/2021-11-vader/#h-01-minting-and-burning-synths-exposes-users-to-unlimited-slippage | G40: The mintSynth function mints synthetic assets based on the native asset amount deposited. The price for minting these synthetic assets is calculated using the current reserve values of native and foreign assets. However, there is no direct price oracle or external data fetched in this function. An attacker could manipulate the reserves or amounts deposited to influence the price of minted synthetic assets.
A41: 52 | B41: burnSynth | C41: =COUNTIFS(c1raw!B:B, A41, c1raw!$E:$E, B41) -> 2 | D41: H-01 | E41: high risk | F41: https://code4rena.com/reports/2021-11-vader/#h-01-minting-and-burning-synths-exposes-users-to-unlimited-slippage | G41: The burnSynth function allows burning of synthetic assets, and the redeemed amount of native asset is calculated based on the current reserve values. Similar to the mintSynth function, there is no direct price oracle or external data fetched in this function. An attacker could manipulate the reserves or amounts burned to influence the price of the redeemed native asset.
A42: 52 | B42: _addLiquidity | C42: =COUNTIFS(c1raw!B:B, A42, c1raw!$E:$E, B42) -> 1 | D42: =FALSE() -> 0 | F42: internal function, and amounts are provided by users. | G42: The _addLiquidity function calculates the amount of tokenA and tokenB to be added to the liquidity pool. Since the function does not use a price oracle to determine the relative value of tokenA and tokenB, it is susceptible to price manipulation attacks. An attacker can manipulate the prices of tokenA and tokenB externally, leading to incorrect valuations when adding liquidity.
A43: 52 | B43: mintFungible | C43: =COUNTIFS(c1raw!B:B, A43, c1raw!$E:$E, B43) -> 1 | D43: =TRUE() -> 1 | E43: very low risk | F43: together with front-running | G43: The mintFungible function mints liquidity in fungible tokens. The liquidity issued is calculated using the current reserve values of native and foreign assets. As with the previous functions, there is no direct price oracle or external data fetched in this function. An attacker could manipulate the reserves or amounts deposited to influence the liquidity minted.
A44: 52 | B44: burnFungible | C44: =COUNTIFS(c1raw!B:B, A44, c1raw!$E:$E, B44) -> 1 | D44: =TRUE() -> 1 | E44: very low risk | F44: together with front-running | G44: The burnFungible function allows burning of liquidity issued in fungible tokens, and the redeemed amounts of native and foreign assets are calculated based on the current reserve values. As with the previous functions, there is no direct price oracle or external data fetched in this function. An attacker could manipulate the reserves or amounts burned to influence the price of the redeemed assets.
A45: 67 | B45: investedAssets | C45: =COUNTIFS(c1raw!B:B, A45, c1raw!$E:$E, B45) -> 3 | D45: =TRUE() -> 1 | E45: very low risk | F45: external data | G45: In the `investedAssets()` function, the `exchangeRateOf` function is called from the `exchangeRateFeeder` contract, which is an external contract that may be potentially manipulated by bad actors to influence the exchange rate. If the exchange rate is manipulated, it would affect the calculation of `ustAssets`, which in turn affects the calculation of the total amount of underlying assets.
A46: 67 | B46: _swapUnderlyingToUst | C46: =COUNTIFS(c1raw!B:B, A46, c1raw!$E:$E, B46) -> 1 | D46: =TRUE() -> 1 | E46: very low risk | F46: external data | G46: In the `_swapUnderlyingToUst()` function, the `curvePool.exchange_underlying()` function is called to swap the underlying token to UST. As the Curve pool is an external contract, it could be potentially manipulated by bad actors, affecting the conversion rate of the underlying token to UST. This would have a direct impact on the funds that are deposited into EthAnchor.
A47: 67 | B47: _swapUstToUnderlying | C47: =COUNTIFS(c1raw!B:B, A47, c1raw!$E:$E, B47) -> 1 | D47: =TRUE() -> 1 | E47: very low risk | F47: external data | G47: Similar to the `_swapUnderlyingToUst()` function, the `_swapUstToUnderlying()` function calls `curvePool.exchange_underlying()` to swap UST back to the underlying token. Again, as the Curve pool is an external contract, bad actors could manipulate the conversion rate. This would affect the amount of the underlying token the contract receives when swapping back from UST, which in turn influences the overall balance of the strategy.
A48: 70 | B48: cumulativePrices | C48: =COUNTIFS(c1raw!B:B, A48, c1raw!$E:$E, B48) -> 3 | D48: =TRUE() -> 1 | E48: very low risk | F48: block.timestamp is used. | G48: In the cumulativePrices function, prices are calculated based on the current reserves of native and foreign assets in the pool. An attacker could manipulate the reserves by executing a large trade, affecting the price ratio between the two assets. This could lead to inaccurate price data being returned by this function.
A49: 70 | B49: mintSynth | C49: =COUNTIFS(c1raw!B:B, A49, c1raw!$E:$E, B49) -> 3 | D49: =TRUE() -> 1 | E49: very low risk | F49: Sandwich attack | G49: The mintSynth function calculates the amount of Synth to be minted based on the deposited native asset and the current reserves. An attacker could manipulate the price by executing a large trade, impacting the reserves, and consequently, the amount of Synth minted. This could lead to unintended consequences for users of the Synth token.
A50: 70 | B50: burnSynth | C50: =COUNTIFS(c1raw!B:B, A50, c1raw!$E:$E, B50) -> 3 | D50: =TRUE() -> 1 | E50: very low risk | F50: Sandwich attack | G50: In the burnSynth function, the amount of native asset to be received when burning a Synth token is calculated based on the current reserves. Similar to the previous cases, an attacker could manipulate the price by executing a large trade, impacting the reserves, and consequently, the amount of native asset received. This could lead to unfair payouts for users burning their Synth tokens.
A51: 70 | B51: mintFungible | C51: =COUNTIFS(c1raw!B:B, A51, c1raw!$E:$E, B51) -> 3 | D51: =TRUE() -> 1 | E51: very low risk | F51: Sandwich attack | G51: The mintFungible function calculates the amount of liquidity to be minted based on the deposited native and foreign assets and the current reserves. An attacker could manipulate the price by executing a large trade, impacting the reserves, and consequently, the amount of liquidity minted. This could lead to unintended consequences for users providing liquidity to the pool.
A52: 70 | B52: burnFungible | C52: =COUNTIFS(c1raw!B:B, A52, c1raw!$E:$E, B52) -> 3 | D52: =TRUE() -> 1 | E52: very low risk | F52: Sandwich attack | G52: In the burnFungible function, the amounts of native and foreign assets to be received when burning liquidity tokens are calculated based on the current reserves. An attacker could manipulate the price by executing a large trade, impacting the reserves, and consequently, the amounts of native and foreign assets received. This could lead to unfair payouts for users burning their liquidity tokens.
A53: 70 | B53: mint | C53: =COUNTIFS(c1raw!B:B, A53, c1raw!$E:$E, B53) -> 3 | D53: =TRUE() -> 1 | E53: very low risk | F53: external data | G53: In the mint function, the price of VADER (vPrice) is fetched from the lbt contract using the getVaderPrice() function. If the price oracle in the lbt contract is manipulated, the number of USDV tokens minted could be inflated or deflated based on the manipulated VADER price.
A54: 70 | B54: burn | C54: =COUNTIFS(c1raw!B:B, A54, c1raw!$E:$E, B54) -> 3 | D54: =TRUE() -> 1 | E54: very low risk | F54: external data | G54: In the burn function, the price of USDV (uPrice) is fetched from the lbt contract using the getUSDVPrice() function. If the price oracle in the lbt contract is manipulated, the number of VADER tokens received in return for burning USDV tokens could be inflated or deflated based on the manipulated USDV price.
A55: 78 | B55: purchasePyroFlan | C55: =COUNTIFS(c1raw!B:B, A55, c1raw!$E:$E, B55) -> 3 | D55: H-05 | E55: high risk | F55: https://code4rena.com/reports/2022-01-behodler/#h-05-flash-loan-price-manipulation-in-purchasepyroflan | G55: The function `purchasePyroFlan` in the given smart contract is prone to price manipulation, particularly due to the way it calculates the price using the balance of the Flan and Stablecoin tokens in the liquidity pool. Since the contract relies on the token balances instead of a price oracle, the opportunity for price manipulation through flash loans exists. An attacker could use a flash loan to artificially inflate or deflate the price before calling this function, which could lead to incorrect price calculations and unfair token distribution. Additionally, the contract uses the `config.acceptableHighestPrice` variable to prevent price manipulation, but this approach relies on the community's ability to set an appropriate circuit breaker, and it only checks for price manipulation after the liquidity pairs have already been minted.
A56: 78 | B56: setEYEBasedAssetStake | C56: =COUNTIFS(c1raw!B:B, A56, c1raw!$E:$E, B56) -> 3 | D56: H-07 | E56: high risk | F56: https://code4rena.com/reports/2022-01-behodler/#h-07-lp-pricing-formula-is-vulnerable-to-flashloan-manipulation | G56: The function 'setEYEBasedAssetStake' allows users to stake assets, which increases their voting power in the DAO. The price of the asset is fetched using the balance of EYE tokens in the asset's contract. However, this approach might be susceptible to price manipulation, as an attacker can potentially manipulate the balance of EYE tokens in the asset's contract, which would directly affect the staking and voting process. This manipulation could lead to imbalanced voting power and decision-making within the DAO.
A57: 78 | B57: burnAsset | C57: =COUNTIFS(c1raw!B:B, A57, c1raw!$E:$E, B57) -> 3 | D57: H-07 | E57: high risk | F57: https://code4rena.com/reports/2022-01-behodler/#h-07-lp-pricing-formula-is-vulnerable-to-flashloan-manipulation | G57: The 'burnAsset' function allows users to burn assets in exchange for newly created FATE tokens. The amount of FATE tokens received depends on the amount of EYE tokens held by the asset. This approach is vulnerable to price manipulation, as an attacker could potentially manipulate the balance of EYE tokens in the asset's contract to increase the FATE tokens received when burning assets. This manipulation could lead to an artificial increase in the user's voting power in the DAO, potentially compromising the decision-making process.
A58: 83 | B58: provide | C58: =COUNTIFS(c1raw!B:B, A58, c1raw!$E:$E, B58) -> 3 | D58: =TRUE() -> 1 | E58: very low risk, and out of scope | G58: The provide function, which can only be called by a guardian, allows for adding liquidity to the USDM-POOL3 curve pool. A malicious guardian could add or withhold liquidity to manipulate the pool's price.
A59: 83 | B59: removeLiquidity | C59: =COUNTIFS(c1raw!B:B, A59, c1raw!$E:$E, B59) -> 3 | D59: =TRUE() -> 1 | E59: very low risk, and out of scope | G59: The removeLiquidity function, also only callable by a guardian, allows for removing liquidity from the USDM-POOL3 curve pool. A malicious guardian could remove liquidity to manipulate the pool's price.
A60: 83 | B60: enableUnlock | C60: =COUNTIFS(c1raw!B:B, A60, c1raw!$E:$E, B60) -> 2 | D60: =TRUE() -> 1 | E60: very low risk, and out of scope | G60: The function enableUnlock can only be called by the kpiOracle. If the kpiOracle is compromised, an attacker could manipulate when the users can withdraw their USDM tokens, which could potentially affect the price.
A61: 83 | B61: deposit | C61: =COUNTIFS(c1raw!B:B, A61, c1raw!$E:$E, B61) -> 1 | D61: =FALSE() -> 0 | E61: already take care | G61: The `deposit` function allows users to deposit USDM and pool3 tokens into the contract. A malicious user may deposit a large amount of tokens to manipulate the price or liquidity in the contract.
A62: 83 | B62: withdraw | C62: =COUNTIFS(c1raw!B:B, A62, c1raw!$E:$E, B62) -> 1 | D62: =FALSE() -> 0 | E62: already take care | G62: The `withdraw` function allows users to withdraw USDM and pool3 tokens from the contract when withdrawals are enabled. An attacker may withdraw a large amount of tokens to manipulate the price or liquidity in the contract.
A63: 193 | B63: price | C63: =COUNTIFS(c1raw!B:B, A63, c1raw!$E:$E, B63) -> 3 | D63: M-05 | E63: low risk | F63: https://code4rena.com/reports/2022-12-caviar/#m-05-pair-price-may-be-manipulated-by-direct-transfers | G63: The price function calculates the price of the fractional tokens based on the base token reserves and the fractional token reserves. It uses the formula: price = (baseTokenReserves * ONE) / fractionalTokenReserves. The base token reserves are fetched using the _baseTokenReserves() function, and the fractional token reserves are fetched using the balanceOf[address(this)] value. Since these values are internal to the contract and can be manipulated by the functions that change the baseTokenReserves and fractionalTokenReserves (like add, remove, buy, sell, wrap, unwrap), an attacker could potentially manipulate the price by calling these functions with a specific strategy.
A64: 193 | B64: buyQuote, sellQuote | C64: =COUNTIFS(c1raw!B:B, A64, c1raw!$E:$E, B64) -> 1 | D64: M-05 | E64: low risk | F64: https://code4rena.com/reports/2022-12-caviar/#m-05-pair-price-may-be-manipulated-by-direct-transfers | G64: The buyQuote and sellQuote functions are used to estimate the input/output amount for a trade. They are calculated using the baseTokenReserves and fractionalTokenReserves. For buyQuote, the calculation is (outputAmount * 1000 * baseTokenReserves()) / ((fractionalTokenReserves() - outputAmount) * 997). For sellQuote, the calculation is (inputAmount * 997 * baseTokenReserves()) / ((fractionalTokenReserves() * 1000) + (inputAmount * 997)). In both cases, manipulation of the baseTokenReserves or fractionalTokenReserves can influence the estimated input or output amounts for a trade.
A74: Proj | B74: Functions | C74: Certainty | D74: comments | E74: bugs
A75: 3 | B75: getPriceFromAMM | C75: =COUNTIFS(c1raw!B:B, A75, c1raw!$E:$E, B75) -> 3 | D75: M-08 | E75: =COUNTIFS(A1:A64, A75, $D1:$D64, D75) -> 1
A76: 3 | B76: getCurrentPriceInPeg | C76: =COUNTIFS(c1raw!B:B, A76, c1raw!$E:$E, B76) -> 2 | D76: H-03 | E76: =COUNTIFS(A2:A65, A76, $D2:$D65, D76) -> 1
A77: 3 | B77: setLiquidationPath | C77: =COUNTIFS(c1raw!B:B, A77, c1raw!$E:$E, B77) -> 1 | D77: M-02 | E77: =COUNTIFS(A3:A66, A77, $D3:$D66, D77) -> 1
A78: 3 | B78: viewCurrentPriceInPeg | C78: =COUNTIFS(c1raw!B:B, A78, c1raw!$E:$E, B78) -> 1 | D78: =TRUE() -> 1 | E78: =COUNTIFS(A4:A67, A78, $D4:$D67, D78) -> 1
A79: 16 | B79: recordTrade | C79: =COUNTIFS(c1raw!B:B, A79, c1raw!$E:$E, B79) -> 3 | D79: H-01 | E79: =COUNTIFS(A5:A68, A79, $D5:$D68, D79) -> 6
A80: 20 | B80: mintSynth | C80: =COUNTIFS(c1raw!B:B, A80, c1raw!$E:$E, B80) -> 3 | D80: H-09 | E80: =COUNTIFS(A6:A69, A80, $D6:$D69, D80) -> 1
A81: 20 | B81: realise | C81: =COUNTIFS(c1raw!B:B, A81, c1raw!$E:$E, B81) -> 3 | D81: H-05 | E81: =COUNTIFS(A7:A70, A81, $D7:$D70, D81) -> 1
A82: 20 | B82: harvestSingle | C82: =COUNTIFS(c1raw!B:B, A82, c1raw!$E:$E, B82) -> 3 | D82: M-08 | E82: =COUNTIFS(A8:A71, A82, $D8:$D71, D82) -> 1
A83: 20 | B83: calcSpotValueInBaseWithPool | C83: =COUNTIFS(c1raw!B:B, A83, c1raw!$E:$E, B83) -> 3 | D83: =TRUE() -> 1 | E83: =COUNTIFS(A9:A72, A83, $D9:$D72, D83) -> 10
A84: 20 | B84: burnSynth | C84: =COUNTIFS(c1raw!B:B, A84, c1raw!$E:$E, B84) -> 2 | D84: L-11 | E84: =COUNTIFS(A10:A73, A84, $D10:$D73, D84) -> 1
A85: 20 | B85: calcSwapOutput | C85: =COUNTIFS(c1raw!B:B, A85, c1raw!$E:$E, B85) -> 1 | D85: =FALSE() -> 0 | E85: =COUNTIFS(A11:A74, A85, $D11:$D74, D85) -> 2
A86: 23 | B86: getRiskAdjustedPresentValue | C86: =COUNTIFS(c1raw!B:B, A86, c1raw!$E:$E, B86) -> 1 | D86: =TRUE() -> 1 | E86: =COUNTIFS(A12:A75, A86, $D12:$D75, D86) -> 2
A87: 23 | B87: getLiquidityTokenValue | C87: =COUNTIFS(c1raw!B:B, A87, c1raw!$E:$E, B87) -> 2 | D87: H-10 | E87: =COUNTIFS(A13:A76, A87, $D13:$D76, D87) -> 1
A88: 42 | B88: distributeMochi | C88: =COUNTIFS(c1raw!B:B, A88, c1raw!$E:$E, B88) -> 4 | D88: =TRUE() -> 1 | E88: =COUNTIFS(A14:A77, A88, $D14:$D77, D88) -> 6
A89: 52 | B89: _swap | C89: =COUNTIFS(c1raw!B:B, A89, c1raw!$E:$E, B89) -> 5 | D89: =TRUE() -> 1 | E89: =COUNTIFS(A15:A78, A89, $D15:$D78, D89) -> 5
A90: 52 | B90: mintSynth | C90: =COUNTIFS(c1raw!B:B, A90, c1raw!$E:$E, B90) -> 2 | D90: H-01 | E90: =COUNTIFS(A16:A79, A90, $D16:$D79, D90) -> 2
A91: 52 | B91: _addLiquidity | C91: =COUNTIFS(c1raw!B:B, A91, c1raw!$E:$E, B91) -> 1 | D91: =FALSE() -> 0 | E91: =COUNTIFS(A17:A80, A91, $D17:$D80, D91) -> 1
A92: 67 | B92: investedAssets | C92: =COUNTIFS(c1raw!B:B, A92, c1raw!$E:$E, B92) -> 3 | D92: =TRUE() -> 1 | E92: =COUNTIFS(A18:A81, A92, $D18:$D81, D92) -> 3
A93: 70 | B93: cumulativePrices | C93: =COUNTIFS(c1raw!B:B, A93, c1raw!$E:$E, B93) -> 3 | D93: =TRUE() -> 1 | E93: =COUNTIFS(A19:A82, A93, $D19:$D82, D93) -> 7
A94: 78 | B94: purchasePyroFlan | C94: =COUNTIFS(c1raw!B:B, A94, c1raw!$E:$E, B94) -> 3 | D94: H-05 | E94: =COUNTIFS(A20:A83, A94, $D20:$D83, D94) -> 1
A95: 78 | B95: setEYEBasedAssetStake | C95: =COUNTIFS(c1raw!B:B, A95, c1raw!$E:$E, B95) -> 3 | D95: H-07 | E95: =COUNTIFS(A21:A84, A95, $D21:$D84, D95) -> 2
A96: 83 | B96: provide | C96: =COUNTIFS(c1raw!B:B, A96, c1raw!$E:$E, B96) -> 3 | D96: =TRUE() -> 1 | E96: =COUNTIFS(A22:A85, A96, $D22:$D85, D96) -> 3
A97: 83 | B97: deposit | C97: =COUNTIFS(c1raw!B:B, A97, c1raw!$E:$E, B97) -> 1 | D97: =FALSE() -> 0 | E97: =COUNTIFS(A23:A86, A97, $D23:$D86, D97) -> 2
A98: 193 | B98: price | C98: =COUNTIFS(c1raw!B:B, A98, c1raw!$E:$E, B98) -> 3 | D98: M-05 | E98: =COUNTIFS(A24:A87, A98, $D24:$D87, D98) -> 2

Sheet c2raw
A1: proj | B1: ID | C1: tests | D1: seq | E1: functions | F1: bug type | G1: justify | H1: notes | I1: explanation | J1: Column1
A2: 3_1 | B2: 3 | C2: 1 | D2: 1 | E2: adjustAmounts | F2: Underflow | I2: In the `adjustAmounts` function, there is a statement `account.holdings[fromToken] = account.holdings[fromToken] - soldAmount;` which can potentially cause an underflow error if `soldAmount` is greater than `account.holdings[fromToken]`. Solidity will not throw an exception on underflow or overflow. Instead, it will silently give an incorrect result.
A3: 3_1 | B3: 3 | C3: 1 | D3: 1 | E3: setLendingCap, setLendingBuffer, setHourlyYieldAPR | F3: Lack of Input Validation | I3: Without proper validation, these functions are prone to misuse or bugs resulting from extreme input values.
A4: 3_1 | B4: 3 | C4: 1 | D4: 2 | E4: applyBorrowInterest, registerBorrow, payOff | F4: Potential Overflow and Underflow | I4: These functions perform arithmetic operations without explicitly checking for overflows or underflows.
A5: 3_1 | B5: 3 | C5: 1 | D5: 3 | E5: N/A | F5: Lack of Events | I5: The contract does not emit events, making it difficult to monitor state changes.
A6: 3_1 | B6: 3 | C6: 1 | D6: 4 | E6: deactivateIssuer | F6: Inaccurate Error Messages | I6: The error message does not correctly reflect the action being performed.
A7: 3_1 | B7: 3 | C7: 1 | D7: 5 | E7: N/A | F7: Implicit Visibility in State Variables | I7: Not declaring visibility explicitly can lead to confusion about how and where state variables can be accessed.
A8: 3_2 | B8: 3 | C8: 2 | D8: 1 | E8: `_makeHourlyBond` | F8: Arithmetic Overflow/Underflow | I8: In the `_makeHourlyBond` function, the `bond.amount` and `lendingMeta[issuer].totalLending` are incremented by `amount`. In Solidity, if these variables are already at their maximum value, this addition could lead to an overflow, resetting the value to zero, which could lead to erroneous behavior. The same issue applies for underflow when subtracting `amount` in the `_withdrawHourlyBond` function.
A9: 3_2 | B9: 3 | C9: 2 | D9: 2 | E9: `updateHourlyBondAmount` | F9: Arithmetic Overflow/Underflow | I9: The same issue applies in the `updateHourlyBondAmount` function where `deltaAmount = bond.amount - oldAmount` and `lendingMeta[issuer].totalLending += deltaAmount;` could cause an overflow or underflow.
A10: 3_2 | B10: 3 | C10: 2 | D10: 3 | E10: `getUpdatedHourlyYield` | F10: Unchecked External Call | I10: The function `getUpdatedHourlyYield` involves a complex calculation and updates to various parameters. If any of these internal calls fail, it will stop the execution of the contract. This could be mitigated by using checks, effects, and interactions pattern in Solidity.
A11: 3_2 | B11: 3 | C11: 2 | D11: 4 | E11: `calcCumulativeYieldFP` | F11: Uncontrolled loop iteration | I11: In the function `calcCumulativeYieldFP`, there is a loop that runs based on the `hoursDelta` value which is calculated from user input `timeDelta`. If the `hoursDelta` value is large, the loop may consume an excessive amount of gas, which may result in an out-of-gas error. It may also allow for a potential Denial-of-Service (DoS) attack.
A12: 3_2 | B12: 3 | C12: 2 | D12: 5 | E12: `getUpdatedHourlyYield`, `calcCumulativeYieldFP` | F12: Magic numbers | I12: In several places in the code, there are hardcoded values (like `FP32`, `1 hours`, `100`). These are often referred to as "magic numbers" and are generally discouraged because they can make code harder to understand and maintain. It would be better to declare these as named constants at the top of the contract.
A13: 3_3 | B13: 3 | C13: 3 | D13: 1 | E13: _withdrawHourlyBond | F13: Underflow vulnerability | I13: In function _withdrawHourlyBond, there is a potential underflow when subtracting the 'amount' from 'bond.amount'. If 'amount' is greater than 'bond.amount', this operation will underflow and lead to an incorrect calculation. We need to add a require statement to ensure 'amount' is less than or equal to 'bond.amount'.
... A91: 25_3 | B91: 25 | C91: 3 | D91: 1 | E91: _updateUserRewards | F91: Arithmetic Precision Loss | I91: In the _updateUserRewards function, you are calculating the accumulated rewards for a user. The calculation involves a division operation at the end (`_balanceOf[user] * (rewardsPerToken_.accumulated - userRewards_.checkpoint) / 1e18`). This operation might lead to a precision loss because of the integer division, which in turn might lead to small inaccuracies in the rewards assigned to a user. This issue might be insignificant for large balances and rewards but could potentially be more noticeable for small balances and rewards.
A92: 29_1 | B92: 29 | C92: 1 | D92: 1 | E92: flashSwap | F92: Missing Input Validation
A93: 29_1 | B93: 29 | C93: 1 | D93: 2 | E93: burn | F93: Arithmetic Underflow
A94: 29_1 | B94: 29 | C94: 1 | D94: 3 | E94: burnSingle | F94: Arithmetic Underflow
A95: 29_1 | B95: 29 | C95: 1 | D95: 4 | E95: swap | F95: Arithmetic Underflow
A96: 29_1 | B96: 29 | C96: 1 | D96: 5 | E96: burnSingle | F96: Missing Input Validation
A97: 29_3 | B97: 29 | C97: 3 | D97: 1 | E97: `mint`, `burn`, `burnSingle`, `swap`, `flashSwap` | F97: Reentrancy Bug** | I97: The lock modifier used in these functions is meant to prevent reentrancy attacks, but it can potentially be bypassed. The `unlocked` variable is initially set to `1` and is changed to `2` at the start of the function execution. However, there's no guarantee that it will always be `1` before the function is called. An attacker can potentially manipulate the state of the contract to make `unlocked == 2` which can then bypass the reentrancy guard and allow for reentrancy attacks.
A98: 29_3 | B98: 29 | C98: 3 | D98: 2 | E98: `_mul`, `_div` | F98: Integer Overflow and Underflow** | I98: Solidity does not handle overflows and underflows automatically. This might lead to unexpected behavior if not handled correctly. Consider using SafeMath or Solidity 0.8.0 or later to handle these operations.
A99: 29_3 | B99: 29 | C99: 3 | D99: 3 | E99: `_transfer` | F99: Call to external contract** | I99: The `bento.call` in the `_transfer` function is a call to an external contract. This is risky because the external contract could be compromised, or it could be coded to perform actions that you don't expect.
A100: 29_3 | B100: 29 | C100: 3 | D100: 1 | E100: mint, burn, burnSingle, swap, flashSwap | F100: Reentrancy | I100: The functions mint, burn, burnSingle, swap, flashSwap contain a potential reentrancy bug. These functions are marked with the modifier 'lock' which uses a flag (unlocked) to prevent reentrancy. However, this flag is set back to 1 at the end of these functions, allowing potential reentrant calls. This could be exploited if the functions have a callback to an external contract that calls back into this contract before the original function has finished executing.
A101: 29_3 | B101: 29 | C101: 3 | D101: 2 | E101: _transfer, _balance | F101: Unchecked external call | I101: The functions _transfer and _balance make an external call to the 'bento' contract without checking the return value. If these calls fail, the entire transaction will revert, which may not be the desired behavior.
A102: 29_3 | B102: 29 | C102: 3 | D102: 3 | E102: _mintFee | F102: Overflow | I102: The _mintFee function multiplies two uint112 numbers, which could potentially result in a number that is larger than what can be stored in a uint256, resulting in an overflow.
A103: 29_3 | B103: 29 | C103: 3 | D103: 4 | E103: updateBarFee | F103: Unhandled exceptions | I103: The updateBarFee function makes a staticcall to the masterDeployer contract and decodes the returned bytes into a uint256. If the call fails or returns incorrect data, this will throw an exception which isn't caught in the function. This could cause transactions that call this function to revert unexpectedly.
A104: 29_3 | B104: 29 | C104: 3 | D104: 5 | E104: _getReserves, _balance, _update, _mintFee, _getAmountOut, _transfer, _nonOptimalMintFee | F104: Missing function visibility | I104: These internal functions don't have an explicit visibility set. Although they default to internal visibility, it's good practice to explicitly set the visibility for clarity.
A105: 29_3 | B105: 29 | C105: 3 | D105: 6 | E105: various | F105: Use of magic numbers | I105: There are several instances where "magic numbers" are used (like 0xf7888aec, 0x97da6d30, 0xf18d03cc). These values should be replaced with named constants for better code readability and maintainability.
A106: 30_1 | B106: 30 | C106: 1 | D106: 1 | E106: setGauge | F106: Zero Address Check | I106: The function `setGauge` is not checking if the provided address is a zero address. A zero address can be set as gauge which could potentially lock funds forever if ever interacted with.
A107: 30_1 | B107: 30 | C107: 1 | D107: 2 | E107: swap | F107: Oracle Manipulation / Front Running | I107: The function `swap` makes use of an expected amount parameter. If an oracle is used for this expected amount, and the oracle is not decentralized or is manipulatable, it could lead to loss of funds. Also, there is a possibility of front-running attacks where someone could see the transaction in the mempool and interact with the `swap` function before the transaction gets mined.
A108: 30_1 | B108: 30 | C108: 1 | D108: 3 | E108: withdraw | F108: Re-entrancy | I108: The `withdraw` function is at risk of re-entrancy attacks. It is calling an external contract (through the `_controller.withdraw` function) before the state (the user balance) is updated which could lead to re-entrancy attacks.
... A138: 45_1 | B138: 45 | C138: 1 | D138: 1 | E138: getLockedAmount | F138: Unexpected Value | I138: In the getLockedAmount function, when 'isIncrease' is set to false, the 'newLockedAmount' is being set to 'array[i].lockedAmount - 1' if 'array[i].lockedAmount' is greater than 'amount'. This might lead to unexpected values of 'newLockedAmount' as it decreases the 'lockedAmount' by 1 instead of 'amount'. It seems like a potential mistake in the code logic as it deviates from the expected behavior of reducing the 'lockedAmount' by 'amount'.
A139: 45_1 | B139: 45 | C139: 1 | D139: 2 | E139: _findMedian | F139: Incorrect Order of Calculations | I139: In the _findMedian function, the median is calculated as an average of two middle numbers when the array length is even. This could lead to incorrect results if those two numbers are large enough that their sum exceeds the maximum value of uint256 (2^256 - 1). A better way to avoid overflow would be to calculate the average by adding half of each number | J139: `(num1 / 2) + (num2 / 2)` and add 1 if num1 and num2 are both odd to account for the division truncation.
A140: 45_2 | B140: 45 | C140: 2 | D140: 1 | E140: _sortArray | F140: Unbounded Loops | I140: This function employs a bubble sort algorithm, which has a time complexity of O(n^2). In the worst-case scenario (an array that is reverse sorted), it could lead to excessive gas costs and possible transaction failure if the array is large enough, due to exceeding the Ethereum block gas limit.
A141: 45_2 | B141: 45 | C141: 2 | D141: 2 | E141: getLockedAmount | F141: Unchecked Return Value | I141: In the function `getLockedAmount`, there are multiple return statements within the for loop. If none of the `array[i].staker` elements match the `account` input, the function will return 0. While not necessarily an error, it might lead to unexpected behavior if this case isn't properly handled where the function is called.
A142: 45_2 | B142: 45 | C142: 2 | D142: 3 | E142: getLockedAmount | F142: Use of Magic Numbers | I142: The function `getLockedAmount` has a magic number 1 in the expression `newLockedAmount = array[i].lockedAmount - 1`. This could lead to confusion and potential errors in the future. It's generally good practice to define such numbers as constants with descriptive names.
A143: 45_2 | B143: 45 | C143: 2 | D143: 4 | E143: getCreditLimit | F143: Inefficient Storage Pattern | I143: The `getCreditLimit` function returns a median value based on an array of values passed as a parameter. If this data is frequently used, it may be more efficient to store it in a state variable to avoid calculating the median repeatedly.
A144: 47_1 | B144: 47 | C144: 1 | D144: 1 | E144: transferFrom, transfer | F144: Erroneous Accounting | I144: The functions `transferFrom` and `transfer` use a function called `balanceToShares` to convert the `amount` into `amountInShares`. This function uses the `pricePerShare` from an oracle, which could lead to erroneous accounting if the oracle provides incorrect or manipulated data.
A145: 47_1 | B145: 47 | C145: 1 | D145: 2 | E145: balanceOf, totalSupply | F145: Erroneous Accounting | I145: The functions `balanceOf` and `totalSupply` also use the `pricePerShare` from an oracle to calculate the balance or total supply. Again, this could lead to erroneous accounting if the oracle provides incorrect or manipulated data.
A146: 47_1 | B146: 47 | C146: 1 | D146: 3 | E146: mint, burn | F146: Incorrect Order of Calculations | I146: In the `mint` and `burn` functions, the transfer of tokens and the minting or burning of shares are not atomic, meaning they are not executed in one transaction. If the transaction fails halfway, it could lead to an inconsistent state of the contract.
A147: 47_1 | B147: 47 | C147: 1 | D147: 4 | E147: mint, burn | F147: Absence of input validation | I147: The `mint` and `burn` functions do not validate the `_shares` input parameter. If `_shares` is zero or a very large number, it could lead to unexpected results.
A148: 47_1 | B148: 47 | C148: 1 | D148: 5 | E148: mint, burn | F148: Absence of Re-entrancy guard | I148: The `mint` and `burn` functions call the external `transferFrom` and `transfer` methods of the `ibbtc` contract, but they don't have a re-entrancy guard to prevent potential re-entrancy attacks.
A149: 47_1 | B149: 47 | C149: 1 | D149: 1 | E149: transferFrom, transfer | F149: Erroneous Accounting | I149: The functions `transferFrom` and `transfer` use a function called `balanceToShares` to convert the `amount` into `amountInShares`. This function uses the `pricePerShare` variable, which could lead to erroneous accounting if the `pricePerShare` is not updated frequently or correctly.
A150: 47_1 | B150: 47 | C150: 1 | D150: 2 | E150: balanceOf, totalSupply | F150: Erroneous Accounting | I150: The functions `balanceOf` and `totalSupply` also use the `pricePerShare` to calculate the balance or total supply. Again, this could lead to erroneous accounting if the `pricePerShare` is not updated frequently or correctly.
A151: 47_1 | B151: 47 | C151: 1 | D151: 3 | E151: mint, burn | F151: Incorrect Order of Calculations | I151: In the `mint` and `burn` functions, the transfer of tokens and the minting or burning of shares are not atomic, meaning they are not executed in one transaction. If the transaction fails halfway, it could lead to an inconsistent state of the contract.
... A179: 49_3 | B179: 49 | C179: 3 | D179: 4 | E179: fetchPricePoint | F179: Potential Revert due to Integer Underflow | I179: In the `fetchPricePoint` function, there's an operation ` _liqs[0] - _liqs[1]` which can potentially underflow if `_liqs[1]` is larger than `_liqs[0]`.
A180: 52_1 | B180: 52 | C180: 1 | D180: 1 | E180: calculateLoss | F180: Incorrect Order of Calculations/Rounding Error | I180: In the function calculateLoss, you have two instances of an operation of the form `(A * B) / C`. Due to the nature of integer division in Solidity, this might not yield the expected results. Specifically, if `(A * B) < C`, the result of the operation will be `0`. The correct order of operations to ensure the right precedence and to avoid the rounding down to 0 before the multiplication should be | J180: `(A * B) / C` should be changed to `A * (B / C)`, given that `B / C` would not result in a fraction.
A181: 52_1 | B181: 52 | C181: 1 | D181: 1 | E181: addLiquidity | F181: Function Overloading Error | I181: There are two functions named `addLiquidity` with the same parameters which could cause confusion and unexpected behavior. The first `addLiquidity` function calls the second `addLiquidity` function with the exact same arguments it received, leading to a recursive call without a base case. This can cause a stack overflow error (out of gas exception).
A182: 52_1 | B182: 52 | C182: 1 | D182: 2 | E182: _addLiquidity | F182: Incomplete Code/Logic Error | I182: The `_addLiquidity` function doesn't account for the scenario when a pool already exists for the provided token pair. In this case, it should determine the amountA and amountB based on the existing pool's reserves and the desired amounts. Currently, it just sets amountA and amountB equal to the desired amounts without considering the existing state of the pool.
A183: 52_1 | B183: 52 | C183: 1 | D183: 3 | E183: initialize | F183: Ownership Renouncement | I183: The `initialize` function renounces the contract's ownership after setting the reserve. This means that no further changes can be made that require owner permissions, such as updating the reserve address. It's important to consider whether this is the desired behavior.
A184: 52_1 | B184: 52 | C184: 1 | D184: 4 | E184: removeLiquidity | F184: Missing Input Validation | I184: The `removeLiquidity` function doesn't validate if the provided tokens (tokenA and tokenB) have a corresponding pool in the factory. This can lead to unexpected behavior or errors if a pool doesn't exist for the provided tokens.
A185: 52_1 | B185: 52 | C185: 1 | D185: 5 | E185: _swap | F185: Missing Return Values | I185: The `_swap` function doesn't return a value in all paths. In the case when path length is 2 and the second token in the path isn't the native asset, there's no return statement. This can lead to unexpected behavior or errors.
A186: 52_1 | B186: 52 | C186: 1 | D186: 1 | E186: burnSynth | F186: Arithmetic Overflow and Underflow | I186: In the function `burnSynth`, there is a subtraction of two uint values, `reserveNative - amountNative`. This could potentially lead to an underflow error if `amountNative` is greater than `reserveNative`. Using SafeMath library or Solidity 0.8.0 or newer for these operations would prevent this issue.
A187: 52_1 | B187: 52 | C187: 1 | D187: 2 | E187: _update | F187: Arithmetic Overflow and Underflow | I187: In the function `_update` (which is not in the provided code but it's called multiple times), there could be potential arithmetic overflows or underflows, depending on the implementation of the function. It's highly recommended to use SafeMath library or Solidity 0.8.0 or newer for these operations.
A188: 52_1 | B188: 52 | C188: 1 | D188: 1 | E188: `vaderToUsdv` | F188: Incorrect order of calculations | I188: If `_usdvEnabled` is `false`, `vaderAmount` is directly multiplied with the return value from `consult(VADER)`. However, considering the difference in decimal places between VADER and the native token, this calculation might need to be adjusted. The return value from `consult(VADER)` should probably be multiplied by `vaderAmount` and then divided by `10**decimals` to account for the decimal difference.
A189: 52_1 | B189: 52 | C189: 1 | D189: 2 | E189: `consult` | F189: Unexpected values | I189: The calculation `uint256(price) * (10**10)` assumes that the Chainlink price feed returns a price with 8 decimal places. This might not be the case for all price feeds. You should confirm the number of decimal places for the specific Chainlink price feed you're using.
A190: 52_1 | B190: 52 | C190: 1 | D190: 3 | E190: `registerPair` | F190: Incorrect variable | I190: When `token0` is not `VADER`, the pair address is set to the `_vaderPool` address. However, the `_vaderPool` is not necessarily the correct pair for `token0` and `token1`. This may lead to incorrect reserves and prices being used for this pair.
A191: 52_2 | B191: 52 | C191: 2 | D191: 1 | E191: _burn | F191: Potential Underflow/Overflow | I191: The `_burn` function contains potential underflow points with the expressions `reserveNative - amountNative` and `reserveForeign - amountForeign`. If `amountNative` or `amountForeign` is greater than their corresponding reserves, this could lead to underflow.
A192: 52_2 | B192: 52 | C192: 2 | D192: 2 | E192: _update | F192: Potential Underflow/Overflow | I192: The `_update` function contains potential overflow points with the expressions `balanceNative <= type(uint112).max` and `balanceForeign <= type(uint112).max`. If `balanceNative` or `balanceForeign` exceed their max limit, this could lead to an overflow.
... A227: 59_1 | B227: 59 | C227: 1 | D227: 1 | E227: `_calculateMaltRequiredForExit` | F227: Over/Underflow Error | I227: This function is using division and multiplication operations which could lead to overflow/underflow errors. Solidity does not throw an error when a number is divided by zero, it will instead return zero. Also, multiplication operations could overflow if the operands are too large. To prevent these potential overflows/underflows, consider using SafeMath for these operations. Specifically, you should consider using SafeMath for the following operations
A228: 59_1 | B228: 59 | C228: 1 | D228: 2 | E228: `exitEarly` | F228: Incorrect Order of Calculations | I228: This function is not checking if the `amountOut` is greater than `minOut` before updating the `auctionExits`. In case the `amountOut` is less than `minOut`, the function will revert but not before updating the `auctionExits`. To correct this, the `require(amountOut > minOut, "EarlyExit | J228: Insufficient output");` statement should be moved up before the `auctionExits` are updated.
A229: 59_1 | B229: 59 | C229: 1 | D229: 3 | E229: `_calculateMaltRequiredForExit` | F229: Use of incorrect variables | I229: In this function, the calculation of `amount` is based on the `userCommitment` and `userRedeemed`. However, these values are not updated in the function. If `amount` is greater than `userCommitment - userRedeemed`, `amount` is set to `userCommitment - userRedeemed`. This may not be the desired behavior as it could lead to an erroneous calculation of `amount`. Consider updating `userCommitment` and `userRedeemed` before calculating `amount`.
A230: 59_1 | B230: 59 | C230: 1 | D230: 4 | E230: `earlyExitReturn` | F230: Incorrect Calculation | I230: In the function `earlyExitReturn`, the calculation for `maxProfit` is done with the formula `(fullReturn - amount) * (maxEarlyExitBps * progressionBps / 10000) / 1000`. The multiplication and division operations are not in parentheses which could lead to incorrect calculation due to operator precedence. You should consider using parentheses to ensure the correct order of operations. The correct expression should be `((fullReturn - amount) * (maxEarlyExitBps * progressionBps)) / (10000 * 1000)`.
A231: 59_2 | B231: 59 | C231: 2 | D231: 1 | E231: consult() | F231: Precision loss | I231: The skew calculation `(frequency + (participation * 2)) / 3;` suffers from precision loss due to integer division. This could lead to slightly inaccurate results.
A232: 59_2 | B232: 59 | C232: 2 | D232: 2 | E232: getAverageParticipation() | F232: Integer overflow | I232: In the line `aggregate.maxCommitments = aggregate.maxCommitments + maxCommitments;` and `aggregate.commitments = aggregate.commitments + commitments;`, there is a potential for integer overflow which could lead to incorrect calculations.
A233: 59_2 | B233: 59 | C233: 2 | D233: 3 | E233: setAuctionAverageLookback() | F233: Unbounded array size | I233: There's no check for the maximum size of the `pegObservations` array. This could lead to out of gas errors if the array becomes too large. It could also be exploited to fill up the blockchain storage.
A234: 59_2 | B234: 59 | C234: 2 | D234: 4 | E234: getRealBurnBudget() | F234: Integer underflow | I234: In the line `uint256 usableExcess = maxBurnSpend.sub(premiumExcess);`, it is not checked whether `maxBurnSpend` is greater than or equal to `premiumExcess` before the subtraction. This can potentially cause an underflow if `premiumExcess` is larger than `maxBurnSpend`.
A235: 59_2 | B235: 59 | C235: 2 | D235: 1 | E235: exitEarly | F235: Unexpected Values | I235: In the `exitEarly` function, there is a lack of validation for the `amount` input. This could potentially lead to negative values, or values that are too high, being used in the function. A require statement should be added to ensure that the `amount` is greater than 0 and less than or equal to the user's balance.
A236: 59_2 | B236: 59 | C236: 2 | D236: 2 | E236: earlyExitReturn | F236: Incorrect Order of Calculations | I236: There could be a potential for underflow in the `earlyExitReturn` function. The line `uint256 userOutstanding = userCommitment - userRedeemed;` assumes that `userCommitment` is always larger than or equal to `userRedeemed`. If for some reason it isn't, this could lead to an underflow error. There should be a check to ensure `userRedeemed` is not larger than `userCommitment`.
A237: 59_2 | B237: 59 | C237: 2 | D237: 3 | E237: _calculateMaltRequiredForExit | F237: Incorrect Order of Calculations | I237: The same potential for underflow exists in the `_calculateMaltRequiredForExit` function as well, with the line `if (amount > (userCommitment - userRedeemed))`. It should be checked that `userRedeemed` is not larger than `userCommitment` before this calculation.
A238: 59_2 | B238: 59 | C238: 2 | D238: 4 | E238: setEarlyExitBps | F238: Use of Incorrect Variables | I238: In the function `setEarlyExitBps`, the requirement checks if `_earlyExitBps` is greater than 0 and less than or equal to 1000, but the comment above says it should be between 0-100%. It looks like a mismatch between the comment and the actual code. The comment should be updated to reflect the actual requirement or vice versa.
A239: 59_2 | B239: 59 | C239: 2 | D239: 5 | E239: earlyExitReturn and _calculateMaltRequiredForExit | F239: Incorrect Order of Calculations | I239: Division before multiplication can lead to loss of precision due to integer division. `maltQuantity.mul(currentPrice) / pegPrice;` this should be rearranged to `maltQuantity.mul(currentPrice).div(pegPrice);` to prevent the loss of precision.
A240: 59_3 | B240: 59 | C240: 3 | D240: 2 | E240: `setEarlyExitBps` | F240: Input validation | I240: This function allows setting a value that's higher than 100% which is probably not intended. It should validate that the input value is between 0 and 1000.
... A363: 112_3 | B363: 112 | C363: 3 | D363: 8 | E363: transfer | F363: Arithmetic Underflow | I363: In the transfer function, the balance of the account is decreased without checking for potential arithmetic underflow.

Sheet c2O
A1: proj | B1: ID | C1: Seq | D1: functions | E1: file | F1: bug type | G1: justify | H1: notes | I1: explanation
A2: 3_1 | B2: 3 | C2: 3 | D2: N/A | F2: Lack of Events | G2: L-13 | H2: https://code4rena.com/reports/2021-04-marginswap/#l-13-not-emitting-event-for-important-state-changes | I2: The contract does not emit events, making it difficult to monitor state changes.
A3: 3_1 | B3: 3 | C3: 4 | D3: deactivateIssuer | F3: Inaccurate Error Messages | G3: true, irrelevant | I3: The error message does not correctly reflect the action being performed.
A4: 3_1 | B4: 3 | C4: 5 | D4: N/A | F4: Implicit Visibility in State Variables | G4: true, irrelevant | I4: Not declaring visibility explicitly can lead to confusion about how and where state variables can be accessed.
A5: 3_2 | B5: 3 | C5: 5 | D5: getUpdatedHourlyYield, calcCumulativeYieldFP | F5: Magic numbers | G5: true, irrelevant | I5: In several places in the code, there are hardcoded values (like `FP32`, `1 hours`, `100`). These are often referred to as "magic numbers" and are generally discouraged because they can make code harder to understand and maintain. It would be better to declare these as named constants at the top of the contract.
A6: 3_3 | B6: 3 | C6: 2 | D6: calcCumulativeYieldFP | F6: Incorrect calculation order | G6: true, but precision loss | I6: The calculation `yieldAccumulator.accumulatorFP * yieldAccumulator.hourlyYieldFP * secondsDelta` in the function `calcCumulativeYieldFP` might lead to overflow due to incorrect order of calculations. The multiplication operation should be done after the division to avoid potential overflow.
A7: 3_3 | B7: 3 | C7: 5 | D7: calcCumulativeYieldFP | F7: Arithmetic Precision Loss | G7: false, already after | I7: In function calcCumulativeYieldFP, when calculating the accumulatorFP, the division is done before the multiplication. This can lead to precision loss, because in Solidity, division truncates the result. This could potentially lead to financial implications as this contract deals with financial calculations.
A8: 5_1 | B8: 5 | C8: 3 | D8: isPool | F8: Uninitialized variables | G8: false, irrelevant. inited by init() | I8: In the isPool function, the variable pool is not initialized which could lead to unpredictable behavior. If the condition inside the if statement does not hold true, the function would return an undefined value.
A9: 5_1 | B9: 5 | C9: 4 | D9: calcPart | F9: Incorrect use of require statement | G9: true, no risk | I9: The require statement in the function calcPart checks if the bp parameter is between 0 and 10000, inclusive. However, it is not required to check if bp is greater than or equal to 0 because the bp parameter is of type uint, which cannot be negative.
A10: 5_2 | B10: 5 | C10: 1 | D10: addLiquidity | F10: Uninitialized variable usage | G10: false, 0 by default | I10: The contract uses the uninitialized variable `_actualInputBase` within the `addLiquidity` function. This could potentially lead to incorrect calculations or unexpected behavior.
A11: 5_2 | B11: 5 | C11: 2 | D11: sync | F11: Incomplete function implementation | G11: false, already commented out | I11: In the `sync` function, there's an unfinished condition branch for `isSynth()`. This might cause unexpected behavior if this condition should be handled in a certain way. This can be considered an incomplete function implementation bug.
A12: 5_3 | B12: 5 | C12: 4 | D12: isBase, isPool | F12: Variable Shadowing | G12: false, irrelevant. returns by default | I12: In the 'isBase' and 'isPool' functions, the return variables 'base' and 'pool' are not explicitly set in all paths, leading to potential variable shadowing and unexpected return values.
A13: 5_3 | B13: 5 | C13: 7 | D13: init | F13: Uninitialized Storage Pointers** | G13: true, low risk | I13: The contract does not initialize its storage pointers (VADER, USDV, ROUTER, FACTORY) in its constructor but instead in the `init` function. This is a bad practice as it exposes the contract state to manipulation before the `init` function is called.
A14: 14_1 | B14: 14 | C14: 1 | D14: balanceOfToken | E14: BadgerYieldSource.sol | F14: Incorrect calculation order | G14: =FALSE() -> 0 | I14: The function `balanceOfToken` performs a multiplication followed by a division. Depending on the values of `balances[addr]`, `badgerSettBadgerBalance`, and `totalShares`, this order of operations might cause rounding errors or integer underflows. Ideally, the division should be performed first to ensure that the multiplication does not exceed the maximum uint256 value.
A15: 14_1 | B15: 14 | C15: 2 | D15: redeemToken | E15: BadgerYieldSource.sol | F15: Unexpected value | G15: false, already take care | I15: In the function `redeemToken`, the case when `totalShares` is zero is handled by returning zero. However, if `totalShares` is zero and `amount` is non-zero, it is possible that the user is expecting to redeem tokens but gets zero in return. This might be an unexpected behavior.
A16: 14_1 | B16: 14 | C16: 3 | D16: redeemToken | E16: BadgerYieldSource.sol | F16: Unexpected value | G16: false, already return before. | I16: There is a potential case with unexpected values where `badgerSettBadgerBalance` is zero. If `badgerSettBadgerBalance` is zero, `requiredShares` will be zero due to the division by `badgerSettBadgerBalance`, and `requiredSharesBalance` will underflow as it tries to subtract 1 from zero. This might cause unexpected behavior and revert the transaction.
A17: 14_1 | B17: 14 | C17: 4 | D17: redeemToken | E17: BadgerYieldSource.sol | F17: Incorrect variable usage | G17: false, as intend | I17: In the `redeemToken` function, `balances[msg.sender]` is decreased by `requiredSharesBalance`, but it seems that it should be decreased by the redeemed `badgerBalanceDiff` instead, because `balances` map seems to track the user's balance in the underlying badger token, not in badgerSett shares.
A18: 14_1 | B18: 14 | C18: 5 | D18: supplyTokenTo | E18: BadgerYieldSource.sol | F18: Unexpected value | G18: true, low risk. return value | I18: The function `supplyTokenTo` does not handle the case where `badgerSett.deposit(amount)` might fail. If the `deposit` function were to fail, `balanceDiff` could be zero and the user's balance would not be updated, even though the badger tokens have already been transferred. This could lead to a loss of funds for the user.
A19: 14_1 | B19: 14 | C19: 1 | D19: _tokenToShares, _sharesToToken | E19: IYieldSource.sol | F19: Incorrect calculation order | G19: true, low risk | I19: In both `_tokenToShares` and `_sharesToToken` functions, there is multiplication before division. In these functions, you should be careful with the order of operations, as the current operation order can lead to loss of precision due to rounding down.
A20: 14_1 | B20: 14 | C20: 2 | D20: _depositToIdle | E20: IYieldSource.sol | F20: Unexpected value | G20: true, low risk. return value | I20: In the `_depositToIdle` function, there's no check for the return value of `mintIdleToken`. If `mintIdleToken` fails and returns zero, the function will still succeed, and the user's tokens will be stuck in this contract.
A21: 14_1 | B21: 14 | C21: 3 | D21: supplyTokenTo, redeemToken | E21: IYieldSource.sol | F21: Unexpected value | G21: false, msg.sender cannot be 0 | I21: In the `supplyTokenTo` and `redeemToken` functions, there's no check if the `to` address or `msg.sender` is the zero address. Transferring tokens to the zero address can lead to permanent loss of those tokens.
A22: 14_1 | B22: 14 | C22: 4 | D22: redeemToken | E22: IYieldSource.sol | F22: Unexpected value | G22: H-01 | H22: https://code4rena.com/reports/2021-06-pooltogether/#h-01-user-could-lose-underlying-tokens-when-redeeming-from-the-idleyieldsource | I22: In the `redeemToken` function, the `redeemAmount` is denominated in `token()`, but it seems to be used as an amount of shares in `redeemIdleToken`. If `token()` and shares have different decimals, this will cause incorrect behavior.
A23: 14_1 | B23: 14 | C23: 5 | D23: transferERC20 | E23: IYieldSource.sol | F23: Unexpected value | G23: true, low risk. input validation | I23: In the `transferERC20` function, there's a check that `erc20Token` is not `idleToken`, but there's no check if `erc20Token` is the zero address. If `erc20Token` is the zero address, this function will revert because `safeTransfer` to the zero address is likely to fail.
A24: 14_3 | B24: 14 | C24: 1 | D24: redeemToken | E24: BadgerYieldSource.sol | F24: Unexpected value | G24: false, already take care | I24: The `redeemToken` function calculates the `requiredShares` to withdraw from the `badgerSett`. However, the calculation is done in such a way that it could potentially lead to unexpected values. The `requiredShares` are calculated as `(amount * totalShares + totalShares) / badgerSettBadgerBalance`. In this calculation, the `totalShares` are added twice, which may not be intended and could lead to unexpected, higher values for `requiredShares`.
A25: 14_3 | B25: 14 | C25: 1 | D25: _tokenToShares | E25: IYieldSource.sol | F25: Incorrect calculation order | G25: false, as intend | I25: The function `_tokenToShares` performs multiplication before division which could lead to an overflow. It might be more accurate and safe to perform the division first.
A26: 14_3 | B26: 14 | C26: 2 | D26: _sharesToToken | E26: IYieldSource.sol | F26: Incorrect calculation order | G26: false, as intend | I26: Similar to `_tokenToShares`, the `_sharesToToken` function also does multiplication before division, which can potentially lead to overflow errors.
A27: 14_3 | B27: 14 | C27: 3 | D27: redeemToken | E27: IYieldSource.sol | F27: Unexpected value | G27: H-01 | H27: https://code4rena.com/reports/2021-06-pooltogether/#h-01-user-could-lose-underlying-tokens-when-redeeming-from-the-idleyieldsource | I27: In the `redeemToken` function, `redeemAmount` is converted to `redeemedShare` using `_tokenToShares` function, which might not yield the expected amount of shares due to the rounding issues in integer division. This could result in slightly lower `redeemedUnderlyingAsset` than expected.
A28: 16_1 | B28: 16 | C28: 1 | D28: Various | E28: TracerPerpetualSwaps.sol | F28: Use of `require` for validating business logic | G28: false, already take care | I28: `require` is used throughout the contract to enforce business rules. While this is a common pattern in Solidity, it can lead to unexpected results if the conditions aren't met, since `require` will revert the entire transaction. This can make it difficult to identify and handle specific errors in a complex system. It might be worth considering a pattern that allows for more granular error handling.
A29: 16_1 | B29: 16 | C29: 4 | D29: Various | E29: TracerPerpetualSwaps.sol | F29: Lack of event emission | G29: true, but no need for internal function | I29: There are some state-changing functions that do not emit events. This can make it harder to track the state changes of the contract via events. An example could be the `_updateAccountLeverage` function which updates the leverage but does not emit an event.
A30: 16_1 | B30: 16 | C30: 1 | D30: latestAnswer | E30: GasOracle.sol | F30: Incorrect calculation order | G30: H-6 | H30: https://code4rena.com/reports/2021-06-tracer/#h-06-wrong-price-scale-for-gasoracle | I30: The gas price and ETH price fetched from Chainlink Oracle are not converted to have consistent decimals before multiplication. Therefore, the returned value may not be in USD/Gas * 10^18 if the decimals of these two oracles are not the same. To fix it, the contract could use the toWad function to convert them to a consistent decimal base before multiplication.
A31: 16_1 | B31: 16 | C31: 2 | D31: setDecimals | E31: GasOracle.sol | F31: Deviating Semantics | G31: false, no check function and no use | I31: The 'setDecimals' function allows the owner to set the 'decimals' variable without any restrictions. This can lead to inconsistency in calculations throughout the smart contract as other functions use the 'decimals' variable assuming it's 18.
A32: 16_1 | B32: 16 | C32: 3 | D32: setGasOracle, setPriceOracle | E32: GasOracle.sol | F32: Incorrect variable usage | G32: true, low risk. address check | I32: The setGasOracle and setPriceOracle functions are not validating if the input addresses are actual contract addresses. This could potentially allow for setting non-contract addresses as oracle addresses, which would lead to failure when trying to interact with these addresses as contracts.
A33: 16_1 | B33: 16 | C33: 4 | D33: toWad | E33: GasOracle.sol | F33: Unexpected value | G33: false, checked by solidity already | I33: The multiplication operation raw * scaler could potentially overflow if not handled correctly. An overflow check should be added for this operation to ensure the result fits in a uint256.
A34: 16_1 | B34: 16 | C34: 1 | D34: applyTrade | E34: LibBalances.sol | F34: Unexpected value | G34: true, checked by solidity already | I34: This function is performing mathematical operations that could potentially lead to overflow or underflow. However, since Solidity 0.8.0 (which this contract is using), arithmetic operations revert on underflow and overflow. Therefore, it is safe. But, it is still a good practice to check for overflows and underflows when working with older versions of Solidity.
A35: 16_1 | B35: 16 | C35: 2 | D35: marginIsValid | E35: LibBalances.sol | F35: Incorrect variable usage | G35: false, no need, mathlib takes care | I35: The function marginIsValid does not check if the provided position is valid. It only checks whether the calculated margin is less than 0 and whether the margin is greater than or equal to the minimum margin. However, it does not validate if the values in the position are within expected bounds.
A36: 16_1 | B36: 16 | C36: 3 | D36: margin | E36: LibBalances.sol | F36: Incorrect calculation order | G36: true, low risk | I36: The price is casted to an int256. If the price is higher than type(int256).max(), this will throw an exception. While this is a guard against an overflow, it also limits the maximum price that can be used. It's not necessarily a bug, but it is a limitation that should be well-documented.
A37: 16_1 | B37: 16 | C37: 4 | D37: tokenToWad, wadToToken | E37: LibBalances.sol | F37: Incorrect variable usage | G37: true, but take care in other files | I37: The functions tokenToWad and wadToToken assume that the provided 'tokenDecimals' are less than or equal to 'MAX_DECIMALS'. If 'tokenDecimals' is greater, these functions will not work correctly.
A38: 16_2 | B38: 16 | C38: 2 | D38: latestAnswer | E38: GasOracle.sol | F38: Unexpected value | G38: true, no use | I38: The function `latestAnswer` doesn't check if the `gasPrice` or `ethPrice` is zero before performing multiplication. This could potentially lead to an unexpected zero output if the oracles do not behave as expected.
A39: 16_2 | B39: 16 | C39: 3 | D39: toWad | E39: GasOracle.sol | F39: Deviating Semantics | G39: true, but as intend | I39: The `toWad` function expects the oracle to provide the correct decimal count. If the oracle behaves in a malicious or unexpected way, it could potentially break the contract logic. While you do check that `_decimals <= MAX_DECIMALS`, it would be better to also check that `_decimals` is not less than a reasonable minimum (e.g., 0).
A40: 16_2 | B40: 16 | C40: 1 | D40: minimumMargin | E40: LibBalances.sol | F40: Unexpected value | G40: L-08 | H40: https://code4rena.com/reports/2021-06-tracer/#l-08-potential-division-by-zero | I40: The function `minimumMargin` doesn't check if `maximumLeverage` is zero before performing division. This could potentially lead to a division by zero error if `maximumLeverage` is not properly validated.
A41: 16_2 | B41: 16 | C41: 2 | D41: wadToToken | E41: LibBalances.sol | F41: Incorrect calculation order | G41: false, not correct explan | I41: The function `wadToToken` performs division before multiplication. If `wadAmount` is less than `scaler`, it will return 0 due to the integer division. It might be better to perform multiplication first to maintain precision and then perform division.
A42: 17_3 | B42: 17 | C42: 1 | D42: _updateRatios | E42: Buoy3Pool.sol | F42: Incorrect calculation order | G42: L-03 | H42: https://code4rena.com/reports/2021-06-gro/#l-03-buoy3pool_updateratios-unsafe-math | I42: In the `_updateRatios` function, the `tolerance` argument is compared against the result of calculations involving `check` variable. However, `check` is calculated by subtracting `_ratio` from `chainRatios[i].div(CHAIN_FACTOR)`. This can potentially lead to an underflow if `_ratio` is greater than `chainRatios[i].div(CHAIN_FACTOR)`. To fix this, it would be advisable to ensure `_ratio` is always less than or equal to `chainRatios[i].div(CHAIN_FACTOR)`.
A43: 17_3 | B43: 17 | C43: 2 | D43: setBasisPointsLmit | E43: Buoy3Pool.sol | F43: Incorrect variable usage | G43: true, no risk | I43: The function name `setBasisPointsLmit` appears to be a typo. It should be `setBasisPointsLimit`.
A44: 17_3 | B44: 17 | C44: 3 | D44: stableToUsd | E44: Buoy3Pool.sol | F44: Unexpected value | G44: false, internal function relies on call | I44: The `stableToUsd` function calculates LP amount by calling `curvePool.calc_token_amount(_tokenAmounts, deposit)`, but there's no guarantee that the `deposit` variable will always be `true` when it should be for deposit operations. Incorrect value for `deposit` variable can lead to unexpected results.
A45: 17_3 | B45: 17 | C45: 4 | D45: poolBalances | E45: Buoy3Pool.sol | F45: Incorrect variable usage | G45: true, no risk | I45: In the `poolBalances` function, the `_balances` array is returned as `balances`. This is unnecessary and potentially confusing. The function should just return `_balances` directly.
A46: 25_1 | B46: 25 | C46: 1 | D46: peek, get | E46: CTokenMultiOracle.sol | F46: Arithmetic Precision Loss | G46: false, as intend | I46: In the `peek` and `get` functions, the value is calculated as `value = price * amount / 1e18;`. This may lead to precision loss due to integer division, especially if `price * amount` is less than `1e18`. It would be more accurate to perform the division first and then multiply by `amount`.
A47: 25_1 | B47: 25 | C47: 2 | D47: _updateUserRewards | E47: ERC20Rewards.sol | F47: Potential loss of rewards | G47: true, as intend | I47: In the _updateUserRewards function, when the new value for userRewards_.accumulated is calculated, the division by 1e18 could potentially result in a loss of rewards due to the truncation of decimal places.
A48: 25_1 | B48: 25 | C48: 3 | D48: setRewards | E48: ERC20Rewards.sol | F48: Incorrect timestamp comparison | G48: true, low risk. timestamp | I48: In the setRewards function, there are checks to ensure that a new rewards program can be set only if one is not currently running. However, these checks compare the current block timestamp (in seconds since Unix epoch) with the start and end times of the reward period, which are stored as uint32 values. Given that the current Unix timestamp has already exceeded the maximum value that can be stored in a uint32, these checks will always fail, preventing a new rewards program from being set.
A49: 25_3 | B49: 25 | C49: 1 | D49: _updateUserRewards | E49: ERC20Rewards.sol | F49: Potential loss of rewards | G49: true, as intend | I49: In the _updateUserRewards function, you are calculating the accumulated rewards for a user. The calculation involves a division operation at the end (`_balanceOf[user] * (rewardsPerToken_.accumulated - userRewards_.checkpoint) / 1e18`). This operation might lead to a precision loss because of the integer division, which in turn might lead to small inaccuracies in the rewards assigned to a user. This issue might be insignificant for large balances and rewards but could potentially be more noticeable for small balances and rewards.
A50: 29_3 | B50: 29 | C50: 6 | D50: various | F50: Use of magic numbers | G50: true, no risk | I50: There are several instances where "magic numbers" are used (like 0xf7888aec, 0x97da6d30, 0xf18d03cc). These values should be replaced with named constants for better code readability and maintainability.
A51: 30_3 | B51: 30 | C51: 3 | D51: withdraw | E51: Vault.sol | F51: Insufficient withdrawal amount check | G51: false, cannot be negative | I51: The withdrawal amount after subtracting the fee is not checked if it's still positive. In case of very high fees, the actual withdrawal amount might be very small or even negative.
A52: 30_3 | B52: 30 | C52: 1 | D52: setCap | E52: Controller.sol | F52: Incorrect calculation order | G52: true, low risk | I52: The function setCap first sets the new cap for the strategy, then withdraws the amount in excess of the new cap. However, it doesn't take into account the possibility that the withdrawal operation might fail, which would result in an incorrect cap being set. Ideally, it should perform the withdrawal first, then set the new cap only if the withdrawal was successful.
A53: 30_3 | B53: 30 | C53: 2 | D53: removeStrategy | E53: Controller.sol | F53: Unexpected value | G53: false, library reverts if underflow | I53: The function removeStrategy removes a strategy from a vault, and it uses the 'sub' function from the SafeMath library to adjust array indexes. However, it does not account for the scenario where the 'index' variable might be zero. If 'index' is zero, 'sub(1)' would underflow and produce an unexpected value. This could result in an incorrect array index being accessed, leading to potential errors or exploits.
A54: 30_3 | B54: 30 | C54: 3 | D54: withdraw | E54: Controller.sol | F54: Deviating Semantics | G54: false, as intend | I54: In the withdraw function, the 'safeTransfer' method is used to transfer tokens from the contract to the caller. However, the amount to be transferred is calculated after the withdrawal operations have been performed. This could lead to a situation where the actual balance of the contract is less than the calculated withdrawal amount, resulting in a failed transfer. This is inconsistent with the typical expectation that a withdrawal should only be possible if there are enough funds in the contract.
A55: 31_2 | B55: 31 | C55: 1 | D55: balanceOfPool() | E55: veCVXStrategy.sol | F55: Incorrect calculation order | G55: false, already before | I55: In the balanceOfPool() function, the value of bCVXToCVX is retrieved and checked for its value after it is used to calculate valueInLocker. If bCVXToCVX is less than or equal to 10**18, the function reverts with "Loss Of Peg". This check should be performed before the calculation is made to ensure that the peg has not been lost and to prevent unnecessary calculations if it has.
A56: 31_2 | B56: 31 | C56: 2 | D56: _withdrawSome() | E56: veCVXStrategy.sol | F56: Incorrect variable usage | G56: false, as intend | I56: In the _withdrawSome() function, it requires that max is greater than or equal to _amount multiplied by 9_980 divided by MAX_BPS. However, the variable "max" is set to the balance of the "want" token in the contract's address, and it may not be the correct amount for this check. This could potentially lead to incorrect calculations and potentially unwanted behavior.
A57: 31_2 | B57: 31 | C57: 3 | D57: manualRebalance() | E57: veCVXStrategy.sol | F57: Unexpected value | G57: false, as intend | I57: In the manualRebalance() function, if the newLockRatio is less than or equal to the currentLockRatio, the function will deposit all CVX into the vault without considering the toWantRatio. This may lead to more tokens being locked than expected, thus not respecting the desired balance defined by the toLock parameter.
A58: 31_2 | B58: 31 | C58: 4 | D58: _deposit() | E58: veCVXStrategy.sol | F58: Incorrect variable usage | G58: false, as intend | I58: In the _deposit() function, the contract calls the function CVX_VAULT.withdraw() with the amount intended to be deposited. This seems to be a mistake and it should be CVX_VAULT.deposit() instead.
A59: 31_3 | B59: 31 | C59: 1 | D59: harvest | E59: veCVXStrategy.sol | F59: Incorrect variable usage | G59: false, as intend | I59: The `harvest` function processes rewards, but the method `_processRewardsFees` receives `earnedReward` as a parameter which is the balance of the `reward` token after getting rewards from the `LOCKER`. The function `_processRewardsFees` processes the fee on this amount and sends the fees to the governance and the strategist. But, the reward is not converted to `want` token before processing fees. The fees should be processed on the `want` token instead of the `reward` token.
A60: 31_3 | B60: 31 | C60: 2 | D60: _withdrawSome | E60: veCVXStrategy.sol | F60: Incorrect calculation order | G60: false, as intend | I60: The `_withdrawSome` function requires that the amount to withdraw is not more than 99.8% of the current balance (`max >= _amount.mul(9_980).div(MAX_BPS)`). This can result in a miscalculation in cases where the `_amount` is very high, and `max` is low. This is because multiplying `_amount` by `9_980` can overflow if `_amount` is very large. This could be prevented by first dividing `_amount` by `MAX_BPS` and then multiplying the result by `9_980`.
A61: 31_3 | B61: 31 | C61: 3 | D61: manualRebalance | E61: veCVXStrategy.sol | F61: Unexpected value | G61: false, nonsense | I61: In the `manualRebalance` function, `toLock` is passed as a parameter, which is then directly used to calculate `newLockRatio`. The contract has a `MAX_BPS` constant which is `10_000`, and `toLock` is required to be less than or equal to `MAX_BPS`. But, it is not checked whether `toLock` is a valid value within the required range (0 to `MAX_BPS`). This could potentially lead to unexpected behavior if `toLock` is a negative value or an excessively large value.
A62: 39_1 | B62: 39 | C62: 1 | D62: initiateVaultFillingZcTokenInitiate, initiateZcTokenFillingVaultInitiate, initiateZcTokenFillingZcTokenExit, initiateVaultFillingVaultExit, exitZcTokenFillingZcTokenInitiate, exitVaultFillingVaultInitiate, exitVaultFillingZcTokenExit, exitZcTokenFillingVaultExit | E62: Swivel.sol | F62: Incorrect calculation order | G62: true, low risk | I62: In these functions, the filled volume of the order is being updated before any of the token transfers and minting operations have been confirmed to have succeeded. It's recommended that state variables like `filled[hash]` be updated only after all external function calls (like `transferFrom`, `mint`, etc.) have been successfully completed to avoid reentrancy attacks.
... A68: 44_3 | B68: 44 | C68: 2 | D68: swapByQuote | E68: Swap.sol | F68: Unexpected value | G68: true, no risk | I68: The function swapByQuote uses the msg.value to determine if the operation involves Ether. If the operation is supposed to involve Ether but msg.value is 0, the function reverts. However, it may be more appropriate to check if msg.value is equal to the amount that is supposed to be sent. If the two values do not match, the function should revert.
A69: 45_1 | B69: 45 | C69: 1 | D69: getLockedAmount | E69: CreditLimitByMedian.sol | F69: Unexpected value | G69: H-02 | H69: https://code4rena.com/reports/2021-10-union/#h-02-wrong-implementation-of-creditlimitbymediansolgetlockedamount-makes-it-unable-to-unlock-lockedamount-in-creditlimitbymedian-model | I69: In the getLockedAmount function, when 'isIncrease' is set to false, the 'newLockedAmount' is being set to 'array[i].lockedAmount - 1' if 'array[i].lockedAmount' is greater than 'amount'. This might lead to unexpected values of 'newLockedAmount' as it decreases the 'lockedAmount' by 1 instead of 'amount'. It seems like a potential mistake in the code logic as it deviates from the expected behavior of reducing the 'lockedAmount' by 'amount'.
A70: 45_1 | B70: 45 | C70: 2 | D70: _findMedian | E70: CreditLimitByMedian.sol | F70: Incorrect calculation order | G70: true, low risk | I70: In the _findMedian function, the median is calculated as an average of two middle numbers when the array length is even. This could lead to incorrect results if those two numbers are large enough that their sum exceeds the maximum value of uint256 (2^256 - 1). A better way to avoid overflow would be to calculate the average by adding half of each number `(num1 / 2) + (num2 / 2)` and add 1 if num1 and num2 are both odd to account for the division truncation.
A71: 45_2 | B71: 45 | C71: 3 | D71: getLockedAmount | E71: CreditLimitByMedian.sol | F71: Use of Magic Numbers | G71: true, no risk | I71: The function `getLockedAmount` has a magic number 1 in the expression `newLockedAmount = array[i].lockedAmount - 1`. This could lead to confusion and potential errors in the future. It's generally good practice to define such numbers as constants with descriptive names.
A72: 45_2 | B72: 45 | C72: 4 | D72: getCreditLimit | E72: CreditLimitByMedian.sol | F72: Inefficient Storage Pattern | G72: true, no risk | I72: The `getCreditLimit` function returns a median value based on an array of values passed as a parameter. If this data is frequently used, it may be more efficient to store it in a state variable to avoid calculating the median repeatedly.
A73: 47_1 | B73: 47 | C73: 1 | D73: transferFrom, transfer | E73: WrappedIbbtc.sol WrappedIbbtcEth.sol | F73: Erroneous Accounting | G73: true, low risk | I73: The functions `transferFrom` and `transfer` use a function called `balanceToShares` to convert the `amount` into `amountInShares`. This function uses the `pricePerShare` from an oracle, which could lead to erroneous accounting if the oracle provides incorrect or manipulated data.
A74: 47_1 | B74: 47 | C74: 2 | D74: balanceOf, totalSupply | F74: Erroneous Accounting | G74: true, low risk | I74: The functions `balanceOf` and `totalSupply` also use the `pricePerShare` from an oracle to calculate the balance or total supply. Again, this could lead to erroneous accounting if the oracle provides incorrect or manipulated data.
A75: 47_1 | B75: 47 | C75: 3 | D75: mint, burn | F75: Incorrect calculation order | G75: false, atomic | I75: In the `mint` and `burn` functions, the transfer of tokens and the minting or burning of shares are not atomic, meaning they are not executed in one transaction. If the transaction fails halfway, it could lead to an inconsistent state of the contract.
A76: 47_1 | B76: 47 | C76: 1 | D76: transferFrom, transfer | F76: Erroneous Accounting | G76: H-03 | H76: https://code4rena.com/reports/2021-10-badgerdao/#h-03-wrappedibbtceth-contract-will-use-stalled-price-for-mintburn-if-updatepricepershare-wasnt-run-properly | I76: The functions `transferFrom` and `transfer` use a function called `balanceToShares` to convert the `amount` into `amountInShares`. This function uses the `pricePerShare` variable, which could lead to erroneous accounting if the `pricePerShare` is not updated frequently or correctly.
A77: 47_1 | B77: 47 | C77: 2 | D77: balanceOf, totalSupply | F77: Erroneous Accounting | G77: H-03 | H77: https://code4rena.com/reports/2021-10-badgerdao/#h-03-wrappedibbtceth-contract-will-use-stalled-price-for-mintburn-if-updatepricepershare-wasnt-run-properly | I77: The functions `balanceOf` and `totalSupply` also use the `pricePerShare` to calculate the balance or total supply. Again, this could lead to erroneous accounting if the `pricePerShare` is not updated frequently or correctly.
A78: 47_1 | B78: 47 | C78: 6 | D78: updatePricePerShare | F78: Possible Stale Data | G78: H-03 | H78: https://code4rena.com/reports/2021-10-badgerdao/#h-03-wrappedibbtceth-contract-will-use-stalled-price-for-mintburn-if-updatepricepershare-wasnt-run-properly | I78: The `updatePricePerShare` function is permissionless, and anyone can call it to update the `pricePerShare`. However, the contract does not enforce the frequency of updates, which could lead to stale data if not updated regularly.
A79: 47_2 | B79: 47 | C79: 5 | D79: balanceToShares, sharesToBalance | F79: Incorrect calculation order | G79: true, no risk | I79: The functions `balanceToShares` and `sharesToBalance` use a magic number `1e18`. It would be better to define this value as a constant at the beginning of the contract to improve readability and maintainability.
A80: 47_3 | B80: 47 | C80: 3 | D80: mint, burn | F80: Lack of event after state-changing action | G80: true, no risk | I80: After changing the contract's state in the "mint" and "burn" functions, there is no event emitted. This can make it harder to track contract interactions and state changes.
A81: 49_2 | B81: 49 | C81: 3 | D81: Constructor | E81: OverlayV1UniswapV3Market.sol | F81: Potential Uninitialized Storage Reference | G81: true, low risk | I81: The constructor is calling four other contracts or libraries via their constructors. If any of these contracts fail to initialize properly, the state of the OverlayV1UniswapV3Market contract could be unpredictable or incorrect.
A82: 49_3 | B82: 49 | C82: 1 | D82: computeDepth | E82: OverlayV1UniswapV4Market.sol | F82: Arithmetic Precision Loss | G82: true, as intend | I82: In the `computeDepth` function, there is a risk of precision loss when dividing `_marketLiquidity * 1e18` by `_ovlPrice`. Solidity performs integer division, where the fractional part is discarded. This could result in a lower than expected `depth_` value, especially if `_ovlPrice` is significantly larger than `_marketLiquidity`.
A83: 49_3 | B83: 49 | C83: 3 | D83: fetchPricePoint | E83: OverlayV1UniswapV5Market.sol | F83: Potential Revert due to Casting | G83: true, low risk | I83: In the `fetchPricePoint` function, casting a `uint32` to `int32` and then again to `int56` might cause the function to revert if the original `uint32` value is larger than the maximum value an `int32` can hold.
A84: 52_1 | B84: 52 | C84: 1 | D84: calculateLoss | E84: VaderMath.sol | F84: Incorrect calculation order | G84: true, as intend | I84: In the function calculateLoss, you have two instances of an operation of the form `(A * B) / C`. Due to the nature of integer division in Solidity, this might not yield the expected results. Specifically, if `(A * B) < C`, the result of the operation will be `0`. The correct order of operations to ensure the right precedence and to avoid the rounding down to 0 before the multiplication should be `(A * B) / C` should be changed to `A * (B / C)`, given that `B / C` would not result in a fraction.
A85: 52_1 | B85: 52 | C85: 1 | D85: addLiquidity | E85: VaderRouter.sol | F85: Function Overloading Error | G85: false, different params | I85: There are two functions named `addLiquidity` with the same parameters which could cause confusion and unexpected behavior. The first `addLiquidity` function calls the second `addLiquidity` function with the exact same arguments it received, leading to a recursive call without a base case. This can cause a stack overflow error (out of gas exception).
A86: 52_1 | B86: 52 | C86: 2 | D86: _addLiquidity | E86: VaderRouter.sol | F86: Incomplete Code/Logic Error | G86: false, already take care | I86: The `_addLiquidity` function doesn't account for the scenario when a pool already exists for the provided token pair. In this case, it should determine the amountA and amountB based on the existing pool's reserves and the desired amounts. Currently, it just sets amountA and amountB equal to the desired amounts without considering the existing state of the pool.
A87: 52_1 | B87: 52 | C87: 1 | D87: vaderToUsdv | E87: TwapOracle.sol | F87: Incorrect calculation order | G87: false, no need. | I87: If `_usdvEnabled` is `false`, `vaderAmount` is directly multiplied with the return value from `consult(VADER)`. However, considering the difference in decimal places between VADER and the native token, this calculation might need to be adjusted. The return value from `consult(VADER)` should probably be multiplied by `vaderAmount` and then divided by `10**decimals` to account for the decimal difference.
A88: 52_1 | B88: 52 | C88: 2 | D88: consult | E88: TwapOracle.sol | F88: Unexpected value | G88: false, no risk | I88: The calculation `uint256(price) * (10**10)` assumes that the Chainlink price feed returns a price with 8 decimal places. This might not be the case for all price feeds. You should confirm the number of decimal places for the specific Chainlink price feed you're using.
A89: 52_1 | B89: 52 | C89: 3 | D89: registerPair | E89: TwapOracle.sol | F89: Incorrect variable usage | G89: false, as intend | I89: When `token0` is not `VADER`, the pair address is set to the `_vaderPool` address. However, the `_vaderPool` is not necessarily the correct pair for `token0` and `token1`. This may lead to incorrect reserves and prices being used for this pair.
A90: 52_2 | B90: 52 | C90: 4 | D90: swap | E90: BasePoolV2.sol | F90: Unexpected value | G90: false, already take care. error understanding | I90: In the `swap` function, it's expected that either `nativeAmountIn` or `foreignAmountIn` should be greater than zero, but not both. However, if both are greater than zero, there is no check or error message for this case, which can lead to unexpected behavior.
A91: 52_2 | B91: 52 | C91: 5 | D91: rescue | E91: BasePoolV2.sol | F91: Unexpected value | G91: M-21 | H91: https://code4rena.com/reports/2021-11-vader/#m-21-vaderpoolv2rescue-results-in-loss-of-funds-rather-than-recoverability | I91: In the `rescue` function, the smart contract transfers tokens to `msg.sender`, which can be any address. This could be a potential security risk if an unexpected address calls this function.
A92: 52_2 | B92: 52 | C92: 6 | D92: mint | E92: BasePoolV2.sol | F92: Unchecked Math | G92: false, already take care by solidity | I92: In the `mint` function, there is unchecked addition `totalLiquidityUnits + liquidity`. If the sum of these two values exceeds the maximum uint256 value, it will cause an overflow.
A93: 52_2 | B93: 52 | C93: 1 | D93: burnFungible | E93: VaderPoolV2.sol | F93: Incorrect SafeMath Operation | G93: false, already take care by solidity | I93: In the 'burnFungible' function, there is a subtraction operation in 'pair.totalSupply = _totalSupply - liquidity;' without using SafeMath which can lead to underflow if '_totalSupply' is less than 'liquidity'.
A94: 52_2 | B94: 52 | C94: 2 | D94: _update | E94: VaderPoolV2.sol | F94: Incorrect SafeMath Operation | G94: false, already take care by solidity | I94: The function '_update' is being called with operations like addition and subtraction of 'reserveNative' and 'reserveForeign' with 'nativeDeposit' and 'foreignDeposit' respectively, without using SafeMath, which can lead to underflow or overflow.
A95: 52_2 | B95: 52 | C95: 3 | D95: mintSynth | E95: VaderPoolV2.sol | F95: Incorrect SafeMath Operation | G95: false, already take care by solidity | I95: In the 'mintSynth' function, there's an addition operation in '_update' call without using SafeMath which can lead to overflow if 'reserveNative' and 'nativeDeposit' are large enough.
A96: 52_2 | B96: 52 | C96: 4 | D96: mintFungible | E96: VaderPoolV2.sol | F96: Incorrect SafeMath Operation | G96: false, already take care by solidity | I96: In the 'mintFungible' function, there are addition operations in '_update' call and 'pair.totalSupply = totalLiquidityUnits + liquidity;' without using SafeMath which can lead to overflow if the operands are large enough.
A97: 52_2 | B97: 52 | C97: 5 | D97: burn | E97: VaderPoolV2.sol | F97: Incorrect variable usage | G97: false, take care in other files | I97: In the 'burn' function, there is a use of '_ONE_YEAR' variable which is not defined anywhere in the contract. It might lead to compilation error.
A98: 52_3 | B98: 52 | C98: 6 | D98: root | E98: VaderMath.sol | F98: Unhandled edge case | G98: true, as intend | I98: This function calculates the square root of a number using the Babylonian method. However, if the input is 2 or 3, it will return 1 which is not the correct square root. This could potentially lead to incorrect calculations in other functions that use the root function.
A99: 52_3 | B99: 52 | C99: 7 | D99: calculateLiquidityUnits | E99: VaderMath.sol | F99: Incorrect calculation order | G99: false, as intend | I99: The function performs multiplication before division which can lead to loss of precision due to integer division. The operation `totalPoolUnits * poolUnitFactor` should be performed after the division by `denominator` to minimize precision loss.
A100: 52_3 | B100: 52 | C100: 1 | D100: addLiquidity | E100: VaderRouter.sol | F100: Function Overloading Error | G100: false, different params | I100: The `addLiquidity` function appears twice, with identical parameters. This could potentially lead to a stack overflow error if the function recursively calls itself indefinitely. This could be a copy-paste mistake, or possibly an attempt at function overloading gone wrong. You should correct this to avoid potential issues.
A101: 52_3 | B101: 52 | C101: 2 | D101: removeLiquidity | E101: VaderRouter.sol | F101: Uninitialized Contract | G101: true, no risk | I101: In the `removeLiquidity` function, the `reserve.reimburseImpermanentLoss` function is called, but the `reserve` variable is not initialized in the constructor and can only be initialized via the `initialize` function. If `removeLiquidity` is called before `initialize`, this will lead to a function call on a zero-address contract, causing a failure.
A102: 58_2 | B102: 58 | C102: 2 | D102: withdraw | E102: LpIssuerGovernance.sol LpIssuer.sol | F102: Incorrect calculation order | G102: false, checked already. | I102: In the "withdraw" function, there's a possibility that the total supply could be zero, causing a division by zero error when calculating tokenAmounts[i]. This could be mitigated by checking if the total supply is greater than zero before performing the division.
A103: 58_2 | B103: 58 | C103: 3 | D103: _chargeFees | E103: LpIssuer.sol | F103: Incorrect variable usage | G103: M-03 | H103: https://code4rena.com/reports/2021-12-mellow/#m-03-users-can-avoid-paying-vault-fees | I103: In the "_chargeFees" function, the elapsed time is calculated by subtracting lastFeeCharge from the current block timestamp. However, if this function is called before any fee has been charged, lastFeeCharge would be zero, causing the elapsed time to be incorrectly calculated as the current timestamp. This could lead to incorrect fee charges.
A104: 59_1 | B104: 59 | C104: 2 | D104: exitEarly | E104: AuctionEscapeHatch.sol | F104: Incorrect calculation order | G104: false, already before | I104: This function is not checking if the `amountOut` is greater than `minOut` before updating the `auctionExits`. In case the `amountOut` is less than `minOut`, the function will revert but not before updating the `auctionExits`. To correct this, the `require(amountOut > minOut, "EarlyExit Insufficient output");` statement should be moved up before the `auctionExits` are updated.
A105: 59_1 | B105: 59 | C105: 3 | D105: _calculateMaltRequiredForExit | E105: AuctionEscapeHatch.sol | F105: Incorrect variable usage | G105: false, as intend | I105: In this function, the calculation of `amount` is based on the `userCommitment` and `userRedeemed`. However, these values are not updated in the function. If `amount` is greater than `userCommitment - userRedeemed`, `amount` is set to `userCommitment - userRedeemed`. This may not be the desired behavior as it could lead to an erroneous calculation of `amount`. Consider updating `userCommitment` and `userRedeemed` before calculating `amount`.
...

Sheet c2Uniq
A1: proj | B1: ID | C1: Seq | D1: functions | E1: file | F1: bug type | G1: justify | H1: notes | I1: explanation
A2: 3_1 | B2: 3 | C2: 3 | D2: N/A | F2: Lack of Events | G2: L-13 | H2: https://code4rena.com/reports/2021-04-marginswap/#l-13-not-emitting-event-for-important-state-changes | I2: The contract does not emit events, making it difficult to monitor state changes.
A3: 3_1 | B3: 3 | C3: 4 | D3: deactivateIssuer | F3: Inaccurate Error Messages | G3: true, irrelevant | I3: The error message does not correctly reflect the action being performed.
A4: 3_1 | B4: 3 | C4: 5 | D4: N/A | F4: Implicit Visibility in State Variables | G4: true, irrelevant | I4: Not declaring visibility explicitly can lead to confusion about how and where state variables can be accessed.
A5: 3_2 | B5: 3 | C5: 5 | D5: getUpdatedHourlyYield, calcCumulativeYieldFP | F5: Magic numbers | G5: true, irrelevant | I5: In several places in the code, there are hardcoded values (like `FP32`, `1 hours`, `100`). These are often referred to as "magic numbers" and are generally discouraged because they can make code harder to understand and maintain. It would be better to declare these as named constants at the top of the contract.
A6: 3_3 | B6: 3 | C6: 2 | D6: calcCumulativeYieldFP | F6: Incorrect calculation order | G6: true, but precision loss | I6: The calculation `yieldAccumulator.accumulatorFP * yieldAccumulator.hourlyYieldFP * secondsDelta` in the function `calcCumulativeYieldFP` might lead to overflow due to incorrect order of calculations. The multiplication operation should be done after the division to avoid potential overflow.
A7: 3_3 | B7: 3 | C7: 5 | D7: calcCumulativeYieldFP | F7: Arithmetic Precision Loss | G7: false, already after | I7: In function calcCumulativeYieldFP, when calculating the accumulatorFP, the division is done before the multiplication. This can lead to precision loss, because in Solidity, division truncates the result. This could potentially lead to financial implications as this contract deals with financial calculations.
A8: 5_1 | B8: 5 | C8: 3 | D8: isPool | F8: Uninitialized variables | G8: false, irrelevant. inited by init() | I8: In the isPool function, the variable pool is not initialized which could lead to unpredictable behavior. If the condition inside the if statement does not hold true, the function would return an undefined value.
A9: 5_1 | B9: 5 | C9: 4 | D9: calcPart | F9: Incorrect use of require statement | G9: true, no risk | I9: The require statement in the function calcPart checks if the bp parameter is between 0 and 10000, inclusive. However, it is not required to check if bp is greater than or equal to 0 because the bp parameter is of type uint, which cannot be negative.
A10: 5_2 | B10: 5 | C10: 1 | D10: addLiquidity | F10: Uninitialized variable usage | G10: false, 0 by default | I10: The contract uses the uninitialized variable `_actualInputBase` within the `addLiquidity` function. This could potentially lead to incorrect calculations or unexpected behavior.
A11: 5_2 | B11: 5 | C11: 2 | D11: sync | F11: Incomplete function implementation | G11: false, already commented out | I11: In the `sync` function, there's an unfinished condition branch for `isSynth()`. This might cause unexpected behavior if this condition should be handled in a certain way. This can be considered an incomplete function implementation bug.
A12: 5_3 | B12: 5 | C12: 4 | D12: isBase, isPool | F12: Variable Shadowing | G12: false, irrelevant. returns by default | I12: In the 'isBase' and 'isPool' functions, the return variables 'base' and 'pool' are not explicitly set in all paths, leading to potential variable shadowing and unexpected return values.
A13: 5_3 | B13: 5 | C13: 7 | D13: init | F13: Uninitialized Storage Pointers** | G13: true, low risk | I13: The contract does not initialize its storage pointers (VADER, USDV, ROUTER, FACTORY) in its constructor but instead in the `init` function. This is a bad practice as it exposes the contract state to manipulation before the `init` function is called.
A14: 14_1 | B14: 14 | C14: 1 | D14: balanceOfToken | E14: BadgerYieldSource.sol | F14: Incorrect calculation order | G14: =FALSE() -> 0 | I14: The function `balanceOfToken` performs a multiplication followed by a division. Depending on the values of `balances[addr]`, `badgerSettBadgerBalance`, and `totalShares`, this order of operations might cause rounding errors or integer underflows. Ideally, the division should be performed first to ensure that the multiplication does not exceed the maximum uint256 value.
A15: 14_1 | B15: 14 | C15: 2 | D15: redeemToken | E15: BadgerYieldSource.sol | F15: Unexpected value | G15: false, already take care | I15: In the function `redeemToken`, the case when `totalShares` is zero is handled by returning zero. However, if `totalShares` is zero and `amount` is non-zero, it is possible that the user is expecting to redeem tokens but gets zero in return. This might be an unexpected behavior.
A16: 14_1 | B16: 14 | C16: 4 | D16: redeemToken | E16: BadgerYieldSource.sol | F16: Incorrect variable usage | G16: false, as intend | I16: In the `redeemToken` function, `balances[msg.sender]` is decreased by `requiredSharesBalance`, but it seems that it should be decreased by the redeemed `badgerBalanceDiff` instead, because `balances` map seems to track the user's balance in the underlying badger token, not in badgerSett shares.
A17: 14_1 | B17: 14 | C17: 5 | D17: supplyTokenTo | E17: BadgerYieldSource.sol | F17: Unexpected value | G17: true, low risk. return value | I17: The function `supplyTokenTo` does not handle the case where `badgerSett.deposit(amount)` might fail. If the `deposit` function were to fail, `balanceDiff` could be zero and the user's balance would not be updated, even though the badger tokens have already been transferred. This could lead to a loss of funds for the user.
A18: 14_1 | B18: 14 | C18: 1 | D18: _tokenToShares, _sharesToToken | E18: IYieldSource.sol | F18: Incorrect calculation order | G18: true, low risk | I18: In both `_tokenToShares` and `_sharesToToken` functions, there is multiplication before division. In these functions, you should be careful with the order of operations, as the current operation order can lead to loss of precision due to rounding down.
A19: 14_1 | B19: 14 | C19: 2 | D19: _depositToIdle | E19: IYieldSource.sol | F19: Unexpected value | G19: true, low risk. return value | I19: In the `_depositToIdle` function, there's no check for the return value of `mintIdleToken`. If `mintIdleToken` fails and returns zero, the function will still succeed, and the user's tokens will be stuck in this contract.
A20: 14_1 | B20: 14 | C20: 3 | D20: supplyTokenTo, redeemToken | E20: IYieldSource.sol | F20: Unexpected value | G20: false, msg.sender cannot be 0 | I20: In the `supplyTokenTo` and `redeemToken` functions, there's no check if the `to` address or `msg.sender` is the zero address. Transferring tokens to the zero address can lead to permanent loss of those tokens.
A21: 14_1 | B21: 14 | C21: 5 | D21: transferERC20 | E21: IYieldSource.sol | F21: Unexpected value | G21: true, low risk. input validation | I21: In the `transferERC20` function, there's a check that `erc20Token` is not `idleToken`, but there's no check if `erc20Token` is the zero address. If `erc20Token` is the zero address, this function will revert because `safeTransfer` to the zero address is likely to fail.
A22: 14_3 | B22: 14 | C22: 1 | D22: _tokenToShares | E22: IYieldSource.sol | F22: Incorrect calculation order | G22: false, as intend | I22: The function `_tokenToShares` performs multiplication before division which could lead to an overflow. It might be more accurate and safe to perform the division first.
A23: 14_3 | B23: 14 | C23: 2 | D23: _sharesToToken | E23: IYieldSource.sol | F23: Incorrect calculation order | G23: false, as intend | I23: Similar to `_tokenToShares`, the `_sharesToToken` function also does multiplication before division, which can potentially lead to overflow errors.
A24: 16_1 | B24: 16 | C24: 1 | D24: Various | E24: TracerPerpetualSwaps.sol | F24: Use of `require` for validating business logic | G24: false, already take care | I24: `require` is used throughout the contract to enforce business rules. While this is a common pattern in Solidity, it can lead to unexpected results if the conditions aren't met, since `require` will revert the entire transaction. This can make it difficult to identify and handle specific errors in a complex system. It might be worth considering a pattern that allows for more granular error handling.
A25: 16_1 | B25: 16 | C25: 4 | D25: Various | E25: TracerPerpetualSwaps.sol | F25: Lack of event emission | G25: true, but no need for internal function | I25: There are some state-changing functions that do not emit events. This can make it harder to track the state changes of the contract via events. An example could be the `_updateAccountLeverage` function which updates the leverage but does not emit an event.
A26: 16_1 | B26: 16 | C26: 1 | D26: latestAnswer | E26: GasOracle.sol | F26: Incorrect calculation order | G26: H-06 | H26: https://code4rena.com/reports/2021-06-tracer/#h-06-wrong-price-scale-for-gasoracle | I26: The gas price and ETH price fetched from Chainlink Oracle are not converted to have consistent decimals before multiplication. Therefore, the returned value may not be in USD/Gas * 10^18 if the decimals of these two oracles are not the same. To fix it, the contract could use the toWad function to convert them to a consistent decimal base before multiplication.
A27: 16_1 | B27: 16 | C27: 2 | D27: setDecimals | E27: GasOracle.sol | F27: Deviating Semantics | G27: false, no check function and no use | I27: The 'setDecimals' function allows the owner to set the 'decimals' variable without any restrictions. This can lead to inconsistency in calculations throughout the smart contract as other functions use the 'decimals' variable assuming it's 18.
A28: 16_1 | B28: 16 | C28: 3 | D28: setGasOracle, setPriceOracle | E28: GasOracle.sol | F28: Incorrect variable usage | G28: true, low risk. address check | I28: The setGasOracle and setPriceOracle functions are not validating if the input addresses are actual contract addresses. This could potentially allow for setting non-contract addresses as oracle addresses, which would lead to failure when trying to interact with these addresses as contracts.
A29: 16_1 | B29: 16 | C29: 4 | D29: toWad | E29: GasOracle.sol | F29: Unexpected value | G29: false, checked by solidity already | I29: The multiplication operation raw * scaler could potentially overflow if not handled correctly. An overflow check should be added for this operation to ensure the result fits in a uint256.
A30: 16_1 | B30: 16 | C30: 1 | D30: applyTrade | E30: LibBalances.sol | F30: Unexpected value | G30: true, checked by solidity already | I30: This function is performing mathematical operations that could potentially lead to overflow or underflow. However, since Solidity 0.8.0 (which this contract is using), arithmetic operations revert on underflow and overflow. Therefore, it is safe. But, it is still a good practice to check for overflows and underflows when working with older versions of Solidity.
A31: 16_1 | B31: 16 | C31: 2 | D31: marginIsValid | E31: LibBalances.sol | F31: Incorrect variable usage | G31: false, no need, mathlib takes care | I31: The function marginIsValid does not check if the provided position is valid. It only checks whether the calculated margin is less than 0 and whether the margin is greater than or equal to the minimum margin. However, it does not validate if the values in the position are within expected bounds.
A32: 16_1 | B32: 16 | C32: 3 | D32: margin | E32: LibBalances.sol | F32: Incorrect calculation order | G32: true, low risk | I32: The price is casted to an int256. If the price is higher than type(int256).max(), this will throw an exception. While this is a guard against an overflow, it also limits the maximum price that can be used. It's not necessarily a bug, but it is a limitation that should be well-documented.
A33: 16_1 | B33: 16 | C33: 4 | D33: tokenToWad, wadToToken | E33: LibBalances.sol | F33: Incorrect variable usage | G33: true, but take care in other files | I33: The functions tokenToWad and wadToToken assume that the provided 'tokenDecimals' are less than or equal to 'MAX_DECIMALS'. If 'tokenDecimals' is greater, these functions will not work correctly.
A34: 16_2 | B34: 16 | C34: 2 | D34: latestAnswer | E34: GasOracle.sol | F34: Unexpected value | G34: true, no use | I34: The function `latestAnswer` doesn't check if the `gasPrice` or `ethPrice` is zero before performing multiplication. This could potentially lead to an unexpected zero output if the oracles do not behave as expected.
A35: 16_2 | B35: 16 | C35: 3 | D35: toWad | E35: GasOracle.sol | F35: Deviating Semantics | G35: true, but as intend | I35: The `toWad` function expects the oracle to provide the correct decimal count. If the oracle behaves in a malicious or unexpected way, it could potentially break the contract logic. While you do check that `_decimals <= MAX_DECIMALS`, it would be better to also check that `_decimals` is not less than a reasonable minimum (e.g., 0).
A36: 16_2 | B36: 16 | C36: 1 | D36: minimumMargin | E36: LibBalances.sol | F36: Unexpected value | G36: L-08 | H36: https://code4rena.com/reports/2021-06-tracer/#l-08-potential-division-by-zero | I36: The function `minimumMargin` doesn't check if `maximumLeverage` is zero before performing division. This could potentially lead to a division by zero error if `maximumLeverage` is not properly validated.
A37: 16_2 | B37: 16 | C37: 2 | D37: wadToToken | E37: LibBalances.sol | F37: Incorrect calculation order | G37: false, not correct explan | I37: The function `wadToToken` performs division before multiplication. If `wadAmount` is less than `scaler`, it will return 0 due to the integer division. It might be better to perform multiplication first to maintain precision and then perform division.
A38: 17_3 | B38: 17 | C38: 1 | D38: _updateRatios | E38: Buoy3Pool.sol | F38: Incorrect calculation order | G38: L-03 | H38: https://code4rena.com/reports/2021-06-gro/#l-03-buoy3pool_updateratios-unsafe-math | I38: In the `_updateRatios` function, the `tolerance` argument is compared against the result of calculations involving `check` variable. However, `check` is calculated by subtracting `_ratio` from `chainRatios[i].div(CHAIN_FACTOR)`. This can potentially lead to an underflow if `_ratio` is greater than `chainRatios[i].div(CHAIN_FACTOR)`. To fix this, it would be advisable to ensure `_ratio` is always less than or equal to `chainRatios[i].div(CHAIN_FACTOR)`.
A39: 17_3 | B39: 17 | C39: 2 | D39: setBasisPointsLmit | E39: Buoy3Pool.sol | F39: Incorrect variable usage | G39: true, no risk | I39: The function name `setBasisPointsLmit` appears to be a typo. It should be `setBasisPointsLimit`.
A40: 17_3 | B40: 17 | C40: 3 | D40: stableToUsd | E40: Buoy3Pool.sol | F40: Unexpected value | G40: false, internal function relies on call | I40: The `stableToUsd` function calculates LP amount by calling `curvePool.calc_token_amount(_tokenAmounts, deposit)`, but there's no guarantee that the `deposit` variable will always be `true` when it should be for deposit operations. Incorrect value for `deposit` variable can lead to unexpected results.
A41: 17_3 | B41: 17 | C41: 4 | D41: poolBalances | E41: Buoy3Pool.sol | F41: Incorrect variable usage | G41: true, no risk | I41: In the `poolBalances` function, the `_balances` array is returned as `balances`. This is unnecessary and potentially confusing. The function should just return `_balances` directly.
A42: 25_1 | B42: 25 | C42: 1 | D42: peek, get | E42: CTokenMultiOracle.sol | F42: Arithmetic Precision Loss | G42: false, as intend | I42: In the `peek` and `get` functions, the value is calculated as `value = price * amount / 1e18;`. This may lead to precision loss due to integer division, especially if `price * amount` is less than `1e18`. It would be more accurate to perform the division first and then multiply by `amount`.
A43: 25_1 | B43: 25 | C43: 2 | D43: _updateUserRewards | E43: ERC20Rewards.sol | F43: Potential loss of rewards | G43: true, as intend | I43: In the _updateUserRewards function, when the new value for userRewards_.accumulated is calculated, the division by 1e18 could potentially result in a loss of rewards due to the truncation of decimal places.
A44: 25_1 | B44: 25 | C44: 3 | D44: setRewards | E44: ERC20Rewards.sol | F44: Incorrect timestamp comparison | G44: true, low risk. timestamp | I44: In the setRewards function, there are checks to ensure that a new rewards program can be set only if one is not currently running. However, these checks compare the current block timestamp (in seconds since Unix epoch) with the start and end times of the reward period, which are stored as uint32 values. Given that the current Unix timestamp has already exceeded the maximum value that can be stored in a uint32, these checks will always fail, preventing a new rewards program from being set.
A45: 29_3 | B45: 29 | C45: 6 | D45: various | F45: Use of magic numbers | G45: true, no risk | I45: There are several instances where "magic numbers" are used (like 0xf7888aec, 0x97da6d30, 0xf18d03cc). These values should be replaced with named constants for better code readability and maintainability.
A46: 30_3 | B46: 30 | C46: 3 | D46: withdraw | E46: Vault.sol | F46: Insufficient withdrawal amount check | G46: false, cannot be negative | I46: The withdrawal amount after subtracting the fee is not checked if it's still positive. In case of very high fees, the actual withdrawal amount might be very small or even negative.
A47: 30_3 | B47: 30 | C47: 1 | D47: setCap | E47: Controller.sol | F47: Incorrect calculation order | G47: true, low risk | I47: The function setCap first sets the new cap for the strategy, then withdraws the amount in excess of the new cap. However, it doesn't take into account the possibility that the withdrawal operation might fail, which would result in an incorrect cap being set. Ideally, it should perform the withdrawal first, then set the new cap only if the withdrawal was successful.
A48: 30_3 | B48: 30 | C48: 2 | D48: removeStrategy | E48: Controller.sol | F48: Unexpected value | G48: false, library reverts if underflow | I48: The function removeStrategy removes a strategy from a vault, and it uses the 'sub' function from the SafeMath library to adjust array indexes. However, it does not account for the scenario where the 'index' variable might be zero. If 'index' is zero, 'sub(1)' would underflow and produce an unexpected value. This could result in an incorrect array index being accessed, leading to potential errors or exploits.
A49: 30_3 | B49: 30 | C49: 3 | D49: withdraw | E49: Controller.sol | F49: Deviating Semantics | G49: false, as intend | I49: In the withdraw function, the 'safeTransfer' method is used to transfer tokens from the contract to the caller. However, the amount to be transferred is calculated after the withdrawal operations have been performed. This could lead to a situation where the actual balance of the contract is less than the calculated withdrawal amount, resulting in a failed transfer. This is inconsistent with the typical expectation that a withdrawal should only be possible if there are enough funds in the contract.
A50: 31_2 | B50: 31 | C50: 1 | D50: balanceOfPool() | E50: veCVXStrategy.sol | F50: Incorrect calculation order | G50: false, already before | I50: In the balanceOfPool() function, the value of bCVXToCVX is retrieved and checked for its value after it is used to calculate valueInLocker. If bCVXToCVX is less than or equal to 10**18, the function reverts with "Loss Of Peg". This check should be performed before the calculation is made to ensure that the peg has not been lost and to prevent unnecessary calculations if it has.
A51: 31_2 | B51: 31 | C51: 2 | D51: _withdrawSome() | E51: veCVXStrategy.sol | F51: Incorrect variable usage | G51: false, as intend | I51: In the _withdrawSome() function, it requires that max is greater than or equal to _amount multiplied by 9_980 divided by MAX_BPS. However, the variable "max" is set to the balance of the "want" token in the contract's address, and it may not be the correct amount for this check. This could potentially lead to incorrect calculations and potentially unwanted behavior.
A52: 31_2 | B52: 31 | C52: 3 | D52: manualRebalance() | E52: veCVXStrategy.sol | F52: Unexpected value | G52: false, as intend | I52: In the manualRebalance() function, if the newLockRatio is less than or equal to the currentLockRatio, the function will deposit all CVX into the vault without considering the toWantRatio. This may lead to more tokens being locked than expected, thus not respecting the desired balance defined by the toLock parameter.
A53: 31_2 | B53: 31 | C53: 4 | D53: _deposit() | E53: veCVXStrategy.sol | F53: Incorrect variable usage | G53: false, as intend | I53: In the _deposit() function, the contract calls the function CVX_VAULT.withdraw() with the amount intended to be deposited. This seems to be a mistake and it should be CVX_VAULT.deposit() instead.
A54: 31_3 | B54: 31 | C54: 1 | D54: harvest | E54: veCVXStrategy.sol | F54: Incorrect variable usage | G54: false, as intend | I54: The `harvest` function processes rewards, but the method `_processRewardsFees` receives `earnedReward` as a parameter which is the balance of the `reward` token after getting rewards from the `LOCKER`. The function `_processRewardsFees` processes the fee on this amount and sends the fees to the governance and the strategist. But, the reward is not converted to `want` token before processing fees. The fees should be processed on the `want` token instead of the `reward` token.
A55: 31_3 | B55: 31 | C55: 2 | D55: _withdrawSome | E55: veCVXStrategy.sol | F55: Incorrect calculation order | G55: false, as intend | I55: The `_withdrawSome` function requires that the amount to withdraw is not more than 99.8% of the current balance (`max >= _amount.mul(9_980).div(MAX_BPS)`). This can result in a miscalculation in cases where the `_amount` is very high, and `max` is low. This is because multiplying `_amount` by `9_980` can overflow if `_amount` is very large. This could be prevented by first dividing `_amount` by `MAX_BPS` and then multiplying the result by `9_980`.
A56: 31_3 | B56: 31 | C56: 3 | D56: manualRebalance | E56: veCVXStrategy.sol | F56: Unexpected value | G56: false, nonsense | I56: In the `manualRebalance` function, `toLock` is passed as a parameter, which is then directly used to calculate `newLockRatio`. The contract has a `MAX_BPS` constant which is `10_000`, and `toLock` is required to be less than or equal to `MAX_BPS`. But, it is not checked whether `toLock` is a valid value within the required range (0 to `MAX_BPS`). This could potentially lead to unexpected behavior if `toLock` is a negative value or an excessively large value.
A57: 39_1 | B57: 39 | C57: 1 | D57: initiateVaultFillingZcTokenInitiate, initiateZcTokenFillingVaultInitiate, initiateZcTokenFillingZcTokenExit, initiateVaultFillingVaultExit, exitZcTokenFillingZcTokenInitiate, exitVaultFillingVaultInitiate, exitVaultFillingZcTokenExit, exitZcTokenFillingVaultExit | E57: Swivel.sol | F57: Incorrect calculation order | G57: true, low risk | I57: In these functions, the filled volume of the order is being updated before any of the token transfers and minting operations have been confirmed to have succeeded. It's recommended that state variables like `filled[hash]` be updated only after all external function calls (like `transferFrom`, `mint`, etc.) have been successfully completed to avoid reentrancy attacks.
... A63: 44_3 | B63: 44 | C63: 2 | D63: swapByQuote | E63: Swap.sol | F63: Unexpected value | G63: true, no risk | I63: The function swapByQuote uses the msg.value to determine if the operation involves Ether. If the operation is supposed to involve Ether but msg.value is 0, the function reverts. However, it may be more appropriate to check if msg.value is equal to the amount that is supposed to be sent. If the two values do not match, the function should revert.
A64: 45_1 | B64: 45 | C64: 1 | D64: getLockedAmount | E64: CreditLimitByMedian.sol | F64: Unexpected value | G64: H-02 | H64: https://code4rena.com/reports/2021-10-union/#h-02-wrong-implementation-of-creditlimitbymediansolgetlockedamount-makes-it-unable-to-unlock-lockedamount-in-creditlimitbymedian-model | I64: In the getLockedAmount function, when 'isIncrease' is set to false, the 'newLockedAmount' is being set to 'array[i].lockedAmount - 1' if 'array[i].lockedAmount' is greater than 'amount'. This might lead to unexpected values of 'newLockedAmount' as it decreases the 'lockedAmount' by 1 instead of 'amount'. It seems like a potential mistake in the code logic as it deviates from the expected behavior of reducing the 'lockedAmount' by 'amount'.
A65: 45_1 | B65: 45 | C65: 2 | D65: _findMedian | E65: CreditLimitByMedian.sol | F65: Incorrect calculation order | G65: true, low risk | I65: In the _findMedian function, the median is calculated as an average of two middle numbers when the array length is even. This could lead to incorrect results if those two numbers are large enough that their sum exceeds the maximum value of uint256 (2^256 - 1). A better way to avoid overflow would be to calculate the average by adding half of each number `(num1 / 2) + (num2 / 2)` and add 1 if num1 and num2 are both odd to account for the division truncation.
A66: 45_2 | B66: 45 | C66: 3 | D66: getLockedAmount | E66: CreditLimitByMedian.sol | F66: Use of Magic Numbers | G66: true, no risk | I66: The function `getLockedAmount` has a magic number 1 in the expression `newLockedAmount = array[i].lockedAmount - 1`. This could lead to confusion and potential errors in the future. It's generally good practice to define such numbers as constants with descriptive names.
A67: 45_2 | B67: 45 | C67: 4 | D67: getCreditLimit | E67: CreditLimitByMedian.sol | F67: Inefficient Storage Pattern | G67: true, no risk | I67: The `getCreditLimit` function returns a median value based on an array of values passed as a parameter. If this data is frequently used, it may be more efficient to store it in a state variable to avoid calculating the median repeatedly.
A68: 47_1 | B68: 47 | C68: 1 | D68: transferFrom, transfer | E68: WrappedIbbtc.sol WrappedIbbtcEth.sol | F68: Erroneous Accounting | G68: true, low risk | I68: The functions `transferFrom` and `transfer` use a function called `balanceToShares` to convert the `amount` into `amountInShares`. This function uses the `pricePerShare` from an oracle, which could lead to erroneous accounting if the oracle provides incorrect or manipulated data.
A69: 47_1 | B69: 47 | C69: 2 | D69: balanceOf, totalSupply | F69: Erroneous Accounting | G69: true, low risk | I69: The functions `balanceOf` and `totalSupply` also use the `pricePerShare` from an oracle to calculate the balance or total supply. Again, this could lead to erroneous accounting if the oracle provides incorrect or manipulated data.
A70: 47_1 | B70: 47 | C70: 3 | D70: mint, burn | F70: Incorrect calculation order | G70: false, atomic | I70: In the `mint` and `burn` functions, the transfer of tokens and the minting or burning of shares are not atomic, meaning they are not executed in one transaction. If the transaction fails halfway, it could lead to an inconsistent state of the contract.
A71: 47_1 | B71: 47 | C71: 6 | D71: updatePricePerShare | F71: Possible Stale Data | G71: H-03 | H71: https://code4rena.com/reports/2021-10-badgerdao/#h-03-wrappedibbtceth-contract-will-use-stalled-price-for-mintburn-if-updatepricepershare-wasnt-run-properly | I71: The `updatePricePerShare` function is permissionless, and anyone can call it to update the `pricePerShare`. However, the contract does not enforce the frequency of updates, which could lead to stale data if not updated regularly.
A72: 47_2 | B72: 47 | C72: 5 | D72: balanceToShares, sharesToBalance | F72: Incorrect calculation order | G72: true, no risk | I72: The functions `balanceToShares` and `sharesToBalance` use a magic number `1e18`. It would be better to define this value as a constant at the beginning of the contract to improve readability and maintainability.
A73: 47_3 | B73: 47 | C73: 3 | D73: mint, burn | F73: Lack of event after state-changing action | G73: true, no risk | I73: After changing the contract's state in the "mint" and "burn" functions, there is no event emitted. This can make it harder to track contract interactions and state changes.
A74: 49_2 | B74: 49 | C74: 3 | D74: Constructor | E74: OverlayV1UniswapV3Market.sol | F74: Potential Uninitialized Storage Reference | G74: true, low risk | I74: The constructor is calling four other contracts or libraries via their constructors. If any of these contracts fail to initialize properly, the state of the OverlayV1UniswapV3Market contract could be unpredictable or incorrect.
A75: 49_3 | B75: 49 | C75: 1 | D75: computeDepth | E75: OverlayV1UniswapV4Market.sol | F75: Arithmetic Precision Loss | G75: true, as intend | I75: In the `computeDepth` function, there is a risk of precision loss when dividing `_marketLiquidity * 1e18` by `_ovlPrice`. Solidity performs integer division, where the fractional part is discarded. This could result in a lower than expected `depth_` value, especially if `_ovlPrice` is significantly larger than `_marketLiquidity`.
A76: 49_3 | B76: 49 | C76: 3 | D76: fetchPricePoint | E76: OverlayV1UniswapV5Market.sol | F76: Potential Revert due to Casting | G76: true, low risk | I76: In the `fetchPricePoint` function, casting a `uint32` to `int32` and then again to `int56` might cause the function to revert if the original `uint32` value is larger than the maximum value an `int32` can hold.
A77: 52_1 | B77: 52 | C77: 1 | D77: calculateLoss | E77: VaderMath.sol | F77: Incorrect calculation order | G77: true, as intend | I77: In the function calculateLoss, you have two instances of an operation of the form `(A * B) / C`. Due to the nature of integer division in Solidity, this might not yield the expected results. Specifically, if `(A * B) < C`, the result of the operation will be `0`. The correct order of operations to ensure the right precedence and to avoid the rounding down to 0 before the multiplication should be `(A * B) / C` should be changed to `A * (B / C)`, given that `B / C` would not result in a fraction.
A78: 52_1 | B78: 52 | C78: 1 | D78: addLiquidity | E78: VaderRouter.sol | F78: Function Overloading Error | G78: false, different params | I78: There are two functions named `addLiquidity` with the same parameters which could cause confusion and unexpected behavior. The first `addLiquidity` function calls the second `addLiquidity` function with the exact same arguments it received, leading to a recursive call without a base case. This can cause a stack overflow error (out of gas exception).
A79: 52_1 | B79: 52 | C79: 2 | D79: _addLiquidity | E79: VaderRouter.sol | F79: Incomplete Code/Logic Error | G79: false, already take care | I79: The `_addLiquidity` function doesn't account for the scenario when a pool already exists for the provided token pair. In this case, it should determine the amountA and amountB based on the existing pool's reserves and the desired amounts. Currently, it just sets amountA and amountB equal to the desired amounts without considering the existing state of the pool.
A80: 52_1 | B80: 52 | C80: 1 | D80: vaderToUsdv | E80: TwapOracle.sol | F80: Incorrect calculation order | G80: false, no need. | I80: If `_usdvEnabled` is `false`, `vaderAmount` is directly multiplied with the return value from `consult(VADER)`. However, considering the difference in decimal places between VADER and the native token, this calculation might need to be adjusted. The return value from `consult(VADER)` should probably be multiplied by `vaderAmount` and then divided by `10**decimals` to account for the decimal difference.
A81: 52_1 | B81: 52 | C81: 2 | D81: consult | E81: TwapOracle.sol | F81: Unexpected value | G81: false, no risk | I81: The calculation `uint256(price) * (10**10)` assumes that the Chainlink price feed returns a price with 8 decimal places. This might not be the case for all price feeds. You should confirm the number of decimal places for the specific Chainlink price feed you're using.
A82: 52_1 | B82: 52 | C82: 3 | D82: registerPair | E82: TwapOracle.sol | F82: Incorrect variable usage | G82: false, as intend | I82: When `token0` is not `VADER`, the pair address is set to the `_vaderPool` address. However, the `_vaderPool` is not necessarily the correct pair for `token0` and `token1`. This may lead to incorrect reserves and prices being used for this pair.
A83: 52_2 | B83: 52 | C83: 4 | D83: swap | E83: BasePoolV2.sol | F83: Unexpected value | G83: false, already take care. error understanding | I83: In the `swap` function, it's expected that either `nativeAmountIn` or `foreignAmountIn` should be greater than zero, but not both. However, if both are greater than zero, there is no check or error message for this case, which can lead to unexpected behavior.
A84: 52_2 | B84: 52 | C84: 5 | D84: rescue | E84: BasePoolV2.sol | F84: Unexpected value | G84: M-21 | H84: https://code4rena.com/reports/2021-11-vader/#m-21-vaderpoolv2rescue-results-in-loss-of-funds-rather-than-recoverability | I84: In the `rescue` function, the smart contract transfers tokens to `msg.sender`, which can be any address. This could be a potential security risk if an unexpected address calls this function.
A85: 52_2 | B85: 52 | C85: 6 | D85: mint | E85: BasePoolV2.sol | F85: Unchecked Math | G85: false, already take care by solidity | I85: In the `mint` function, there is unchecked addition `totalLiquidityUnits + liquidity`. If the sum of these two values exceeds the maximum uint256 value, it will cause an overflow.
A86: 52_2 | B86: 52 | C86: 1 | D86: burnFungible | E86: VaderPoolV2.sol | F86: Incorrect SafeMath Operation | G86: false, already take care by solidity | I86: In the 'burnFungible' function, there is a subtraction operation in 'pair.totalSupply = _totalSupply - liquidity;' without using SafeMath which can lead to underflow if '_totalSupply' is less than 'liquidity'.
A87: 52_2 | B87: 52 | C87: 2 | D87: _update | E87: VaderPoolV2.sol | F87: Incorrect SafeMath Operation | G87: false, already take care by solidity | I87: The function '_update' is being called with operations like addition and subtraction of 'reserveNative' and 'reserveForeign' with 'nativeDeposit' and 'foreignDeposit' respectively, without using SafeMath, which can lead to underflow or overflow.
A88: 52_2 | B88: 52 | C88: 3 | D88: mintSynth | E88: VaderPoolV2.sol | F88: Incorrect SafeMath Operation | G88: false, already take care by solidity | I88: In the 'mintSynth' function, there's an addition operation in '_update' call without using SafeMath which can lead to overflow if 'reserveNative' and 'nativeDeposit' are large enough.
A89: 52_2 | B89: 52 | C89: 4 | D89: mintFungible | E89: VaderPoolV2.sol | F89: Incorrect SafeMath Operation | G89: false, already take care by solidity | I89: In the 'mintFungible' function, there are addition operations in '_update' call and 'pair.totalSupply = totalLiquidityUnits + liquidity;' without using SafeMath which can lead to overflow if the operands are large enough.
A90: 52_2 | B90: 52 | C90: 5 | D90: burn | E90: VaderPoolV2.sol | F90: Incorrect variable usage | G90: false, take care in other files | I90: In the 'burn' function, there is a use of '_ONE_YEAR' variable which is not defined anywhere in the contract. It might lead to compilation error.
A91: 52_3 | B91: 52 | C91: 6 | D91: root | E91: VaderMath.sol | F91: Unhandled edge case | G91: true, as intend | I91: This function calculates the square root of a number using the Babylonian method. However, if the input is 2 or 3, it will return 1 which is not the correct square root. This could potentially lead to incorrect calculations in other functions that use the root function.
A92: 52_3 | B92: 52 | C92: 7 | D92: calculateLiquidityUnits | E92: VaderMath.sol | F92: Incorrect calculation order | G92: false, as intend | I92: The function performs multiplication before division which can lead to loss of precision due to integer division. The operation `totalPoolUnits * poolUnitFactor` should be performed after the division by `denominator` to minimize precision loss.
A93: 52_3 | B93: 52 | C93: 2 | D93: removeLiquidity | E93: VaderRouter.sol | F93: Uninitialized Contract | G93: true, no risk | I93: In the `removeLiquidity` function, the `reserve.reimburseImpermanentLoss` function is called, but the `reserve` variable is not initialized in the constructor and can only be initialized via the `initialize` function. If `removeLiquidity` is called before `initialize`, this will lead to a function call on a zero-address contract, causing a failure.
A94: 58_2 | B94: 58 | C94: 2 | D94: withdraw | E94: LpIssuerGovernance.sol LpIssuer.sol | F94: Incorrect calculation order | G94: false, checked already. | I94: In the "withdraw" function, there's a possibility that the total supply could be zero, causing a division by zero error when calculating tokenAmounts[i]. This could be mitigated by checking if the total supply is greater than zero before performing the division.
A95: 58_2 | B95: 58 | C95: 3 | D95: _chargeFees | E95: LpIssuer.sol | F95: Incorrect variable usage | G95: M-03 | H95: https://code4rena.com/reports/2021-12-mellow/#m-03-users-can-avoid-paying-vault-fees | I95: In the "_chargeFees" function, the elapsed time is calculated by subtracting lastFeeCharge from the current block timestamp. However, if this function is called before any fee has been charged, lastFeeCharge would be zero, causing the elapsed time to be incorrectly calculated as the current timestamp. This could lead to incorrect fee charges.
A96: 59_1 | B96: 59 | C96: 2 | D96: exitEarly | E96: AuctionEscapeHatch.sol | F96: Incorrect calculation order | G96: false, already before | I96: This function is not checking if the `amountOut` is greater than `minOut` before updating the `auctionExits`. In case the `amountOut` is less than `minOut`, the function will revert but not before updating the `auctionExits`. To correct this, the `require(amountOut > minOut, "EarlyExit Insufficient output");` statement should be moved up before the `auctionExits` are updated.
A97: 59_1 | B97: 59 | C97: 3 | D97: _calculateMaltRequiredForExit | E97: AuctionEscapeHatch.sol | F97: Incorrect variable usage | G97: false, as intend | I97: In this function, the calculation of `amount` is based on the `userCommitment` and `userRedeemed`. However, these values are not updated in the function. If `amount` is greater than `userCommitment - userRedeemed`, `amount` is set to `userCommitment - userRedeemed`. This may not be the desired behavior as it could lead to an erroneous calculation of `amount`. Consider updating `userCommitment` and `userRedeemed` before calculating `amount`.
A98: 59_1 | B98: 59 | C98: 4 | D98: earlyExitReturn | E98: AuctionEscapeHatch.sol | F98: Incorrect calculation order | G98: false, as intend | I98: In the function `earlyExitReturn`, the calculation for `maxProfit` is done with the formula `(fullReturn - amount) * (maxEarlyExitBps * progressionBps / 10000) / 1000`. The multiplication and division operations are not in parentheses which could lead to incorrect calculation due to operator precedence. You should consider using parentheses to ensure the correct order of operations. The correct expression should be `((fullReturn - amount) * (maxEarlyExitBps * progressionBps)) / (10000 * 1000)`.
A99: 59_2 | B99: 59 | C99: 1 | D99: consult() | E99: AuctionBurnReserveSkew.sol | F99: Arithmetic Precision Loss | G99: true, as intend | I99: The skew calculation `(frequency + (participation * 2)) / 3;` suffers from precision loss due to integer division. This could lead to slightly inaccurate results.
A100: 59_2 | B100: 59 | C100: 1 | D100: exitEarly | E100: AuctionEscapeHatch.sol | F100: Unexpected value | G100: false, no need | I100: In the `exitEarly` function, there is a lack of validation for the `amount` input. This could potentially lead to negative values, or values that are too high, being used in the function. A require statement should be added to ensure that the `amount` is greater than 0 and less than or equal to the user's balance.
A101: 59_2 | B101: 59 | C101: 3 | D101: _calculateMaltRequiredForExit | E101: AuctionEscapeHatch.sol | F101: Incorrect calculation order | G101: true, already take care in other files | I101: The same potential for underflow exists in the `_calculateMaltRequiredForExit` function as well, with the line `if (amount > (userCommitment - userRedeemed))`. It should be checked that `userRedeemed` is not larger than `userCommitment` before this calculation.
A102: 59_2 | B102: 59 | C102: 4 | D102: setEarlyExitBps | E102: AuctionEscapeHatch.sol | F102: Incorrect variable usage | G102: false, already take care | I102: In the function `setEarlyExitBps`, the requirement checks if `_earlyExitBps` is greater than 0 and less than or equal to 1000, but the comment above says it should be between 0-100%. It looks like a mismatch between the comment and the actual code. The comment should be updated to reflect the actual requirement or vice versa.
